Workbook

Sheet METHODES_PERFUSION
A1: Méthodes de perfusion — paramètres généraux
A2: Base de paramètres lue par le logiciel. Les scénarios ne sont pas saisis ici : ils seront générés dynamiquement par le moteur inversé.
A3: methode_id | B3: libelle | C3: mode | D3: volume_ml | E3: duree_h_defaut | F3: location_jour | G3: dm_captif | H3: dm_unique | I3: passages_ide_par_jour_defaut | J3: frequences_possibles | K3: contexte_defaut | L3: commentaire
A4: POCHE_VOL_CONT | B4: Poche en pompe volumétrique classique | C4: continu | D4: variable | E4: 24 | F4: non | G4: non | H4: oui | I4: 1 | J4: q24/q12/q8/q6 | K4: HOSPITALIER | L4: Intra-hospitalier uniquement dans le modèle ; volume selon moteur.
A5: PSE_48_CONT | B5: PSE 48 mL | C5: continu | D5: 48 | E5: variable | F5: non | G5: non | H5: oui | I5: variable | J5: q24/q12/q8/q6 | K5: HOSPITALIER | L5: PSE 48 mL intra-hospitalier ; changement selon stabilité.
A6: PSE_24_HAD_CONT | B6: PSE HAD 24 mL | C6: continu | D6: 24 | E6: variable | F6: oui | G6: non | H6: oui | I6: variable | J6: q24/q12/q8/q6 | K6: HAD | L6: Pousse-seringue électrique HAD ; location par jour ; concentration calculée sur 24 mL.
A7: RYTHMIC_CONT | B7: Pompe Rythmic / Micrel | C7: continu | D7: 100 ou 200 | E7: 24 | F7: oui | G7: oui | H7: non | I7: 1 | J7: q24/q12 | K7: HAD | L7: HAD uniquement ; location par jour + DM captif.
A8: ANAPA_CONT | B8: ANAPA | C8: continu | D8: 250 | E8: 12 | F8: non | G8: non | H8: oui | I8: 2 | J8: q12 | K8: HOSPITALIER/HAD | L8: DM unique. | ACV/poids diffuseur unifies (0,3 kgCO2e / 43 g).
A9: NEOPUMP_CONT | B9: NEOPUMP | C9: continu | D9: 500 | E9: 12 ou 24 | F9: non | G9: non | H9: oui | I9: 1 ou 2 | J9: q24/q12 | K9: HOSPITALIER/HAD | L9: DM unique. | ACV/poids diffuseur unifies (0,3 kgCO2e / 43 g).
A10: POCHE_DISCONT | B10: Poche classique discontinue | C10: discontinu | D10: variable | E10: administration courte | F10: non | G10: non | H10: oui | I10: nb administrations/j | J10: x1 à x6/j | K10: HOSPITALIER/HAD | L10: Discontinu : poche classique uniquement.
A11: ELASTOMERE_GENERIC | B11: Diffuseur élastomère générique | C11: continu | D11: 100/150/250/500 | E11: 12 ou 24 | F11: non | G11: non | H11: oui | I11: 1 ou 2 | J11: q24/q12 | K11: HOSPITALIER/HAD | L11: Proxy coût/CO₂ : diffuseur élastomère générique assimilé à NEOPUMP 250/500 mL selon volume, à remplacer par données fournisseur si disponibles. | ACV/poids diffuseur unifies (0,3 kgCO2e / 43 g).

Sheet MATERIEL_PAR_METHODE
A1: Matériel par méthode — panier de consommables
A2: Chaque ligne représente un item consommé par administration/perfusion. Le moteur multiplie par le nombre réel de perfusions/changements par jour.
A3: methode_id | B3: item_id | C3: item_libelle | D3: categorie | E3: quantite_par_perfusion | F3: inclus_dans_dm_captif | G3: a_compter | H3: commentaire
A4: POCHE_VOL_CONT | B4: POCHE_NACL_G5_VARIABLE | C4: Poche NaCl/G5 volume selon moteur | D4: contenant/solvant final | E4: 1 | F4: non | G4: oui | H4: Continu : poche en pompe volumétrique classique ; le moteur choisit le plus petit volume compatible par solvant.
A5: POCHE_VOL_CONT | B5: TUBULURE_POMPE_VOL | C5: Tubulure pompe volumétrique | D5: administration | E5: 1 | F5: non | G5: oui | H5: Tubulure spécifique pompe volumétrique.
A6: POCHE_VOL_CONT | B6: PROLONGATEUR_STANDARD | C6: Prolongateur standard | D6: administration | E6: 1 | F6: non | G6: à confirmer | H6: Selon montage local ; inclus si paramètre inclure_items_a_confirmer = 1.
A7: POCHE_VOL_CONT | B7: RINCAGE_NACL_10ML | C7: Rinçage NaCl 10 mL | D7: rinçage | E7: 1 | F7: non | G7: oui | H7: Avant/après selon protocole.
A8: POCHE_VOL_CONT | B8: ETIQUETTE | C8: Étiquette préparation | D8: traçabilité | E8: 1 | F8: non | G8: oui | H8: Par administration préparée.
A9: PSE_48_CONT | B9: SERINGUE_PP_50ML | C9: Seringue PP 50 mL | D9: contenant | E9: 1 | F9: non | G9: oui | H9: PSE 48 mL intra-hospitalier.
A10: PSE_48_CONT | B10: POCHE_NACL_G5_VARIABLE | C10: Poche NaCl/G5 pour dilution/remplissage | D10: solvant final | E10: 1 | F10: non | G10: oui | H10: Le moteur choisit la plus petite poche possible compatible avec la concentration.
A11: PSE_48_CONT | B11: PROLONGATEUR_PSE | C11: Prolongateur PSE | D11: administration | E11: 1 | F11: non | G11: oui | H11: Tubulure/prolongateur spécifique PSE.
A12: PSE_48_CONT | B12: RINCAGE_NACL_10ML | C12: Rinçage NaCl 10 mL | D12: rinçage | E12: 1 | F12: non | G12: oui | H12: Par changement de seringue.
A13: PSE_48_CONT | B13: ETIQUETTE | C13: Étiquette préparation | D13: traçabilité | E13: 1 | F13: non | G13: oui | H13: Par seringue préparée.
A14: PSE_24_HAD_CONT | B14: SERINGUE_PP_24ML | C14: Seringue PP 24 mL | D14: contenant | E14: 1 | F14: non | G14: oui | H14: PSE HAD 24 mL ; continu en HAD uniquement.
A15: PSE_24_HAD_CONT | B15: POCHE_NACL_G5_VARIABLE | C15: Poche NaCl/G5 pour dilution/remplissage | D15: solvant final | E15: 1 | F15: non | G15: oui | H15: Le moteur choisit la plus petite poche possible compatible avec la concentration.
... A40: ELASTOMERE_GENERIC | B40: ETIQUETTE | C40: Étiquette préparation | D40: traçabilité | E40: 1 | F40: non | G40: oui | H40: Par dispositif préparé.

Sheet FACTEURS_ITEMS
A1: Facteurs coût et CO₂ des consommables
A2: Compléter les coûts unitaires, kgCO₂e unitaires et poids. Ces valeurs seront utilisées pour calculer coût/CO₂ par jour et par traitement.
A3: item_id | B3: item_libelle | C3: cout_unitaire_eur | D3: kgco2e_unitaire | E3: poids_g | F3: type_dechet | G3: source_cout | H3: source_co2 | I3: niveau_incertitude | J3: commentaire
A4: POCHE_NACL_G5_50ML | B4: Poche NaCl/G5 50 mL | C4: =0.5*1.02 -> 0.51 | D4: 0.201 | E4: 8 | F4: DASRI | G4: Copilote | H4: Carebone / LLM | I4: moyen
A5: POCHE_NACL_G5_100ML | B5: Poche NaCl/G5 100 mL | C5: =0.53*1.02 -> 0.5406 | D5: 0.278 | E5: 10 | F5: DASRI | G5: Copilote | H5: Carebone / LLM | I5: moyen
A6: POCHE_NACL_G5_250ML | B6: Poche NaCl/G5 250 mL | C6: =0.697*1.021 -> 0.711637 | D6: 0.507 | E6: 14 | F6: DASRI | G6: Copilote | H6: Carebone / LLM | I6: moyen
A7: POCHE_NACL_G5_500ML | B7: Poche NaCl/G5 500 mL | C7: =0.714*1.021 -> 0.728994 | D7: 0.889 | E7: 20 | F7: DASRI | G7: Copilote | H7: Carebone / LLM | I7: moyen
A8: SERINGUE_PP_24ML | B8: Seringue PP 24 mL | C8: =0.176*1.2 -> 0.2112 | D8: 0.069 | E8: 12 | F8: DASRI | G8: Copilote | H8: Carebone / LLM | I8: moyen | J8: Utilisée aussi comme proxy de seringue de reconstitution par défaut dans l'onglet ACV ATB ; à adapter si seringue 10/20 mL réelle.
A9: SERINGUE_PP_50ML | B9: Seringue PP 50 mL | C9: =0.8435*1.2 -> 1.0122 | D9: 0.136 | E9: 18 | F9: DASRI | G9: Copilote | H9: Carebone / LLM | I9: moyen
A10: TUBULURE_POMPE_VOL | B10: Tubulure pompe volumétrique | C10: =9.8*1.2 -> 11.76 | D10: 0.241 | E10: 55 | F10: DASRI | G10: Copilote | H10: Carebone / LLM | I10: élevé | J10: Poste ACV dominant (0,241 kgCO₂e/changement). Source LLM — à revalider en priorité auprès du fournisseur ou via ACV de référence plastique médical.
A11: PROLONGATEUR_STANDARD | B11: Prolongateur standard | C11: =0.3926*1.2 -> 0.47112 | D11: 0.079 | E11: 8 | F11: DASRI | G11: Copilote | H11: Carebone / LLM | I11: élevé | J11: Source LLM. À revalider fournisseur. Faible poids (8 g) donc impact limité, mais utilisé sur toutes les méthodes poche.
A12: PROLONGATEUR_PSE | B12: Prolongateur PSE | C12: =0.2759*1.2 -> 0.33108 | D12: 0.055 | E12: 10 | F12: DASRI | G12: Copilote | H12: Carebone / LLM | I12: élevé | J12: Source LLM. À revalider fournisseur.
A13: PERFUSEUR_STANDARD | B13: Perfuseur standard | C13: =0.3876*1.2 -> 0.46512 | D13: 0.182 | E13: 35 | F13: DASRI | G13: Copilote | H13: Carebone / LLM | I13: élevé | J13: Poste ACV significatif (0,182 kgCO₂e). Source LLM — à revalider fournisseur.
A14: RESERVOIR_RYTHMIC_200ML | B14: Poche/réservoir Rythmic avec tubulure 200 mL | C14: =16.97*1.2 -> 20.364 | D14: 0.209 | E14: 50 | F14: DASRI | G14: Copilote | H14: Carebone / LLM | I14: faible | J14: À renseigner seulement si non inclus dans DM captif/location
A15: RESERVOIR_RYTHMIC_100ML | B15: Poche/réservoir Rythmic avec tubulure 100 mL | C15: =16*1.2 -> 19.2 | D15: =0.209-0.037/2 -> 0.1905 | E15: 50 | F15: DASRI | G15: Copilote | H15: Carebone / LLM | I15: faible | J15: À renseigner seulement si non inclus dans DM captif/location
A16: DISPOSITIF_ANAPA_250 | B16: ANAPA 250 mL | C16: =36.41*1.2 -> 43.692 | D16: 0.3 | E16: 43 | F16: DASRI | G16: Copilote | H16: ACV unifiée diffuseurs (base NEOPUMP 500) | I16: moyen | J16: ACV et poids unifies pour tous les diffuseurs (0.3 kgCO2e, 43 g) : valeurs par marque/volume = estimations LLM non differenciables. Cout d'achat conserve par marque. Anciennes valeurs : 0.668 kgCO2e / 150 g. A remplacer par pesee/ACV fournisseur.
A17: NEOPUMP_500 | B17: NEOPUMP 500 mL | C17: =11.96*1.2 -> 14.352 | D17: 0.3 | E17: 43 | F17: DASRI | G17: Copilote | H17: ACV unifiée diffuseurs (base NEOPUMP 500) | I17: moyen | J17: ACV et poids unifies pour tous les diffuseurs (0.3 kgCO2e, 43 g) : valeurs par marque/volume = estimations LLM non differenciables. Cout d'achat conserve par marque. Anciennes valeurs : 0.3 kgCO2e / 43 g. A remplacer par pesee/ACV fournisseur.
A18: NEOPUMP_250 | B18: NEOPUMP 250 mL | C18: =11.96*1.2 -> 14.352 | D18: 0.3 | E18: 43 | F18: DASRI | G18: Estimation | H18: ACV unifiée diffuseurs (base NEOPUMP 500) | I18: moyen | J18: ACV et poids unifies pour tous les diffuseurs (0.3 kgCO2e, 43 g) : valeurs par marque/volume = estimations LLM non differenciables. Cout d'achat conserve par marque. Anciennes valeurs : 0.242 kgCO2e / 43 g. A remplacer par pesee/ACV fournisseur.
A19: RINCAGE_NACL_10ML | B19: Rinçage NaCl 10 mL | C19: =0.3 -> 0.3 | D19: 0.047 | E19: 8 | F19: DASRI | G19: Copilote | H19: Carebone / LLM | I19: moyen | J19: Seringue préremplie ou seringue + ampoule selon pratique
A20: COMPRESSE_ANTISEPTIQUE | B20: Compresse + antiseptique | C20: =0.1 -> 0.1 | D20: 0.055 | E20: 3 | F20: DASRI | G20: Copilote | H20: Carebone / LLM | I20: faible | J20: Optionnel
A21: ETIQUETTE | B21: Étiquette préparation | C21: 0 | D21: 0.003 | E21: 1 | F21: DAOM | G21: Copilote | H21: Carebone / LLM | I21: faible | J21: Optionnel
A22: AIGUILLE_RECONSTITUTION | B22: Aiguille de reconstitution / prélèvement | C22: 0.04 | D22: 0.01 | E22: 2 | F22: DASRI | G22: Hypothèse interne | H22: Carebone / estimation par masse matière | I22: élevé | J22: Ajoutée pour ACV médicaments nécessitant une reconstitution ; valeur provisoire à revalider par pesée/fournisseur. | Hypothèse interne 0,01 kgCO₂e. Multiplié par nb flacons/j×nb flacon/admin — peut cumuler. À revalider par masse matière ou fournisseur.

Sheet LOCATIONS
A1: Locations journalières
A2: Règle métier : Rythmic et PSE 24 mL HAD sont en location par jour.
A3: methode_id | B3: location_par_jour_eur | C3: ACV | D3: Nbre jour utilisation | E3: kgco2e_location_par_jour | F3: source_cout | G3: source_co2 | H3: commentaire
A4: RYTHMIC_CONT | B4: 12 | C4: 27.431 | D4: 1540 | E4: 0.019812338 | F4: Marchés | G4: à compléter | H4: Location pompe Rythmic par jour.
A5: PSE_24_HAD_CONT | B5: 3.6 | C5: 24.961 | D5: 1250 | E5: 0.0399688 | F5: Marchés | G5: à compléter | H5: Location pousse-seringue HAD par jour ; consommation électrique incluse dans kgCO2e/jour si documentée.

Sheet DM Perfusion de l'hôpital
A1: Data coût à l'utilisation matériel réutilisable intra-hospitalier
A2: Hypothèse de calcul = coût et ACV de fabrication amortis au jour d’utilisation. Les consommables, flacons et reconstitution restent multipliés par le nombre réel d’administrations/jour.
A3: methode_id | B3: Coût à l'achat | C3: ACV | D3: Jours d'utilisation | E3: cout_par_jour | F3: kgco2e_par_jour | G3: source_cout | H3: source_co2 | I3: commentaire | J3: ancienne_methode
A4: PSE_48_CONT | B4: 1250 | C4: 62.34 | D4: 2400 | E4: =B4/D4 -> 0.52083333 | F4: =C4/D4 -> 0.025975 | G4: Hypothèse utilisateur : 1500 € TTC, TVA 20 %, soit 1250 € HT | H4: NA | I4: PSE hospitalier : amortissement au jour d’utilisation, pas de location dans le modèle intra-hospitalier. | J4: Avant : amortissement par administration réelle
A5: POCHE_VOL_CONT | B5: 2160 | C5: 79.683 | D5: 2240 | E5: =B5/D5 -> 0.96428571 | F5: =C5/D5 -> 0.035572768 | G5: NA | H5: NA | I5: Pompe volumétrique classique hospitalière : amortissement au jour d’utilisation pour Poche en pompe volumétrique classique. | J5: Avant : amortissement par administration réelle

Sheet HAD
A1: Paramètres HAD et passages infirmiers
A2: Le logiciel calculera : coût HAD/jour = nombre de passages IDE/jour × 60 €. Impact déplacement = nombre de passages IDE/jour × km_moyen_par_passage × kgco2e_par_km, avec fallback sur kgco2e_passage_ide.
A3: contexte | B3: cout_passage_ide_eur | C3: kgco2e_passage_ide | D3: km_moyen_par_passage | E3: commentaire | F3: kgco2e_par_km
A4: IDEL pour passage | B4: 60 | C4: 4.56 | D4: 30 | E4: Aller-retour IDEL (montagne) : 15 km aller x2 = 30 km/passage. kgco2e_passage_ide = 30 x 0,152 = 4,56 kgCO2e. Corrige le sous-comptage (aller simple 2,28). Facteur 0,152 a revalider vs ADEME Base Carbone (~0,193-0,218 kgCO2e/veh.km). | F4: 0.152

Sheet TEMPS_HUMAIN
A1: Temps humain par méthode
A2: Optionnel. Utile pour comparer le coût hospitalier hors forfait HAD.
A3: methode_id | B3: temps_preparation_min | C3: temps_controle_pharma_min | D3: temps_pose_ide_min | E3: temps_retrait_ide_min | F3: temps_surveillance_min | G3: commentaire
A4: POCHE_VOL_CONT | B4: 10 | C4: 0 | D4: 5 | E4: 5 | F4: 0 | G4: Par poche
A5: PSE_48_CONT | B5: 7 | C5: 0 | D5: 5 | E5: 5 | F5: 0 | G5: Par seringue
A6: RYTHMIC_CONT | B6: 12 | C6: 0 | D6: 5 | E6: 5 | F6: 0 | G6: Par réservoir Rythmic
A7: ANAPA_CONT | B7: 12 | C7: 0 | D7: 5 | E7: 5 | F7: 0 | G7: Par dispositif ANAPA
A8: NEOPUMP_CONT | B8: 20 | C8: 0 | D8: 5 | E8: 5 | F8: 0 | G8: Par dispositif NEOPUMP
A9: POCHE_DISCONT | B9: 10 | C9: 0 | D9: 5 | E9: 5 | F9: 0 | G9: Par administration
A10: PSE_24_HAD_DISCONT | B10: 7 | C10: 0 | D10: 5 | E10: 5 | F10: 0 | G10: En HAD, peut être remplacé par forfait passage IDE

Sheet COUTS_HORAIRES
A1: Coûts horaires
A2: Optionnel. Utilisé seulement si le calcul du temps humain hospitalier est activé.
A3: profil | B3: cout_horaire_eur | C3: source | D3: commentaire
A4: préparateur pharmacie | B4: 15.7 | C4: à compléter | D4: Coût horaire chargé
A5: pharmacien | B5: 25 | C5: à compléter | D5: Coût horaire chargé
A6: IDE hospitalier | B6: 18 | C6: à compléter | D6: Coût horaire chargé

Sheet DECHETS
A1: Facteurs déchets
A2: Optionnel. Calcul déchets = poids item × facteur traitement.
A3: type_dechet | B3: cout_traitement_eur_kg | C3: kgco2e_traitement_kg | D3: source | E3: commentaire
A4: DASRI | B4: 0.75 | C4: 0.943 | D4: Carebone | E4: Incinération/traitement spécifique, inclus emballage primaire, verre ou non
A5: DAOM | B5: 0.18 | C5: 0.386 | D5: Carebone | E5: Déchet assimilé ordures ménagères
A6: CARTON | B6: 0.08 | C6: 0.737 | D6: Carebone | E6: Emballage secondaire ; coût conservateur retenu 0,08 €/kg

Sheet PARAMETRES
A1: Paramètres globaux du modèle
A2: Paramètres généraux modifiables sans toucher au code.
A3: parametre | B3: valeur | C3: unite | D3: commentaire
A4: cout_passage_ide_had | B4: 60 | C4: € / passage | D4: Règle fournie : chaque passage IDEL en HAD coûte 60 €.
A5: inclure_medicament | B5: 1 | C5: 0/1 | D5: 0 = non, 1 = oui.
A6: inclure_reconstitution | B6: 1 | C6: 0/1 | D6: Ajoute les DM de reconstitution pour les présentations nécessitant une reconstitution/poudre.
A7: inclure_temps_humain_hospitalier | B7: 1 | C7: 0/1 | D7: Active le calcul temps humain hospitalier.
A8: inclure_transport_had | B8: 1 | C8: 0/1 | D8: Activé : ajoute les émissions de déplacement IDEL en HAD. Par défaut : 15 km/passage × 0,152 kgCO₂e/km = 2,28 kgCO₂e/passage. Ajuster l'onglet HAD si besoin.
A9: inclure_dechets | B9: 1 | C9: 0/1 | D9: Active coût/CO₂ d’élimination des déchets.
A10: inclure_location | B10: 1 | C10: 0/1 | D10: Rythmic / PSE 24 mL HAD.
A11: inclure_equipement_hospitalier | B11: 1 | C11: 0/1 | D11: Active amortissement pompe volumétrique/PSE 48 mL intra-hospitalier si renseigné.
A12: inclure_items_a_confirmer | B12: 1 | C12: 0/1 | D12: Compte les items marqués 'à confirmer' dans MATERIEL_PAR_METHODE.
A13: duree_traitement_jours_defaut | B13: 1 | C13: jours | D13: Valeur par défaut si non fournie.
A14: item_lingette_reconstitution | B14: COMPRESSE_ANTISEPTIQUE | C14: item_id | D14: Lingette/compresse antiseptique ajoutée si reconstitution nécessaire.
A15: nb_lingette_par_flacon_reconstitution | B15: 1 | C15: unité/flacon | D15: Multiplié par le nombre de flacons/jour nécessitant une reconstitution.
A16: item_solvant_reconstitution | B16: RINCAGE_NACL_10ML | C16: item_id | D16: Proxy solvant de reconstitution 10 mL NaCl/EPPI si poudre.
A17: nb_solvant_10ml_par_flacon_reconstitution | B17: 1 | C17: unité/flacon | D17: Multiplié par le nombre de flacons/jour nécessitant une reconstitution.
A18: item_etiquette_preparation | B18: ETIQUETTE | C18: item_id | D18: Étiquette comptée via MATERIEL_PAR_METHODE par administration.
A19: passage_ide_had_prix_defaut | B19: 60 | C19: € | D19: À garder identique à cout_passage_ide_had sauf changement volontaire.

Sheet README
A1: README — Consignes d'utilisation
A2: Documentation interne de la base de coûts et d'impact carbone.
A3: section | B3: contenu
A4: Objectif | B4: Base de paramètres pour simuler l'impact économique et écologique des méthodes de perfusion proposées par Breaking Stab.
A5: Principe | B5: Les scénarios cliniques ne sont pas saisis dans ce fichier. Ils seront générés automatiquement par le logiciel à partir du moteur inversé.
A6: Règle HAD | B6: Chaque passage infirmier libéral en HAD est valorisé à 60 € par défaut.
A7: Règle location | B7: Rythmic et PSE HAD 24 mL sont modélisés avec une location par jour.
A8: Règle DM | B8: Rythmic = DM captif. Le reste = DM unique, sauf exception renseignée dans les tables.
A9: À compléter | B9: Renseigner les coûts unitaires, kgCO₂e, poids, sources et incertitudes dans FACTEURS_ITEMS, LOCATIONS, HAD, DECHETS et COUTS_HORAIRES.
A10: Amortissement équipement | B10: Les équipements hospitaliers doivent avoir un methode_id identique au code HTML : POCHE_VOL_CONT pour pompe volumétrique classique, PSE_48_CONT pour PSE hospitalier.

Sheet CHANGELOG
A1: CHANGELOG — Suivi des modifications
A2: Tracer chaque modification significative : coût, kgCO₂e, poids, ajout/retrait d'un item ou d'une méthode.
A3: date | B3: auteur | C3: onglet | D3: modification | E3: justification | F3: source
A4: AAAA-MM-JJ | B4: Nom | C4: FACTEURS_ITEMS | D4: À compléter | E4: À compléter | F4: URL ou référence
A5: AAAA-MM-JJ | B5: Nom | C5: LOCATIONS | D5: À compléter | E5: À compléter | F5: URL ou référence
A6: AAAA-MM-JJ | B6: Nom | C6: HAD | D6: À compléter | E6: À compléter | F6: URL ou référence
A7: AAAA-MM-JJ | B7: Nom | C7: DECHETS | D7: À compléter | E7: À compléter | F7: URL ou référence
A8: AAAA-MM-JJ | B8: Nom | C8: PARAMETRES | D8: À compléter | E8: À compléter | F8: URL ou référence
A9: 2026-06-05 | B9: ChatGPT | C9: FACTEURS_ITEMS | D9: Correction poids NeoPump 250/500 à 43 g et ANAPA 250 à 150 g | E9: Validation utilisateur après revue des hypothèses ; poids à revalider par pesée | F9: Fiches techniques fournies + hypothèses utilisateur
A10: 2026-06-05 | B10: ChatGPT | C10: METHODES/MATERIEL/LOCATIONS | D10: Renommage PSE_24_HAD_CONT en PSE_24_HAD_DISCONT | E10: Méthode HAD 24 mL discontinue, ancien identifiant ambigu | F10: Correction utilisateur
A11: 2026-06-05 | B11: ChatGPT | C11: MATERIEL_PAR_METHODE/FACTEURS_ITEMS | D11: Harmonisation item_id Rythmic 100/200 mL | E11: Éviter les non-correspondances lors des jointures | F11: Correction utilisateur
A12: 2026-06-05 | B12: ChatGPT | C12: DM Perfusion de l'hôpital | D12: Correction coût PSE 48 mL à 1250 € HT | E12: 1500 € TTC avec TVA 20 % | F12: Hypothèse utilisateur
A13: 2026-06-05 13:21 | B13: Ajout onglet ACV ATB | C13: Ajout d’un onglet avec ATB Breaking Stab, flacons/dosages, valeurs ACV provisoires calculées selon structure EcovaMED. | D13: ACV ATB | E13: Assistant | F13: FE PA générique à revalider
A14: 2026-06-05 | B14: Ajout reconstitution ACV ATB | C14: Ajout aiguille de reconstitution dans FACTEURS_ITEMS et colonnes X:AH dans ACV ATB. | D14: Toutes lignes ACV ATB | E14: Flacon = reconstitution par défaut ; ampoule/poche/plastique = prêt à diluer/administrer. | F14: À revalider par présentation exacte et pratique locale.
... A19: 2026-06-15 | B19: Claude | C19: PARAMETRES | D19: Documentation du risque transport HAD désactivé par défaut | E19: Transport peut inverser comparaison HAD vs hospitalier selon distances | F19: Analyse interne
A20: 2026-06-15 | B20: v3 | C20: HAD transport | D20: Ajout émissions déplacement IDEL | E20: 15 km/passage × 0,152 kgCO₂e/km = 2,28 kgCO₂e/passage ; transport HAD activé
A21: 2026-06-15 | B21: Correction | C21: ELASTOMERE_GENERIC | D21: Ajout panier matériel diffuseur générique | E21: Le CO₂ DM du diffuseur générique est désormais pris en compte via proxy NEOPUMP 250/500 selon volume. | F21: DP/ChatGPT
A201: 2026-07-03 | B201: Revue assistée | C201: HAD | D201: Transport IDEL en aller-retour : km 15->30 ; kgco2e_passage 2,28->4,56. | E201: L'IDEL revient a sa base ; l'aller simple sous-comptait de moitie le transport HAD. | F201: Commentaire onglet HAD + ADEME.
A202: 2026-07-03 | B202: Revue assistée | C202: FACTEURS_ITEMS + METHODES_PERFUSION | D202: ACV et poids diffuseurs unifies (0,3 kgCO2e / 43 g). | E202: ACV par marque/volume = estimations LLM sans base fournisseur (fausse precision). Base NEOPUMP 500. Couts conserves par marque. | F202: Fiche technique NeoPump 500 mL.

Sheet ACV ATB
A1: ACV ATB — flacons/dosages Breaking Stab (valeurs provisoires calculables)
A3: NOTE | B3: Les valeurs ci-dessous utilisent la structure EcovaMED : masse de PA × FE PA, pertes de fabrication, transport amont PA, conditionnement primaire et emballage secondaire. Le FE PA spécifique n’est pas fourni dans la matrice ; un FE PA générique provisoire est utilisé et doit être remplacé dès qu’un FE PA fournisseur/EcovaMED calculé est disponible. | D3: Paramètre | E3: Valeur | F3: Unité | G3: Source / commentaire
A4: Source ATB | B4: Liste issue de l’outil Breaking Stab / onglet STABILITE et sources CHICAS/Micrel intégrées. | D4: FE_PA_generique_provisoire | E4: 100 | F4: kgCO2e/kg PA | G4: Hypothèse interne provisoire à remplacer par FE PA fournisseur/EcovaMED calculateur
A5: Source coefficients | B5: Matrice EcovaMED v0.7 : pertes PA 5 %, transport excipients/conditionnements 0,095 kgCO2e/kg, flacon verre Europe 7,1 kgCO2e/kg, ampoule verre Europe 5,0 kgCO2e/kg, flacon plastique Europe 4,2 kgCO2e/kg, conditionnement tertiaire carton 1,16 kgCO2e/kg. | D5: Taux_perte_PA | E5: 5 | F5: % | G5: EcovaMED matrice médicament, valeur par défaut
A6: Périmètre | B6: ACV par flacon/unité de médicament avant ajout des DM de perfusion ; destruction/excrétion/administration non incluses ici. | D6: FE_transport_amont_PA | E6: 0.095 | F6: kgCO2e/kg | G6: EcovaMED, transport vers site de fabrication
D7: FE_flacon_verre_Europe | E7: 7.1 | F7: kgCO2e/kg | G7: EcovaMED, conditionnement primaire
D8: FE_ampoule_verre_Europe | E8: 5 | F8: kgCO2e/kg | G8: EcovaMED, conditionnement primaire
D9: FE_flacon_plastique_Europe | E9: 4.2 | F9: kgCO2e/kg | G9: EcovaMED, conditionnement primaire
D10: FE_carton_secondaire | E10: 1.16 | F10: kgCO2e/kg | G10: EcovaMED, conditionnement tertiaire carton
D11: Poids_flacon_verre_defaut | E11: 10 | F11: g | G11: Hypothèse interne à remplacer si poids fournisseur disponible
D12: Poids_ampoule_defaut | E12: 5 | F12: g | G12: Hypothèse interne à remplacer si poids fournisseur disponible
D13: Poids_poche_PEA_defaut | E13: 20 | F13: g | G13: Hypothèse interne pour poches/prêt-à-l’emploi
D14: Poids_carton_proratise_defaut | E14: 3 | F14: g/unité | G14: Hypothèse interne emballage secondaire/tertiaire proratisé
A15: Ajout reconstitution | B15: Les colonnes X:AH classent les présentations en “reconstitution nécessaire” vs “prêt à être dilué/administré” par règle provisoire : flacon = reconstitution ; ampoule/poche/plastique = prêt. Les DM de reconstitution ajoutés par défaut sont 1 seringue 24 mL + 1 aiguille. À revalider par présentation exacte. | D15: DM_reconstitution_defaut | E15: 1 seringue 24 mL + 1 aiguille | F15: par flacon si reconstitution | G15: Hypothèse interne, à ajuster si plusieurs flacons/dose ou pratiques locales
A17: molecule_outil | B17: presentation_flacon_dosage | C17: type_presentation | D17: PA1 | E17: PA1_mg | F17: PA2 | G17: PA2_mg | H17: PA3 | I17: PA3_mg | J17: masse_PA_totale_g | K17: FE_PA_retenu_kgCO2e_kg | L17: ACV_PA_kgCO2e | M17: ACV_transport_PA_kgCO2e | N17: poids_conditionnement_primaire_g | O17: FE_conditionnement_primaire | P17: ACV_conditionnement_primaire_kgCO2e | Q17: poids_carton_proratise_g | R17: ACV_carton_secondaire_kgCO2e | S17: ACV_flacon_total_kgCO2e | T17: niveau_incertitude | U17: source_ATB | V17: source_coefficients | W17: commentaire | X17: statut_preparation | Y17: hypothese_reconstitution | Z17: nb_seringue_reconstitution | AA17: item_seringue_reconstitution | AB17: ACV_seringue_reconstitution_kgCO2e | AC17: nb_aiguille_reconstitution | AD17: item_aiguille_reconstitution | AE17: ACV_aiguille_reconstitution_kgCO2e | AF17: ACV_DM_reconstitution_kgCO2e | AG17: ACV_medicament_total_avec_reconstitution_kgCO2e | AH17: commentaire_preparation
A18: Aciclovir | B18: Flacon 250 mg | C18: flacon verre | D18: Aciclovir | E18: 250 | J18: =IFERROR(SUM(E18,G18,I18)/1000,"") -> 0.25 | K18: =$E$4 -> 100 | L18: =IF(J18="","",J18/1000*K18*(1+$E$5/100)) -> 0.02625 | M18: =IF(J18="","",J18/1000*$E$6) -> 2.375e-05 | N18: =IF(C18="ampoule verre",$E$12,IF(C18="poche PEA",$E$13,$E$11)) -> 10 | O18: =IF(C18="ampoule verre",$E$8,IF(C18="poche PEA",$E$9,$E$7)) -> 7.1 | P18: =N18/1000*O18*(1+$E$5/100) -> 0.07455 | Q18: =$E$14 -> 3 | R18: =Q18/1000*$E$10 -> 0.00348 | S18: =IF(J18="","",SUM(L18:M18,P18,R18)) -> 0.10430375 | T18: =IF(OR(J18="",K18=$E$4),"Élevé - FE PA générique",IF(W18<>"","À vérifier","Moyen")) -> Élevé - FE PA générique | U18: Breaking Stab | V18: EcovaMED v0.7 + hypothèses internes explicites | X18: =IF(A18="","",IF(OR(ISNUMBER(SEARCH("poche",C18)),ISNUMBER(SEARCH("ampoule",C18)),ISNUMBER(SEARCH("plastique",C18))),"Prêt à être dilué / administré (hypothèse)","Reconstitution nécessaire (hypothèse)")) -> Reconstitution nécessaire (hypothèse) | Y18: =IF(A18="","",IF(ISNUMBER(SEARCH("Reconstitution",X18)),"Flacon/poudre : ajout par défaut 1 seringue + 1 aiguille ; à revalider selon présentation exacte.","Ampoule/poche/présentation solution : aucun DM de reconstitution ajouté ; DM de perfusion calculés ailleurs.")) -> Flacon/poudre : ajout par défaut 1 seringue + 1 aiguille ; à revalider selon présentation exacte. | Z18: =IF(A18="","",IF(ISNUMBER(SEARCH("Reconstitution",X18)),1,0)) -> 1 | AA18: =IF(Z18>0,"SERINGUE_PP_24ML","") -> SERINGUE_PP_24ML | AB18: =IF(Z18>0,Z18*VLOOKUP(AA18,FACTEURS_ITEMS!$A$3:$J$30,4,FALSE()),0) -> 0.069 | AC18: =IF(A18="","",IF(ISNUMBER(SEARCH("Reconstitution",X18)),1,0)) -> 1 | AD18: =IF(AC18>0,"AIGUILLE_RECONSTITUTION","") -> AIGUILLE_RECONSTITUTION | AE18: =IF(AC18>0,AC18*VLOOKUP(AD18,FACTEURS_ITEMS!$A$3:$J$30,4,FALSE()),0) -> 0.01 | AF18: =IF(A18="","",AB18+AE18) -> 0.079 | AG18: =IF(A18="","",S18+AF18) -> 0.18330375 | AH18: =IF(A18="","",IF(AF18>0,"ACV médicament incluant PA + conditionnement + DM de reconstitution. Ne comprend pas poche/solvant/tubulure/administration.","ACV médicament sans DM de reconstitution ajouté.")) -> ACV médicament incluant PA + conditionnement + DM de reconstitution. Ne comprend pas poche/solvant/tubulure/administration.
A19: Aciclovir | B19: Flacon 500 mg | C19: flacon verre | D19: Aciclovir | E19: 500 | J19: =IFERROR(SUM(E19,G19,I19)/1000,"") -> 0.5 | K19: =$E$4 -> 100 | L19: =IF(J19="","",J19/1000*K19*(1+$E$5/100)) -> 0.0525 | M19: =IF(J19="","",J19/1000*$E$6) -> 4.75e-05 | N19: =IF(C19="ampoule verre",$E$12,IF(C19="poche PEA",$E$13,$E$11)) -> 10 | O19: =IF(C19="ampoule verre",$E$8,IF(C19="poche PEA",$E$9,$E$7)) -> 7.1 | P19: =N19/1000*O19*(1+$E$5/100) -> 0.07455 | Q19: =$E$14 -> 3 | R19: =Q19/1000*$E$10 -> 0.00348 | S19: =IF(J19="","",SUM(L19:M19,P19,R19)) -> 0.1305775 | T19: =IF(OR(J19="",K19=$E$4),"Élevé - FE PA générique",IF(W19<>"","À vérifier","Moyen")) -> Élevé - FE PA générique | U19: Breaking Stab | V19: EcovaMED v0.7 + hypothèses internes explicites | X19: =IF(A19="","",IF(OR(ISNUMBER(SEARCH("poche",C19)),ISNUMBER(SEARCH("ampoule",C19)),ISNUMBER(SEARCH("plastique",C19))),"Prêt à être dilué / administré (hypothèse)","Reconstitution nécessaire (hypothèse)")) -> Reconstitution nécessaire (hypothèse) | Y19: =IF(A19="","",IF(ISNUMBER(SEARCH("Reconstitution",X19)),"Flacon/poudre : ajout par défaut 1 seringue + 1 aiguille ; à revalider selon présentation exacte.","Ampoule/poche/présentation solution : aucun DM de reconstitution ajouté ; DM de perfusion calculés ailleurs.")) -> Flacon/poudre : ajout par défaut 1 seringue + 1 aiguille ; à revalider selon présentation exacte. | Z19: =IF(A19="","",IF(ISNUMBER(SEARCH("Reconstitution",X19)),1,0)) -> 1 | AA19: =IF(Z19>0,"SERINGUE_PP_24ML","") -> SERINGUE_PP_24ML | AB19: =IF(Z19>0,Z19*VLOOKUP(AA19,FACTEURS_ITEMS!$A$3:$J$30,4,FALSE()),0) -> 0.069 | AC19: =IF(A19="","",IF(ISNUMBER(SEARCH("Reconstitution",X19)),1,0)) -> 1 | AD19: =IF(AC19>0,"AIGUILLE_RECONSTITUTION","") -> AIGUILLE_RECONSTITUTION | AE19: =IF(AC19>0,AC19*VLOOKUP(AD19,FACTEURS_ITEMS!$A$3:$J$30,4,FALSE()),0) -> 0.01 | AF19: =IF(A19="","",AB19+AE19) -> 0.079 | AG19: =IF(A19="","",S19+AF19) -> 0.2095775 | AH19: =IF(A19="","",IF(AF19>0,"ACV médicament incluant PA + conditionnement + DM de reconstitution. Ne comprend pas poche/solvant/tubulure/administration.","ACV médicament sans DM de reconstitution ajouté.")) -> ACV médicament incluant PA + conditionnement + DM de reconstitution. Ne comprend pas poche/solvant/tubulure/administration.
A20: Amikacine | B20: Flacon/ampoule 250 mg | C20: ampoule verre | D20: Amikacine | E20: 250 | J20: =IFERROR(SUM(E20,G20,I20)/1000,"") -> 0.25 | K20: =$E$4 -> 100 | L20: =IF(J20="","",J20/1000*K20*(1+$E$5/100)) -> 0.02625 | M20: =IF(J20="","",J20/1000*$E$6) -> 2.375e-05 | N20: =IF(C20="ampoule verre",$E$12,IF(C20="poche PEA",$E$13,$E$11)) -> 5 | O20: =IF(C20="ampoule verre",$E$8,IF(C20="poche PEA",$E$9,$E$7)) -> 5 | P20: =N20/1000*O20*(1+$E$5/100) -> 0.02625 | Q20: =$E$14 -> 3 | R20: =Q20/1000*$E$10 -> 0.00348 | S20: =IF(J20="","",SUM(L20:M20,P20,R20)) -> 0.05600375 | T20: =IF(OR(J20="",K20=$E$4),"Élevé - FE PA générique",IF(W20<>"","À vérifier","Moyen")) -> Élevé - FE PA générique | U20: Breaking Stab | V20: EcovaMED v0.7 + hypothèses internes explicites | X20: =IF(A20="","",IF(OR(ISNUMBER(SEARCH("poche",C20)),ISNUMBER(SEARCH("ampoule",C20)),ISNUMBER(SEARCH("plastique",C20))),"Prêt à être dilué / administré (hypothèse)","Reconstitution nécessaire (hypothèse)")) -> Prêt à être dilué / administré (hypothèse) | Y20: =IF(A20="","",IF(ISNUMBER(SEARCH("Reconstitution",X20)),"Flacon/poudre : ajout par défaut 1 seringue + 1 aiguille ; à revalider selon présentation exacte.","Ampoule/poche/présentation solution : aucun DM de reconstitution ajouté ; DM de perfusion calculés ailleurs.")) -> Ampoule/poche/présentation solution : aucun DM de reconstitution ajouté ; DM de perfusion calculés ailleurs. | Z20: =IF(A20="","",IF(ISNUMBER(SEARCH("Reconstitution",X20)),1,0)) -> 0 | AA20: =IF(Z20>0,"SERINGUE_PP_24ML","") | AB20: =IF(Z20>0,Z20*VLOOKUP(AA20,FACTEURS_ITEMS!$A$3:$J$30,4,FALSE()),0) -> 0 | AC20: =IF(A20="","",IF(ISNUMBER(SEARCH("Reconstitution",X20)),1,0)) -> 0 | AD20: =IF(AC20>0,"AIGUILLE_RECONSTITUTION","") | AE20: =IF(AC20>0,AC20*VLOOKUP(AD20,FACTEURS_ITEMS!$A$3:$J$30,4,FALSE()),0) -> 0 | AF20: =IF(A20="","",AB20+AE20) -> 0 | AG20: =IF(A20="","",S20+AF20) -> 0.05600375 | AH20: =IF(A20="","",IF(AF20>0,"ACV médicament incluant PA + conditionnement + DM de reconstitution. Ne comprend pas poche/solvant/tubulure/administration.","ACV médicament sans DM de reconstitution ajouté.")) -> ACV médicament sans DM de reconstitution ajouté.
A21: Amikacine | B21: Flacon/ampoule 500 mg | C21: ampoule verre | D21: Amikacine | E21: 500 | J21: =IFERROR(SUM(E21,G21,I21)/1000,"") -> 0.5 | K21: =$E$4 -> 100 | L21: =IF(J21="","",J21/1000*K21*(1+$E$5/100)) -> 0.0525 | M21: =IF(J21="","",J21/1000*$E$6) -> 4.75e-05 | N21: =IF(C21="ampoule verre",$E$12,IF(C21="poche PEA",$E$13,$E$11)) -> 5 | O21: =IF(C21="ampoule verre",$E$8,IF(C21="poche PEA",$E$9,$E$7)) -> 5 | P21: =N21/1000*O21*(1+$E$5/100) -> 0.02625 | Q21: =$E$14 -> 3 | R21: =Q21/1000*$E$10 -> 0.00348 | S21: =IF(J21="","",SUM(L21:M21,P21,R21)) -> 0.0822775 | T21: =IF(OR(J21="",K21=$E$4),"Élevé - FE PA générique",IF(W21<>"","À vérifier","Moyen")) -> Élevé - FE PA générique | U21: Breaking Stab | V21: EcovaMED v0.7 + hypothèses internes explicites | X21: =IF(A21="","",IF(OR(ISNUMBER(SEARCH("poche",C21)),ISNUMBER(SEARCH("ampoule",C21)),ISNUMBER(SEARCH("plastique",C21))),"Prêt à être dilué / administré (hypothèse)","Reconstitution nécessaire (hypothèse)")) -> Prêt à être dilué / administré (hypothèse) | Y21: =IF(A21="","",IF(ISNUMBER(SEARCH("Reconstitution",X21)),"Flacon/poudre : ajout par défaut 1 seringue + 1 aiguille ; à revalider selon présentation exacte.","Ampoule/poche/présentation solution : aucun DM de reconstitution ajouté ; DM de perfusion calculés ailleurs.")) -> Ampoule/poche/présentation solution : aucun DM de reconstitution ajouté ; DM de perfusion calculés ailleurs. | Z21: =IF(A21="","",IF(ISNUMBER(SEARCH("Reconstitution",X21)),1,0)) -> 0 | AA21: =IF(Z21>0,"SERINGUE_PP_24ML","") | AB21: =IF(Z21>0,Z21*VLOOKUP(AA21,FACTEURS_ITEMS!$A$3:$J$30,4,FALSE()),0) -> 0 | AC21: =IF(A21="","",IF(ISNUMBER(SEARCH("Reconstitution",X21)),1,0)) -> 0 | AD21: =IF(AC21>0,"AIGUILLE_RECONSTITUTION","") | AE21: =IF(AC21>0,AC21*VLOOKUP(AD21,FACTEURS_ITEMS!$A$3:$J$30,4,FALSE()),0) -> 0 | AF21: =IF(A21="","",AB21+AE21) -> 0 | AG21: =IF(A21="","",S21+AF21) -> 0.0822775 | AH21: =IF(A21="","",IF(AF21>0,"ACV médicament incluant PA + conditionnement + DM de reconstitution. Ne comprend pas poche/solvant/tubulure/administration.","ACV médicament sans DM de reconstitution ajouté.")) -> ACV médicament sans DM de reconstitution ajouté.
A22: Amikacine | B22: Flacon/ampoule 1 g | C22: flacon verre | D22: Amikacine | E22: 1000 | J22: =IFERROR(SUM(E22,G22,I22)/1000,"") -> 1 | K22: =$E$4 -> 100 | L22: =IF(J22="","",J22/1000*K22*(1+$E$5/100)) -> 0.105 | M22: =IF(J22="","",J22/1000*$E$6) -> 9.5e-05 | N22: =IF(C22="ampoule verre",$E$12,IF(C22="poche PEA",$E$13,$E$11)) -> 10 | O22: =IF(C22="ampoule verre",$E$8,IF(C22="poche PEA",$E$9,$E$7)) -> 7.1 | P22: =N22/1000*O22*(1+$E$5/100) -> 0.07455 | Q22: =$E$14 -> 3 | R22: =Q22/1000*$E$10 -> 0.00348 | S22: =IF(J22="","",SUM(L22:M22,P22,R22)) -> 0.183125 | T22: =IF(OR(J22="",K22=$E$4),"Élevé - FE PA générique",IF(W22<>"","À vérifier","Moyen")) -> Élevé - FE PA générique | U22: Breaking Stab | V22: EcovaMED v0.7 + hypothèses internes explicites | X22: =IF(A22="","",IF(OR(ISNUMBER(SEARCH("poche",C22)),ISNUMBER(SEARCH("ampoule",C22)),ISNUMBER(SEARCH("plastique",C22))),"Prêt à être dilué / administré (hypothèse)","Reconstitution nécessaire (hypothèse)")) -> Reconstitution nécessaire (hypothèse) | Y22: =IF(A22="","",IF(ISNUMBER(SEARCH("Reconstitution",X22)),"Flacon/poudre : ajout par défaut 1 seringue + 1 aiguille ; à revalider selon présentation exacte.","Ampoule/poche/présentation solution : aucun DM de reconstitution ajouté ; DM de perfusion calculés ailleurs.")) -> Flacon/poudre : ajout par défaut 1 seringue + 1 aiguille ; à revalider selon présentation exacte. | Z22: =IF(A22="","",IF(ISNUMBER(SEARCH("Reconstitution",X22)),1,0)) -> 1 | AA22: =IF(Z22>0,"SERINGUE_PP_24ML","") -> SERINGUE_PP_24ML | AB22: =IF(Z22>0,Z22*VLOOKUP(AA22,FACTEURS_ITEMS!$A$3:$J$30,4,FALSE()),0) -> 0.069 | AC22: =IF(A22="","",IF(ISNUMBER(SEARCH("Reconstitution",X22)),1,0)) -> 1 | AD22: =IF(AC22>0,"AIGUILLE_RECONSTITUTION","") -> AIGUILLE_RECONSTITUTION | AE22: =IF(AC22>0,AC22*VLOOKUP(AD22,FACTEURS_ITEMS!$A$3:$J$30,4,FALSE()),0) -> 0.01 | AF22: =IF(A22="","",AB22+AE22) -> 0.079 | AG22: =IF(A22="","",S22+AF22) -> 0.262125 | AH22: =IF(A22="","",IF(AF22>0,"ACV médicament incluant PA + conditionnement + DM de reconstitution. Ne comprend pas poche/solvant/tubulure/administration.","ACV médicament sans DM de reconstitution ajouté.")) -> ACV médicament incluant PA + conditionnement + DM de reconstitution. Ne comprend pas poche/solvant/tubulure/administration.
A23: Amoxicilline | B23: Flacon 1 g | C23: flacon verre | D23: Amoxicilline | E23: 1000 | J23: =IFERROR(SUM(E23,G23,I23)/1000,"") -> 1 | K23: =$E$4 -> 100 | L23: =IF(J23="","",J23/1000*K23*(1+$E$5/100)) -> 0.105 | M23: =IF(J23="","",J23/1000*$E$6) -> 9.5e-05 | N23: =IF(C23="ampoule verre",$E$12,IF(C23="poche PEA",$E$13,$E$11)) -> 10 | O23: =IF(C23="ampoule verre",$E$8,IF(C23="poche PEA",$E$9,$E$7)) -> 7.1 | P23: =N23/1000*O23*(1+$E$5/100) -> 0.07455 | Q23: =$E$14 -> 3 | R23: =Q23/1000*$E$10 -> 0.00348 | S23: =IF(J23="","",SUM(L23:M23,P23,R23)) -> 0.183125 | T23: =IF(OR(J23="",K23=$E$4),"Élevé - FE PA générique",IF(W23<>"","À vérifier","Moyen")) -> Élevé - FE PA générique | U23: Breaking Stab | V23: EcovaMED v0.7 + hypothèses internes explicites | X23: =IF(A23="","",IF(OR(ISNUMBER(SEARCH("poche",C23)),ISNUMBER(SEARCH("ampoule",C23)),ISNUMBER(SEARCH("plastique",C23))),"Prêt à être dilué / administré (hypothèse)","Reconstitution nécessaire (hypothèse)")) -> Reconstitution nécessaire (hypothèse) | Y23: =IF(A23="","",IF(ISNUMBER(SEARCH("Reconstitution",X23)),"Flacon/poudre : ajout par défaut 1 seringue + 1 aiguille ; à revalider selon présentation exacte.","Ampoule/poche/présentation solution : aucun DM de reconstitution ajouté ; DM de perfusion calculés ailleurs.")) -> Flacon/poudre : ajout par défaut 1 seringue + 1 aiguille ; à revalider selon présentation exacte. | Z23: =IF(A23="","",IF(ISNUMBER(SEARCH("Reconstitution",X23)),1,0)) -> 1 | AA23: =IF(Z23>0,"SERINGUE_PP_24ML","") -> SERINGUE_PP_24ML | AB23: =IF(Z23>0,Z23*VLOOKUP(AA23,FACTEURS_ITEMS!$A$3:$J$30,4,FALSE()),0) -> 0.069 | AC23: =IF(A23="","",IF(ISNUMBER(SEARCH("Reconstitution",X23)),1,0)) -> 1 | AD23: =IF(AC23>0,"AIGUILLE_RECONSTITUTION","") -> AIGUILLE_RECONSTITUTION | AE23: =IF(AC23>0,AC23*VLOOKUP(AD23,FACTEURS_ITEMS!$A$3:$J$30,4,FALSE()),0) -> 0.01 | AF23: =IF(A23="","",AB23+AE23) -> 0.079 | AG23: =IF(A23="","",S23+AF23) -> 0.262125 | AH23: =IF(A23="","",IF(AF23>0,"ACV médicament incluant PA + conditionnement + DM de reconstitution. Ne comprend pas poche/solvant/tubulure/administration.","ACV médicament sans DM de reconstitution ajouté.")) -> ACV médicament incluant PA + conditionnement + DM de reconstitution. Ne comprend pas poche/solvant/tubulure/administration.
A24: Amoxicilline | B24: Flacon 2 g | C24: flacon verre | D24: Amoxicilline | E24: 2000 | J24: =IFERROR(SUM(E24,G24,I24)/1000,"") -> 2 | K24: =$E$4 -> 100 | L24: =IF(J24="","",J24/1000*K24*(1+$E$5/100)) -> 0.21 | M24: =IF(J24="","",J24/1000*$E$6) -> 0.00019 | N24: =IF(C24="ampoule verre",$E$12,IF(C24="poche PEA",$E$13,$E$11)) -> 10 | O24: =IF(C24="ampoule verre",$E$8,IF(C24="poche PEA",$E$9,$E$7)) -> 7.1 | P24: =N24/1000*O24*(1+$E$5/100) -> 0.07455 | Q24: =$E$14 -> 3 | R24: =Q24/1000*$E$10 -> 0.00348 | S24: =IF(J24="","",SUM(L24:M24,P24,R24)) -> 0.28822 | T24: =IF(OR(J24="",K24=$E$4),"Élevé - FE PA générique",IF(W24<>"","À vérifier","Moyen")) -> Élevé - FE PA générique | U24: Breaking Stab | V24: EcovaMED v0.7 + hypothèses internes explicites | X24: =IF(A24="","",IF(OR(ISNUMBER(SEARCH("poche",C24)),ISNUMBER(SEARCH("ampoule",C24)),ISNUMBER(SEARCH("plastique",C24))),"Prêt à être dilué / administré (hypothèse)","Reconstitution nécessaire (hypothèse)")) -> Reconstitution nécessaire (hypothèse) | Y24: =IF(A24="","",IF(ISNUMBER(SEARCH("Reconstitution",X24)),"Flacon/poudre : ajout par défaut 1 seringue + 1 aiguille ; à revalider selon présentation exacte.","Ampoule/poche/présentation solution : aucun DM de reconstitution ajouté ; DM de perfusion calculés ailleurs.")) -> Flacon/poudre : ajout par défaut 1 seringue + 1 aiguille ; à revalider selon présentation exacte. | Z24: =IF(A24="","",IF(ISNUMBER(SEARCH("Reconstitution",X24)),1,0)) -> 1 | AA24: =IF(Z24>0,"SERINGUE_PP_24ML","") -> SERINGUE_PP_24ML | AB24: =IF(Z24>0,Z24*VLOOKUP(AA24,FACTEURS_ITEMS!$A$3:$J$30,4,FALSE()),0) -> 0.069 | AC24: =IF(A24="","",IF(ISNUMBER(SEARCH("Reconstitution",X24)),1,0)) -> 1 | AD24: =IF(AC24>0,"AIGUILLE_RECONSTITUTION","") -> AIGUILLE_RECONSTITUTION | AE24: =IF(AC24>0,AC24*VLOOKUP(AD24,FACTEURS_ITEMS!$A$3:$J$30,4,FALSE()),0) -> 0.01 | AF24: =IF(A24="","",AB24+AE24) -> 0.079 | AG24: =IF(A24="","",S24+AF24) -> 0.36722 | AH24: =IF(A24="","",IF(AF24>0,"ACV médicament incluant PA + conditionnement + DM de reconstitution. Ne comprend pas poche/solvant/tubulure/administration.","ACV médicament sans DM de reconstitution ajouté.")) -> ACV médicament incluant PA + conditionnement + DM de reconstitution. Ne comprend pas poche/solvant/tubulure/administration.
A25: Amoxicilline/acide clavulanique | B25: Flacon 1 g/200 mg | C25: flacon verre | D25: Amoxicilline | E25: 1000 | F25: Acide clavulanique | G25: 200 | J25: =IFERROR(SUM(E25,G25,I25)/1000,"") -> 1.2 | K25: =$E$4 -> 100 | L25: =IF(J25="","",J25/1000*K25*(1+$E$5/100)) -> 0.126 | M25: =IF(J25="","",J25/1000*$E$6) -> 0.000114 | N25: =IF(C25="ampoule verre",$E$12,IF(C25="poche PEA",$E$13,$E$11)) -> 10 | O25: =IF(C25="ampoule verre",$E$8,IF(C25="poche PEA",$E$9,$E$7)) -> 7.1 | P25: =N25/1000*O25*(1+$E$5/100) -> 0.07455 | Q25: =$E$14 -> 3 | R25: =Q25/1000*$E$10 -> 0.00348 | S25: =IF(J25="","",SUM(L25:M25,P25,R25)) -> 0.204144 | T25: =IF(OR(J25="",K25=$E$4),"Élevé - FE PA générique",IF(W25<>"","À vérifier","Moyen")) -> Élevé - FE PA générique | U25: Breaking Stab | V25: EcovaMED v0.7 + hypothèses internes explicites | X25: =IF(A25="","",IF(OR(ISNUMBER(SEARCH("poche",C25)),ISNUMBER(SEARCH("ampoule",C25)),ISNUMBER(SEARCH("plastique",C25))),"Prêt à être dilué / administré (hypothèse)","Reconstitution nécessaire (hypothèse)")) -> Reconstitution nécessaire (hypothèse) | Y25: =IF(A25="","",IF(ISNUMBER(SEARCH("Reconstitution",X25)),"Flacon/poudre : ajout par défaut 1 seringue + 1 aiguille ; à revalider selon présentation exacte.","Ampoule/poche/présentation solution : aucun DM de reconstitution ajouté ; DM de perfusion calculés ailleurs.")) -> Flacon/poudre : ajout par défaut 1 seringue + 1 aiguille ; à revalider selon présentation exacte. | Z25: =IF(A25="","",IF(ISNUMBER(SEARCH("Reconstitution",X25)),1,0)) -> 1 | AA25: =IF(Z25>0,"SERINGUE_PP_24ML","") -> SERINGUE_PP_24ML | AB25: =IF(Z25>0,Z25*VLOOKUP(AA25,FACTEURS_ITEMS!$A$3:$J$30,4,FALSE()),0) -> 0.069 | AC25: =IF(A25="","",IF(ISNUMBER(SEARCH("Reconstitution",X25)),1,0)) -> 1 | AD25: =IF(AC25>0,"AIGUILLE_RECONSTITUTION","") -> AIGUILLE_RECONSTITUTION | AE25: =IF(AC25>0,AC25*VLOOKUP(AD25,FACTEURS_ITEMS!$A$3:$J$30,4,FALSE()),0) -> 0.01 | AF25: =IF(A25="","",AB25+AE25) -> 0.079 | AG25: =IF(A25="","",S25+AF25) -> 0.283144 | AH25: =IF(A25="","",IF(AF25>0,"ACV médicament incluant PA + conditionnement + DM de reconstitution. Ne comprend pas poche/solvant/tubulure/administration.","ACV médicament sans DM de reconstitution ajouté.")) -> ACV médicament incluant PA + conditionnement + DM de reconstitution. Ne comprend pas poche/solvant/tubulure/administration.
A26: Amoxicilline/acide clavulanique | B26: Flacon 2 g/200 mg | C26: flacon verre | D26: Amoxicilline | E26: 2000 | F26: Acide clavulanique | G26: 200 | J26: =IFERROR(SUM(E26,G26,I26)/1000,"") -> 2.2 | K26: =$E$4 -> 100 | L26: =IF(J26="","",J26/1000*K26*(1+$E$5/100)) -> 0.231 | M26: =IF(J26="","",J26/1000*$E$6) -> 0.000209 | N26: =IF(C26="ampoule verre",$E$12,IF(C26="poche PEA",$E$13,$E$11)) -> 10 | O26: =IF(C26="ampoule verre",$E$8,IF(C26="poche PEA",$E$9,$E$7)) -> 7.1 | P26: =N26/1000*O26*(1+$E$5/100) -> 0.07455 | Q26: =$E$14 -> 3 | R26: =Q26/1000*$E$10 -> 0.00348 | S26: =IF(J26="","",SUM(L26:M26,P26,R26)) -> 0.309239 | T26: =IF(OR(J26="",K26=$E$4),"Élevé - FE PA générique",IF(W26<>"","À vérifier","Moyen")) -> Élevé - FE PA générique | U26: Breaking Stab | V26: EcovaMED v0.7 + hypothèses internes explicites | X26: =IF(A26="","",IF(OR(ISNUMBER(SEARCH("poche",C26)),ISNUMBER(SEARCH("ampoule",C26)),ISNUMBER(SEARCH("plastique",C26))),"Prêt à être dilué / administré (hypothèse)","Reconstitution nécessaire (hypothèse)")) -> Reconstitution nécessaire (hypothèse) | Y26: =IF(A26="","",IF(ISNUMBER(SEARCH("Reconstitution",X26)),"Flacon/poudre : ajout par défaut 1 seringue + 1 aiguille ; à revalider selon présentation exacte.","Ampoule/poche/présentation solution : aucun DM de reconstitution ajouté ; DM de perfusion calculés ailleurs.")) -> Flacon/poudre : ajout par défaut 1 seringue + 1 aiguille ; à revalider selon présentation exacte. | Z26: =IF(A26="","",IF(ISNUMBER(SEARCH("Reconstitution",X26)),1,0)) -> 1 | AA26: =IF(Z26>0,"SERINGUE_PP_24ML","") -> SERINGUE_PP_24ML | AB26: =IF(Z26>0,Z26*VLOOKUP(AA26,FACTEURS_ITEMS!$A$3:$J$30,4,FALSE()),0) -> 0.069 | AC26: =IF(A26="","",IF(ISNUMBER(SEARCH("Reconstitution",X26)),1,0)) -> 1 | AD26: =IF(AC26>0,"AIGUILLE_RECONSTITUTION","") -> AIGUILLE_RECONSTITUTION | AE26: =IF(AC26>0,AC26*VLOOKUP(AD26,FACTEURS_ITEMS!$A$3:$J$30,4,FALSE()),0) -> 0.01 | AF26: =IF(A26="","",AB26+AE26) -> 0.079 | AG26: =IF(A26="","",S26+AF26) -> 0.388239 | AH26: =IF(A26="","",IF(AF26>0,"ACV médicament incluant PA + conditionnement + DM de reconstitution. Ne comprend pas poche/solvant/tubulure/administration.","ACV médicament sans DM de reconstitution ajouté.")) -> ACV médicament incluant PA + conditionnement + DM de reconstitution. Ne comprend pas poche/solvant/tubulure/administration.
A27: Ampicilline | B27: Flacon 1 g | C27: flacon verre | D27: Ampicilline | E27: 1000 | J27: =IFERROR(SUM(E27,G27,I27)/1000,"") -> 1 | K27: =$E$4 -> 100 | L27: =IF(J27="","",J27/1000*K27*(1+$E$5/100)) -> 0.105 | M27: =IF(J27="","",J27/1000*$E$6) -> 9.5e-05 | N27: =IF(C27="ampoule verre",$E$12,IF(C27="poche PEA",$E$13,$E$11)) -> 10 | O27: =IF(C27="ampoule verre",$E$8,IF(C27="poche PEA",$E$9,$E$7)) -> 7.1 | P27: =N27/1000*O27*(1+$E$5/100) -> 0.07455 | Q27: =$E$14 -> 3 | R27: =Q27/1000*$E$10 -> 0.00348 | S27: =IF(J27="","",SUM(L27:M27,P27,R27)) -> 0.183125 | T27: =IF(OR(J27="",K27=$E$4),"Élevé - FE PA générique",IF(W27<>"","À vérifier","Moyen")) -> Élevé - FE PA générique | U27: CHICAS/Breaking Stab | V27: EcovaMED v0.7 + hypothèses internes explicites | X27: =IF(A27="","",IF(OR(ISNUMBER(SEARCH("poche",C27)),ISNUMBER(SEARCH("ampoule",C27)),ISNUMBER(SEARCH("plastique",C27))),"Prêt à être dilué / administré (hypothèse)","Reconstitution nécessaire (hypothèse)")) -> Reconstitution nécessaire (hypothèse) | Y27: =IF(A27="","",IF(ISNUMBER(SEARCH("Reconstitution",X27)),"Flacon/poudre : ajout par défaut 1 seringue + 1 aiguille ; à revalider selon présentation exacte.","Ampoule/poche/présentation solution : aucun DM de reconstitution ajouté ; DM de perfusion calculés ailleurs.")) -> Flacon/poudre : ajout par défaut 1 seringue + 1 aiguille ; à revalider selon présentation exacte. | Z27: =IF(A27="","",IF(ISNUMBER(SEARCH("Reconstitution",X27)),1,0)) -> 1 | AA27: =IF(Z27>0,"SERINGUE_PP_24ML","") -> SERINGUE_PP_24ML | AB27: =IF(Z27>0,Z27*VLOOKUP(AA27,FACTEURS_ITEMS!$A$3:$J$30,4,FALSE()),0) -> 0.069 | AC27: =IF(A27="","",IF(ISNUMBER(SEARCH("Reconstitution",X27)),1,0)) -> 1 | AD27: =IF(AC27>0,"AIGUILLE_RECONSTITUTION","") -> AIGUILLE_RECONSTITUTION | AE27: =IF(AC27>0,AC27*VLOOKUP(AD27,FACTEURS_ITEMS!$A$3:$J$30,4,FALSE()),0) -> 0.01 | AF27: =IF(A27="","",AB27+AE27) -> 0.079 | AG27: =IF(A27="","",S27+AF27) -> 0.262125 | AH27: =IF(A27="","",IF(AF27>0,"ACV médicament incluant PA + conditionnement + DM de reconstitution. Ne comprend pas poche/solvant/tubulure/administration.","ACV médicament sans DM de reconstitution ajouté.")) -> ACV médicament incluant PA + conditionnement + DM de reconstitution. Ne comprend pas poche/solvant/tubulure/administration.
A28: Ampicilline | B28: Flacon 2 g | C28: flacon verre | D28: Ampicilline | E28: 2000 | J28: =IFERROR(SUM(E28,G28,I28)/1000,"") -> 2 | K28: =$E$4 -> 100 | L28: =IF(J28="","",J28/1000*K28*(1+$E$5/100)) -> 0.21 | M28: =IF(J28="","",J28/1000*$E$6) -> 0.00019 | N28: =IF(C28="ampoule verre",$E$12,IF(C28="poche PEA",$E$13,$E$11)) -> 10 | O28: =IF(C28="ampoule verre",$E$8,IF(C28="poche PEA",$E$9,$E$7)) -> 7.1 | P28: =N28/1000*O28*(1+$E$5/100) -> 0.07455 | Q28: =$E$14 -> 3 | R28: =Q28/1000*$E$10 -> 0.00348 | S28: =IF(J28="","",SUM(L28:M28,P28,R28)) -> 0.28822 | T28: =IF(OR(J28="",K28=$E$4),"Élevé - FE PA générique",IF(W28<>"","À vérifier","Moyen")) -> Élevé - FE PA générique | U28: CHICAS/Breaking Stab | V28: EcovaMED v0.7 + hypothèses internes explicites | X28: =IF(A28="","",IF(OR(ISNUMBER(SEARCH("poche",C28)),ISNUMBER(SEARCH("ampoule",C28)),ISNUMBER(SEARCH("plastique",C28))),"Prêt à être dilué / administré (hypothèse)","Reconstitution nécessaire (hypothèse)")) -> Reconstitution nécessaire (hypothèse) | Y28: =IF(A28="","",IF(ISNUMBER(SEARCH("Reconstitution",X28)),"Flacon/poudre : ajout par défaut 1 seringue + 1 aiguille ; à revalider selon présentation exacte.","Ampoule/poche/présentation solution : aucun DM de reconstitution ajouté ; DM de perfusion calculés ailleurs.")) -> Flacon/poudre : ajout par défaut 1 seringue + 1 aiguille ; à revalider selon présentation exacte. | Z28: =IF(A28="","",IF(ISNUMBER(SEARCH("Reconstitution",X28)),1,0)) -> 1 | AA28: =IF(Z28>0,"SERINGUE_PP_24ML","") -> SERINGUE_PP_24ML | AB28: =IF(Z28>0,Z28*VLOOKUP(AA28,FACTEURS_ITEMS!$A$3:$J$30,4,FALSE()),0) -> 0.069 | AC28: =IF(A28="","",IF(ISNUMBER(SEARCH("Reconstitution",X28)),1,0)) -> 1 | AD28: =IF(AC28>0,"AIGUILLE_RECONSTITUTION","") -> AIGUILLE_RECONSTITUTION | AE28: =IF(AC28>0,AC28*VLOOKUP(AD28,FACTEURS_ITEMS!$A$3:$J$30,4,FALSE()),0) -> 0.01 | AF28: =IF(A28="","",AB28+AE28) -> 0.079 | AG28: =IF(A28="","",S28+AF28) -> 0.36722 | AH28: =IF(A28="","",IF(AF28>0,"ACV médicament incluant PA + conditionnement + DM de reconstitution. Ne comprend pas poche/solvant/tubulure/administration.","ACV médicament sans DM de reconstitution ajouté.")) -> ACV médicament incluant PA + conditionnement + DM de reconstitution. Ne comprend pas poche/solvant/tubulure/administration.
A29: Artesunate | B29: Flacon 60 mg | C29: flacon verre | D29: Artésunate | E29: 60 | J29: =IFERROR(SUM(E29,G29,I29)/1000,"") -> 0.06 | K29: =$E$4 -> 100 | L29: =IF(J29="","",J29/1000*K29*(1+$E$5/100)) -> 0.0063 | M29: =IF(J29="","",J29/1000*$E$6) -> 5.7e-06 | N29: =IF(C29="ampoule verre",$E$12,IF(C29="poche PEA",$E$13,$E$11)) -> 10 | O29: =IF(C29="ampoule verre",$E$8,IF(C29="poche PEA",$E$9,$E$7)) -> 7.1 | P29: =N29/1000*O29*(1+$E$5/100) -> 0.07455 | Q29: =$E$14 -> 3 | R29: =Q29/1000*$E$10 -> 0.00348 | S29: =IF(J29="","",SUM(L29:M29,P29,R29)) -> 0.0843357 | T29: =IF(OR(J29="",K29=$E$4),"Élevé - FE PA générique",IF(W29<>"","À vérifier","Moyen")) -> Élevé - FE PA générique | U29: Breaking Stab | V29: EcovaMED v0.7 + hypothèses internes explicites | X29: =IF(A29="","",IF(OR(ISNUMBER(SEARCH("poche",C29)),ISNUMBER(SEARCH("ampoule",C29)),ISNUMBER(SEARCH("plastique",C29))),"Prêt à être dilué / administré (hypothèse)","Reconstitution nécessaire (hypothèse)")) -> Reconstitution nécessaire (hypothèse) | Y29: =IF(A29="","",IF(ISNUMBER(SEARCH("Reconstitution",X29)),"Flacon/poudre : ajout par défaut 1 seringue + 1 aiguille ; à revalider selon présentation exacte.","Ampoule/poche/présentation solution : aucun DM de reconstitution ajouté ; DM de perfusion calculés ailleurs.")) -> Flacon/poudre : ajout par défaut 1 seringue + 1 aiguille ; à revalider selon présentation exacte. | Z29: =IF(A29="","",IF(ISNUMBER(SEARCH("Reconstitution",X29)),1,0)) -> 1 | AA29: =IF(Z29>0,"SERINGUE_PP_24ML","") -> SERINGUE_PP_24ML | AB29: =IF(Z29>0,Z29*VLOOKUP(AA29,FACTEURS_ITEMS!$A$3:$J$30,4,FALSE()),0) -> 0.069 | AC29: =IF(A29="","",IF(ISNUMBER(SEARCH("Reconstitution",X29)),1,0)) -> 1 | AD29: =IF(AC29>0,"AIGUILLE_RECONSTITUTION","") -> AIGUILLE_RECONSTITUTION | AE29: =IF(AC29>0,AC29*VLOOKUP(AD29,FACTEURS_ITEMS!$A$3:$J$30,4,FALSE()),0) -> 0.01 | AF29: =IF(A29="","",AB29+AE29) -> 0.079 | AG29: =IF(A29="","",S29+AF29) -> 0.1633357 | AH29: =IF(A29="","",IF(AF29>0,"ACV médicament incluant PA + conditionnement + DM de reconstitution. Ne comprend pas poche/solvant/tubulure/administration.","ACV médicament sans DM de reconstitution ajouté.")) -> ACV médicament incluant PA + conditionnement + DM de reconstitution. Ne comprend pas poche/solvant/tubulure/administration.
A30: Aztréonam | B30: Flacon 1 g | C30: flacon verre | D30: Aztréonam | E30: 1000 | J30: =IFERROR(SUM(E30,G30,I30)/1000,"") -> 1 | K30: =$E$4 -> 100 | L30: =IF(J30="","",J30/1000*K30*(1+$E$5/100)) -> 0.105 | M30: =IF(J30="","",J30/1000*$E$6) -> 9.5e-05 | N30: =IF(C30="ampoule verre",$E$12,IF(C30="poche PEA",$E$13,$E$11)) -> 10 | O30: =IF(C30="ampoule verre",$E$8,IF(C30="poche PEA",$E$9,$E$7)) -> 7.1 | P30: =N30/1000*O30*(1+$E$5/100) -> 0.07455 | Q30: =$E$14 -> 3 | R30: =Q30/1000*$E$10 -> 0.00348 | S30: =IF(J30="","",SUM(L30:M30,P30,R30)) -> 0.183125 | T30: =IF(OR(J30="",K30=$E$4),"Élevé - FE PA générique",IF(W30<>"","À vérifier","Moyen")) -> Élevé - FE PA générique | U30: Breaking Stab | V30: EcovaMED v0.7 + hypothèses internes explicites | X30: =IF(A30="","",IF(OR(ISNUMBER(SEARCH("poche",C30)),ISNUMBER(SEARCH("ampoule",C30)),ISNUMBER(SEARCH("plastique",C30))),"Prêt à être dilué / administré (hypothèse)","Reconstitution nécessaire (hypothèse)")) -> Reconstitution nécessaire (hypothèse) | Y30: =IF(A30="","",IF(ISNUMBER(SEARCH("Reconstitution",X30)),"Flacon/poudre : ajout par défaut 1 seringue + 1 aiguille ; à revalider selon présentation exacte.","Ampoule/poche/présentation solution : aucun DM de reconstitution ajouté ; DM de perfusion calculés ailleurs.")) -> Flacon/poudre : ajout par défaut 1 seringue + 1 aiguille ; à revalider selon présentation exacte. | Z30: =IF(A30="","",IF(ISNUMBER(SEARCH("Reconstitution",X30)),1,0)) -> 1 | AA30: =IF(Z30>0,"SERINGUE_PP_24ML","") -> SERINGUE_PP_24ML | AB30: =IF(Z30>0,Z30*VLOOKUP(AA30,FACTEURS_ITEMS!$A$3:$J$30,4,FALSE()),0) -> 0.069 | AC30: =IF(A30="","",IF(ISNUMBER(SEARCH("Reconstitution",X30)),1,0)) -> 1 | AD30: =IF(AC30>0,"AIGUILLE_RECONSTITUTION","") -> AIGUILLE_RECONSTITUTION | AE30: =IF(AC30>0,AC30*VLOOKUP(AD30,FACTEURS_ITEMS!$A$3:$J$30,4,FALSE()),0) -> 0.01 | AF30: =IF(A30="","",AB30+AE30) -> 0.079 | AG30: =IF(A30="","",S30+AF30) -> 0.262125 | AH30: =IF(A30="","",IF(AF30>0,"ACV médicament incluant PA + conditionnement + DM de reconstitution. Ne comprend pas poche/solvant/tubulure/administration.","ACV médicament sans DM de reconstitution ajouté.")) -> ACV médicament incluant PA + conditionnement + DM de reconstitution. Ne comprend pas poche/solvant/tubulure/administration.
A31: Aztréonam | B31: Flacon 2 g | C31: flacon verre | D31: Aztréonam | E31: 2000 | J31: =IFERROR(SUM(E31,G31,I31)/1000,"") -> 2 | K31: =$E$4 -> 100 | L31: =IF(J31="","",J31/1000*K31*(1+$E$5/100)) -> 0.21 | M31: =IF(J31="","",J31/1000*$E$6) -> 0.00019 | N31: =IF(C31="ampoule verre",$E$12,IF(C31="poche PEA",$E$13,$E$11)) -> 10 | O31: =IF(C31="ampoule verre",$E$8,IF(C31="poche PEA",$E$9,$E$7)) -> 7.1 | P31: =N31/1000*O31*(1+$E$5/100) -> 0.07455 | Q31: =$E$14 -> 3 | R31: =Q31/1000*$E$10 -> 0.00348 | S31: =IF(J31="","",SUM(L31:M31,P31,R31)) -> 0.28822 | T31: =IF(OR(J31="",K31=$E$4),"Élevé - FE PA générique",IF(W31<>"","À vérifier","Moyen")) -> Élevé - FE PA générique | U31: Breaking Stab | V31: EcovaMED v0.7 + hypothèses internes explicites | X31: =IF(A31="","",IF(OR(ISNUMBER(SEARCH("poche",C31)),ISNUMBER(SEARCH("ampoule",C31)),ISNUMBER(SEARCH("plastique",C31))),"Prêt à être dilué / administré (hypothèse)","Reconstitution nécessaire (hypothèse)")) -> Reconstitution nécessaire (hypothèse) | Y31: =IF(A31="","",IF(ISNUMBER(SEARCH("Reconstitution",X31)),"Flacon/poudre : ajout par défaut 1 seringue + 1 aiguille ; à revalider selon présentation exacte.","Ampoule/poche/présentation solution : aucun DM de reconstitution ajouté ; DM de perfusion calculés ailleurs.")) -> Flacon/poudre : ajout par défaut 1 seringue + 1 aiguille ; à revalider selon présentation exacte. | Z31: =IF(A31="","",IF(ISNUMBER(SEARCH("Reconstitution",X31)),1,0)) -> 1 | AA31: =IF(Z31>0,"SERINGUE_PP_24ML","") -> SERINGUE_PP_24ML | AB31: =IF(Z31>0,Z31*VLOOKUP(AA31,FACTEURS_ITEMS!$A$3:$J$30,4,FALSE()),0) -> 0.069 | AC31: =IF(A31="","",IF(ISNUMBER(SEARCH("Reconstitution",X31)),1,0)) -> 1 | AD31: =IF(AC31>0,"AIGUILLE_RECONSTITUTION","") -> AIGUILLE_RECONSTITUTION | AE31: =IF(AC31>0,AC31*VLOOKUP(AD31,FACTEURS_ITEMS!$A$3:$J$30,4,FALSE()),0) -> 0.01 | AF31: =IF(A31="","",AB31+AE31) -> 0.079 | AG31: =IF(A31="","",S31+AF31) -> 0.36722 | AH31: =IF(A31="","",IF(AF31>0,"ACV médicament incluant PA + conditionnement + DM de reconstitution. Ne comprend pas poche/solvant/tubulure/administration.","ACV médicament sans DM de reconstitution ajouté.")) -> ACV médicament incluant PA + conditionnement + DM de reconstitution. Ne comprend pas poche/solvant/tubulure/administration.
A32: Benzylpénicilline | B32: Flacon 1 MUI ≈ 0,6 g | C32: flacon verre | D32: Benzylpénicilline | E32: 600 | J32: =IFERROR(SUM(E32,G32,I32)/1000,"") -> 0.6 | K32: =$E$4 -> 100 | L32: =IF(J32="","",J32/1000*K32*(1+$E$5/100)) -> 0.063 | M32: =IF(J32="","",J32/1000*$E$6) -> 5.7e-05 | N32: =IF(C32="ampoule verre",$E$12,IF(C32="poche PEA",$E$13,$E$11)) -> 10 | O32: =IF(C32="ampoule verre",$E$8,IF(C32="poche PEA",$E$9,$E$7)) -> 7.1 | P32: =N32/1000*O32*(1+$E$5/100) -> 0.07455 | Q32: =$E$14 -> 3 | R32: =Q32/1000*$E$10 -> 0.00348 | S32: =IF(J32="","",SUM(L32:M32,P32,R32)) -> 0.141087 | T32: =IF(OR(J32="",K32=$E$4),"Élevé - FE PA générique",IF(W32<>"","À vérifier","Moyen")) -> Élevé - FE PA générique | U32: CHICAS/Breaking Stab ; conversion MUI approximative | V32: EcovaMED v0.7 + hypothèses internes explicites | W32: Conversion MUI→mg utilisée pour ordre de grandeur ; à confirmer avec la présentation locale. | X32: =IF(A32="","",IF(OR(ISNUMBER(SEARCH("poche",C32)),ISNUMBER(SEARCH("ampoule",C32)),ISNUMBER(SEARCH("plastique",C32))),"Prêt à être dilué / administré (hypothèse)","Reconstitution nécessaire (hypothèse)")) -> Reconstitution nécessaire (hypothèse) | Y32: =IF(A32="","",IF(ISNUMBER(SEARCH("Reconstitution",X32)),"Flacon/poudre : ajout par défaut 1 seringue + 1 aiguille ; à revalider selon présentation exacte.","Ampoule/poche/présentation solution : aucun DM de reconstitution ajouté ; DM de perfusion calculés ailleurs.")) -> Flacon/poudre : ajout par défaut 1 seringue + 1 aiguille ; à revalider selon présentation exacte. | Z32: =IF(A32="","",IF(ISNUMBER(SEARCH("Reconstitution",X32)),1,0)) -> 1 | AA32: =IF(Z32>0,"SERINGUE_PP_24ML","") -> SERINGUE_PP_24ML | AB32: =IF(Z32>0,Z32*VLOOKUP(AA32,FACTEURS_ITEMS!$A$3:$J$30,4,FALSE()),0) -> 0.069 | AC32: =IF(A32="","",IF(ISNUMBER(SEARCH("Reconstitution",X32)),1,0)) -> 1 | AD32: =IF(AC32>0,"AIGUILLE_RECONSTITUTION","") -> AIGUILLE_RECONSTITUTION | AE32: =IF(AC32>0,AC32*VLOOKUP(AD32,FACTEURS_ITEMS!$A$3:$J$30,4,FALSE()),0) -> 0.01 | AF32: =IF(A32="","",AB32+AE32) -> 0.079 | AG32: =IF(A32="","",S32+AF32) -> 0.220087 | AH32: =IF(A32="","",IF(AF32>0,"ACV médicament incluant PA + conditionnement + DM de reconstitution. Ne comprend pas poche/solvant/tubulure/administration.","ACV médicament sans DM de reconstitution ajouté.")) -> ACV médicament incluant PA + conditionnement + DM de reconstitution. Ne comprend pas poche/solvant/tubulure/administration.
A33: Benzylpénicilline | B33: Flacon 5 MUI ≈ 3 g | C33: flacon verre | D33: Benzylpénicilline | E33: 3000 | J33: =IFERROR(SUM(E33,G33,I33)/1000,"") -> 3 | K33: =$E$4 -> 100 | L33: =IF(J33="","",J33/1000*K33*(1+$E$5/100)) -> 0.315 | M33: =IF(J33="","",J33/1000*$E$6) -> 0.000285 | N33: =IF(C33="ampoule verre",$E$12,IF(C33="poche PEA",$E$13,$E$11)) -> 10 | O33: =IF(C33="ampoule verre",$E$8,IF(C33="poche PEA",$E$9,$E$7)) -> 7.1 | P33: =N33/1000*O33*(1+$E$5/100) -> 0.07455 | Q33: =$E$14 -> 3 | R33: =Q33/1000*$E$10 -> 0.00348 | S33: =IF(J33="","",SUM(L33:M33,P33,R33)) -> 0.393315 | T33: =IF(OR(J33="",K33=$E$4),"Élevé - FE PA générique",IF(W33<>"","À vérifier","Moyen")) -> Élevé - FE PA générique | U33: CHICAS/Breaking Stab ; conversion MUI approximative | V33: EcovaMED v0.7 + hypothèses internes explicites | W33: Conversion MUI→mg utilisée pour ordre de grandeur ; à confirmer avec la présentation locale. | X33: =IF(A33="","",IF(OR(ISNUMBER(SEARCH("poche",C33)),ISNUMBER(SEARCH("ampoule",C33)),ISNUMBER(SEARCH("plastique",C33))),"Prêt à être dilué / administré (hypothèse)","Reconstitution nécessaire (hypothèse)")) -> Reconstitution nécessaire (hypothèse) | Y33: =IF(A33="","",IF(ISNUMBER(SEARCH("Reconstitution",X33)),"Flacon/poudre : ajout par défaut 1 seringue + 1 aiguille ; à revalider selon présentation exacte.","Ampoule/poche/présentation solution : aucun DM de reconstitution ajouté ; DM de perfusion calculés ailleurs.")) -> Flacon/poudre : ajout par défaut 1 seringue + 1 aiguille ; à revalider selon présentation exacte. | Z33: =IF(A33="","",IF(ISNUMBER(SEARCH("Reconstitution",X33)),1,0)) -> 1 | AA33: =IF(Z33>0,"SERINGUE_PP_24ML","") -> SERINGUE_PP_24ML | AB33: =IF(Z33>0,Z33*VLOOKUP(AA33,FACTEURS_ITEMS!$A$3:$J$30,4,FALSE()),0) -> 0.069 | AC33: =IF(A33="","",IF(ISNUMBER(SEARCH("Reconstitution",X33)),1,0)) -> 1 | AD33: =IF(AC33>0,"AIGUILLE_RECONSTITUTION","") -> AIGUILLE_RECONSTITUTION | AE33: =IF(AC33>0,AC33*VLOOKUP(AD33,FACTEURS_ITEMS!$A$3:$J$30,4,FALSE()),0) -> 0.01 | AF33: =IF(A33="","",AB33+AE33) -> 0.079 | AG33: =IF(A33="","",S33+AF33) -> 0.472315 | AH33: =IF(A33="","",IF(AF33>0,"ACV médicament incluant PA + conditionnement + DM de reconstitution. Ne comprend pas poche/solvant/tubulure/administration.","ACV médicament sans DM de reconstitution ajouté.")) -> ACV médicament incluant PA + conditionnement + DM de reconstitution. Ne comprend pas poche/solvant/tubulure/administration.
A34: Benzylpénicilline | B34: Flacon 10 MUI ≈ 6 g | C34: flacon verre | D34: Benzylpénicilline | E34: 6000 | J34: =IFERROR(SUM(E34,G34,I34)/1000,"") -> 6 | K34: =$E$4 -> 100 | L34: =IF(J34="","",J34/1000*K34*(1+$E$5/100)) -> 0.63 | M34: =IF(J34="","",J34/1000*$E$6) -> 0.00057 | N34: =IF(C34="ampoule verre",$E$12,IF(C34="poche PEA",$E$13,$E$11)) -> 10 | O34: =IF(C34="ampoule verre",$E$8,IF(C34="poche PEA",$E$9,$E$7)) -> 7.1 | P34: =N34/1000*O34*(1+$E$5/100) -> 0.07455 | Q34: =$E$14 -> 3 | R34: =Q34/1000*$E$10 -> 0.00348 | S34: =IF(J34="","",SUM(L34:M34,P34,R34)) -> 0.7086 | T34: =IF(OR(J34="",K34=$E$4),"Élevé - FE PA générique",IF(W34<>"","À vérifier","Moyen")) -> Élevé - FE PA générique | U34: CHICAS/Breaking Stab ; conversion MUI approximative | V34: EcovaMED v0.7 + hypothèses internes explicites | W34: Conversion MUI→mg utilisée pour ordre de grandeur ; à confirmer avec la présentation locale. | X34: =IF(A34="","",IF(OR(ISNUMBER(SEARCH("poche",C34)),ISNUMBER(SEARCH("ampoule",C34)),ISNUMBER(SEARCH("plastique",C34))),"Prêt à être dilué / administré (hypothèse)","Reconstitution nécessaire (hypothèse)")) -> Reconstitution nécessaire (hypothèse) | Y34: =IF(A34="","",IF(ISNUMBER(SEARCH("Reconstitution",X34)),"Flacon/poudre : ajout par défaut 1 seringue + 1 aiguille ; à revalider selon présentation exacte.","Ampoule/poche/présentation solution : aucun DM de reconstitution ajouté ; DM de perfusion calculés ailleurs.")) -> Flacon/poudre : ajout par défaut 1 seringue + 1 aiguille ; à revalider selon présentation exacte. | Z34: =IF(A34="","",IF(ISNUMBER(SEARCH("Reconstitution",X34)),1,0)) -> 1 | AA34: =IF(Z34>0,"SERINGUE_PP_24ML","") -> SERINGUE_PP_24ML | AB34: =IF(Z34>0,Z34*VLOOKUP(AA34,FACTEURS_ITEMS!$A$3:$J$30,4,FALSE()),0) -> 0.069 | AC34: =IF(A34="","",IF(ISNUMBER(SEARCH("Reconstitution",X34)),1,0)) -> 1 | AD34: =IF(AC34>0,"AIGUILLE_RECONSTITUTION","") -> AIGUILLE_RECONSTITUTION | AE34: =IF(AC34>0,AC34*VLOOKUP(AD34,FACTEURS_ITEMS!$A$3:$J$30,4,FALSE()),0) -> 0.01 | AF34: =IF(A34="","",AB34+AE34) -> 0.079 | AG34: =IF(A34="","",S34+AF34) -> 0.7876 | AH34: =IF(A34="","",IF(AF34>0,"ACV médicament incluant PA + conditionnement + DM de reconstitution. Ne comprend pas poche/solvant/tubulure/administration.","ACV médicament sans DM de reconstitution ajouté.")) -> ACV médicament incluant PA + conditionnement + DM de reconstitution. Ne comprend pas poche/solvant/tubulure/administration.
A35: Caspofungine | B35: Flacon 50 mg | C35: flacon verre | D35: Caspofungine | E35: 50 | J35: =IFERROR(SUM(E35,G35,I35)/1000,"") -> 0.05 | K35: =$E$4 -> 100 | L35: =IF(J35="","",J35/1000*K35*(1+$E$5/100)) -> 0.00525 | M35: =IF(J35="","",J35/1000*$E$6) -> 4.75e-06 | N35: =IF(C35="ampoule verre",$E$12,IF(C35="poche PEA",$E$13,$E$11)) -> 10 | O35: =IF(C35="ampoule verre",$E$8,IF(C35="poche PEA",$E$9,$E$7)) -> 7.1 | P35: =N35/1000*O35*(1+$E$5/100) -> 0.07455 | Q35: =$E$14 -> 3 | R35: =Q35/1000*$E$10 -> 0.00348 | S35: =IF(J35="","",SUM(L35:M35,P35,R35)) -> 0.08328475 | T35: =IF(OR(J35="",K35=$E$4),"Élevé - FE PA générique",IF(W35<>"","À vérifier","Moyen")) -> Élevé - FE PA générique | U35: Breaking Stab | V35: EcovaMED v0.7 + hypothèses internes explicites | X35: =IF(A35="","",IF(OR(ISNUMBER(SEARCH("poche",C35)),ISNUMBER(SEARCH("ampoule",C35)),ISNUMBER(SEARCH("plastique",C35))),"Prêt à être dilué / administré (hypothèse)","Reconstitution nécessaire (hypothèse)")) -> Reconstitution nécessaire (hypothèse) | Y35: =IF(A35="","",IF(ISNUMBER(SEARCH("Reconstitution",X35)),"Flacon/poudre : ajout par défaut 1 seringue + 1 aiguille ; à revalider selon présentation exacte.","Ampoule/poche/présentation solution : aucun DM de reconstitution ajouté ; DM de perfusion calculés ailleurs.")) -> Flacon/poudre : ajout par défaut 1 seringue + 1 aiguille ; à revalider selon présentation exacte. | Z35: =IF(A35="","",IF(ISNUMBER(SEARCH("Reconstitution",X35)),1,0)) -> 1 | AA35: =IF(Z35>0,"SERINGUE_PP_24ML","") -> SERINGUE_PP_24ML | AB35: =IF(Z35>0,Z35*VLOOKUP(AA35,FACTEURS_ITEMS!$A$3:$J$30,4,FALSE()),0) -> 0.069 | AC35: =IF(A35="","",IF(ISNUMBER(SEARCH("Reconstitution",X35)),1,0)) -> 1 | AD35: =IF(AC35>0,"AIGUILLE_RECONSTITUTION","") -> AIGUILLE_RECONSTITUTION | AE35: =IF(AC35>0,AC35*VLOOKUP(AD35,FACTEURS_ITEMS!$A$3:$J$30,4,FALSE()),0) -> 0.01 | AF35: =IF(A35="","",AB35+AE35) -> 0.079 | AG35: =IF(A35="","",S35+AF35) -> 0.16228475 | AH35: =IF(A35="","",IF(AF35>0,"ACV médicament incluant PA + conditionnement + DM de reconstitution. Ne comprend pas poche/solvant/tubulure/administration.","ACV médicament sans DM de reconstitution ajouté.")) -> ACV médicament incluant PA + conditionnement + DM de reconstitution. Ne comprend pas poche/solvant/tubulure/administration.
A36: Caspofungine | B36: Flacon 70 mg | C36: flacon verre | D36: Caspofungine | E36: 70 | J36: =IFERROR(SUM(E36,G36,I36)/1000,"") -> 0.07 | K36: =$E$4 -> 100 | L36: =IF(J36="","",J36/1000*K36*(1+$E$5/100)) -> 0.00735 | M36: =IF(J36="","",J36/1000*$E$6) -> 6.65e-06 | N36: =IF(C36="ampoule verre",$E$12,IF(C36="poche PEA",$E$13,$E$11)) -> 10 | O36: =IF(C36="ampoule verre",$E$8,IF(C36="poche PEA",$E$9,$E$7)) -> 7.1 | P36: =N36/1000*O36*(1+$E$5/100) -> 0.07455 | Q36: =$E$14 -> 3 | R36: =Q36/1000*$E$10 -> 0.00348 | S36: =IF(J36="","",SUM(L36:M36,P36,R36)) -> 0.08538665 | T36: =IF(OR(J36="",K36=$E$4),"Élevé - FE PA générique",IF(W36<>"","À vérifier","Moyen")) -> Élevé - FE PA générique | U36: Breaking Stab | V36: EcovaMED v0.7 + hypothèses internes explicites | X36: =IF(A36="","",IF(OR(ISNUMBER(SEARCH("poche",C36)),ISNUMBER(SEARCH("ampoule",C36)),ISNUMBER(SEARCH("plastique",C36))),"Prêt à être dilué / administré (hypothèse)","Reconstitution nécessaire (hypothèse)")) -> Reconstitution nécessaire (hypothèse) | Y36: =IF(A36="","",IF(ISNUMBER(SEARCH("Reconstitution",X36)),"Flacon/poudre : ajout par défaut 1 seringue + 1 aiguille ; à revalider selon présentation exacte.","Ampoule/poche/présentation solution : aucun DM de reconstitution ajouté ; DM de perfusion calculés ailleurs.")) -> Flacon/poudre : ajout par défaut 1 seringue + 1 aiguille ; à revalider selon présentation exacte. | Z36: =IF(A36="","",IF(ISNUMBER(SEARCH("Reconstitution",X36)),1,0)) -> 1 | AA36: =IF(Z36>0,"SERINGUE_PP_24ML","") -> SERINGUE_PP_24ML | AB36: =IF(Z36>0,Z36*VLOOKUP(AA36,FACTEURS_ITEMS!$A$3:$J$30,4,FALSE()),0) -> 0.069 | AC36: =IF(A36="","",IF(ISNUMBER(SEARCH("Reconstitution",X36)),1,0)) -> 1 | AD36: =IF(AC36>0,"AIGUILLE_RECONSTITUTION","") -> AIGUILLE_RECONSTITUTION | AE36: =IF(AC36>0,AC36*VLOOKUP(AD36,FACTEURS_ITEMS!$A$3:$J$30,4,FALSE()),0) -> 0.01 | AF36: =IF(A36="","",AB36+AE36) -> 0.079 | AG36: =IF(A36="","",S36+AF36) -> 0.16438665 | AH36: =IF(A36="","",IF(AF36>0,"ACV médicament incluant PA + conditionnement + DM de reconstitution. Ne comprend pas poche/solvant/tubulure/administration.","ACV médicament sans DM de reconstitution ajouté.")) -> ACV médicament incluant PA + conditionnement + DM de reconstitution. Ne comprend pas poche/solvant/tubulure/administration.
A37: Céfazoline | B37: Flacon 1 g | C37: flacon verre | D37: Céfazoline | E37: 1000 | J37: =IFERROR(SUM(E37,G37,I37)/1000,"") -> 1 | K37: =$E$4 -> 100 | L37: =IF(J37="","",J37/1000*K37*(1+$E$5/100)) -> 0.105 | M37: =IF(J37="","",J37/1000*$E$6) -> 9.5e-05 | N37: =IF(C37="ampoule verre",$E$12,IF(C37="poche PEA",$E$13,$E$11)) -> 10 | O37: =IF(C37="ampoule verre",$E$8,IF(C37="poche PEA",$E$9,$E$7)) -> 7.1 | P37: =N37/1000*O37*(1+$E$5/100) -> 0.07455 | Q37: =$E$14 -> 3 | R37: =Q37/1000*$E$10 -> 0.00348 | S37: =IF(J37="","",SUM(L37:M37,P37,R37)) -> 0.183125 | T37: =IF(OR(J37="",K37=$E$4),"Élevé - FE PA générique",IF(W37<>"","À vérifier","Moyen")) -> Élevé - FE PA générique | U37: Breaking Stab | V37: EcovaMED v0.7 + hypothèses internes explicites | X37: =IF(A37="","",IF(OR(ISNUMBER(SEARCH("poche",C37)),ISNUMBER(SEARCH("ampoule",C37)),ISNUMBER(SEARCH("plastique",C37))),"Prêt à être dilué / administré (hypothèse)","Reconstitution nécessaire (hypothèse)")) -> Reconstitution nécessaire (hypothèse) | Y37: =IF(A37="","",IF(ISNUMBER(SEARCH("Reconstitution",X37)),"Flacon/poudre : ajout par défaut 1 seringue + 1 aiguille ; à revalider selon présentation exacte.","Ampoule/poche/présentation solution : aucun DM de reconstitution ajouté ; DM de perfusion calculés ailleurs.")) -> Flacon/poudre : ajout par défaut 1 seringue + 1 aiguille ; à revalider selon présentation exacte. | Z37: =IF(A37="","",IF(ISNUMBER(SEARCH("Reconstitution",X37)),1,0)) -> 1 | AA37: =IF(Z37>0,"SERINGUE_PP_24ML","") -> SERINGUE_PP_24ML | AB37: =IF(Z37>0,Z37*VLOOKUP(AA37,FACTEURS_ITEMS!$A$3:$J$30,4,FALSE()),0) -> 0.069 | AC37: =IF(A37="","",IF(ISNUMBER(SEARCH("Reconstitution",X37)),1,0)) -> 1 | AD37: =IF(AC37>0,"AIGUILLE_RECONSTITUTION","") -> AIGUILLE_RECONSTITUTION | AE37: =IF(AC37>0,AC37*VLOOKUP(AD37,FACTEURS_ITEMS!$A$3:$J$30,4,FALSE()),0) -> 0.01 | AF37: =IF(A37="","",AB37+AE37) -> 0.079 | AG37: =IF(A37="","",S37+AF37) -> 0.262125 | AH37: =IF(A37="","",IF(AF37>0,"ACV médicament incluant PA + conditionnement + DM de reconstitution. Ne comprend pas poche/solvant/tubulure/administration.","ACV médicament sans DM de reconstitution ajouté.")) -> ACV médicament incluant PA + conditionnement + DM de reconstitution. Ne comprend pas poche/solvant/tubulure/administration.
A38: Céfazoline | B38: Flacon 2 g | C38: flacon verre | D38: Céfazoline | E38: 2000 | J38: =IFERROR(SUM(E38,G38,I38)/1000,"") -> 2 | K38: =$E$4 -> 100 | L38: =IF(J38="","",J38/1000*K38*(1+$E$5/100)) -> 0.21 | M38: =IF(J38="","",J38/1000*$E$6) -> 0.00019 | N38: =IF(C38="ampoule verre",$E$12,IF(C38="poche PEA",$E$13,$E$11)) -> 10 | O38: =IF(C38="ampoule verre",$E$8,IF(C38="poche PEA",$E$9,$E$7)) -> 7.1 | P38: =N38/1000*O38*(1+$E$5/100) -> 0.07455 | Q38: =$E$14 -> 3 | R38: =Q38/1000*$E$10 -> 0.00348 | S38: =IF(J38="","",SUM(L38:M38,P38,R38)) -> 0.28822 | T38: =IF(OR(J38="",K38=$E$4),"Élevé - FE PA générique",IF(W38<>"","À vérifier","Moyen")) -> Élevé - FE PA générique | U38: Breaking Stab | V38: EcovaMED v0.7 + hypothèses internes explicites | X38: =IF(A38="","",IF(OR(ISNUMBER(SEARCH("poche",C38)),ISNUMBER(SEARCH("ampoule",C38)),ISNUMBER(SEARCH("plastique",C38))),"Prêt à être dilué / administré (hypothèse)","Reconstitution nécessaire (hypothèse)")) -> Reconstitution nécessaire (hypothèse) | Y38: =IF(A38="","",IF(ISNUMBER(SEARCH("Reconstitution",X38)),"Flacon/poudre : ajout par défaut 1 seringue + 1 aiguille ; à revalider selon présentation exacte.","Ampoule/poche/présentation solution : aucun DM de reconstitution ajouté ; DM de perfusion calculés ailleurs.")) -> Flacon/poudre : ajout par défaut 1 seringue + 1 aiguille ; à revalider selon présentation exacte. | Z38: =IF(A38="","",IF(ISNUMBER(SEARCH("Reconstitution",X38)),1,0)) -> 1 | AA38: =IF(Z38>0,"SERINGUE_PP_24ML","") -> SERINGUE_PP_24ML | AB38: =IF(Z38>0,Z38*VLOOKUP(AA38,FACTEURS_ITEMS!$A$3:$J$30,4,FALSE()),0) -> 0.069 | AC38: =IF(A38="","",IF(ISNUMBER(SEARCH("Reconstitution",X38)),1,0)) -> 1 | AD38: =IF(AC38>0,"AIGUILLE_RECONSTITUTION","") -> AIGUILLE_RECONSTITUTION | AE38: =IF(AC38>0,AC38*VLOOKUP(AD38,FACTEURS_ITEMS!$A$3:$J$30,4,FALSE()),0) -> 0.01 | AF38: =IF(A38="","",AB38+AE38) -> 0.079 | AG38: =IF(A38="","",S38+AF38) -> 0.36722 | AH38: =IF(A38="","",IF(AF38>0,"ACV médicament incluant PA + conditionnement + DM de reconstitution. Ne comprend pas poche/solvant/tubulure/administration.","ACV médicament sans DM de reconstitution ajouté.")) -> ACV médicament incluant PA + conditionnement + DM de reconstitution. Ne comprend pas poche/solvant/tubulure/administration.
A39: Céfépime | B39: Flacon 1 g | C39: flacon verre | D39: Céfépime | E39: 1000 | J39: =IFERROR(SUM(E39,G39,I39)/1000,"") -> 1 | K39: =$E$4 -> 100 | L39: =IF(J39="","",J39/1000*K39*(1+$E$5/100)) -> 0.105 | M39: =IF(J39="","",J39/1000*$E$6) -> 9.5e-05 | N39: =IF(C39="ampoule verre",$E$12,IF(C39="poche PEA",$E$13,$E$11)) -> 10 | O39: =IF(C39="ampoule verre",$E$8,IF(C39="poche PEA",$E$9,$E$7)) -> 7.1 | P39: =N39/1000*O39*(1+$E$5/100) -> 0.07455 | Q39: =$E$14 -> 3 | R39: =Q39/1000*$E$10 -> 0.00348 | S39: =IF(J39="","",SUM(L39:M39,P39,R39)) -> 0.183125 | T39: =IF(OR(J39="",K39=$E$4),"Élevé - FE PA générique",IF(W39<>"","À vérifier","Moyen")) -> Élevé - FE PA générique | U39: Breaking Stab | V39: EcovaMED v0.7 + hypothèses internes explicites | X39: =IF(A39="","",IF(OR(ISNUMBER(SEARCH("poche",C39)),ISNUMBER(SEARCH("ampoule",C39)),ISNUMBER(SEARCH("plastique",C39))),"Prêt à être dilué / administré (hypothèse)","Reconstitution nécessaire (hypothèse)")) -> Reconstitution nécessaire (hypothèse) | Y39: =IF(A39="","",IF(ISNUMBER(SEARCH("Reconstitution",X39)),"Flacon/poudre : ajout par défaut 1 seringue + 1 aiguille ; à revalider selon présentation exacte.","Ampoule/poche/présentation solution : aucun DM de reconstitution ajouté ; DM de perfusion calculés ailleurs.")) -> Flacon/poudre : ajout par défaut 1 seringue + 1 aiguille ; à revalider selon présentation exacte. | Z39: =IF(A39="","",IF(ISNUMBER(SEARCH("Reconstitution",X39)),1,0)) -> 1 | AA39: =IF(Z39>0,"SERINGUE_PP_24ML","") -> SERINGUE_PP_24ML | AB39: =IF(Z39>0,Z39*VLOOKUP(AA39,FACTEURS_ITEMS!$A$3:$J$30,4,FALSE()),0) -> 0.069 | AC39: =IF(A39="","",IF(ISNUMBER(SEARCH("Reconstitution",X39)),1,0)) -> 1 | AD39: =IF(AC39>0,"AIGUILLE_RECONSTITUTION","") -> AIGUILLE_RECONSTITUTION | AE39: =IF(AC39>0,AC39*VLOOKUP(AD39,FACTEURS_ITEMS!$A$3:$J$30,4,FALSE()),0) -> 0.01 | AF39: =IF(A39="","",AB39+AE39) -> 0.079 | AG39: =IF(A39="","",S39+AF39) -> 0.262125 | AH39: =IF(A39="","",IF(AF39>0,"ACV médicament incluant PA + conditionnement + DM de reconstitution. Ne comprend pas poche/solvant/tubulure/administration.","ACV médicament sans DM de reconstitution ajouté.")) -> ACV médicament incluant PA + conditionnement + DM de reconstitution. Ne comprend pas poche/solvant/tubulure/administration.
A40: Céfépime | B40: Flacon 2 g | C40: flacon verre | D40: Céfépime | E40: 2000 | J40: =IFERROR(SUM(E40,G40,I40)/1000,"") -> 2 | K40: =$E$4 -> 100 | L40: =IF(J40="","",J40/1000*K40*(1+$E$5/100)) -> 0.21 | M40: =IF(J40="","",J40/1000*$E$6) -> 0.00019 | N40: =IF(C40="ampoule verre",$E$12,IF(C40="poche PEA",$E$13,$E$11)) -> 10 | O40: =IF(C40="ampoule verre",$E$8,IF(C40="poche PEA",$E$9,$E$7)) -> 7.1 | P40: =N40/1000*O40*(1+$E$5/100) -> 0.07455 | Q40: =$E$14 -> 3 | R40: =Q40/1000*$E$10 -> 0.00348 | S40: =IF(J40="","",SUM(L40:M40,P40,R40)) -> 0.28822 | T40: =IF(OR(J40="",K40=$E$4),"Élevé - FE PA générique",IF(W40<>"","À vérifier","Moyen")) -> Élevé - FE PA générique | U40: Breaking Stab | V40: EcovaMED v0.7 + hypothèses internes explicites | X40: =IF(A40="","",IF(OR(ISNUMBER(SEARCH("poche",C40)),ISNUMBER(SEARCH("ampoule",C40)),ISNUMBER(SEARCH("plastique",C40))),"Prêt à être dilué / administré (hypothèse)","Reconstitution nécessaire (hypothèse)")) -> Reconstitution nécessaire (hypothèse) | Y40: =IF(A40="","",IF(ISNUMBER(SEARCH("Reconstitution",X40)),"Flacon/poudre : ajout par défaut 1 seringue + 1 aiguille ; à revalider selon présentation exacte.","Ampoule/poche/présentation solution : aucun DM de reconstitution ajouté ; DM de perfusion calculés ailleurs.")) -> Flacon/poudre : ajout par défaut 1 seringue + 1 aiguille ; à revalider selon présentation exacte. | Z40: =IF(A40="","",IF(ISNUMBER(SEARCH("Reconstitution",X40)),1,0)) -> 1 | AA40: =IF(Z40>0,"SERINGUE_PP_24ML","") -> SERINGUE_PP_24ML | AB40: =IF(Z40>0,Z40*VLOOKUP(AA40,FACTEURS_ITEMS!$A$3:$J$30,4,FALSE()),0) -> 0.069 | AC40: =IF(A40="","",IF(ISNUMBER(SEARCH("Reconstitution",X40)),1,0)) -> 1 | AD40: =IF(AC40>0,"AIGUILLE_RECONSTITUTION","") -> AIGUILLE_RECONSTITUTION | AE40: =IF(AC40>0,AC40*VLOOKUP(AD40,FACTEURS_ITEMS!$A$3:$J$30,4,FALSE()),0) -> 0.01 | AF40: =IF(A40="","",AB40+AE40) -> 0.079 | AG40: =IF(A40="","",S40+AF40) -> 0.36722 | AH40: =IF(A40="","",IF(AF40>0,"ACV médicament incluant PA + conditionnement + DM de reconstitution. Ne comprend pas poche/solvant/tubulure/administration.","ACV médicament sans DM de reconstitution ajouté.")) -> ACV médicament incluant PA + conditionnement + DM de reconstitution. Ne comprend pas poche/solvant/tubulure/administration.
A41: Céfidérocol | B41: Flacon 1 g | C41: flacon verre | D41: Céfidérocol | E41: 1000 | J41: =IFERROR(SUM(E41,G41,I41)/1000,"") -> 1 | K41: =$E$4 -> 100 | L41: =IF(J41="","",J41/1000*K41*(1+$E$5/100)) -> 0.105 | M41: =IF(J41="","",J41/1000*$E$6) -> 9.5e-05 | N41: =IF(C41="ampoule verre",$E$12,IF(C41="poche PEA",$E$13,$E$11)) -> 10 | O41: =IF(C41="ampoule verre",$E$8,IF(C41="poche PEA",$E$9,$E$7)) -> 7.1 | P41: =N41/1000*O41*(1+$E$5/100) -> 0.07455 | Q41: =$E$14 -> 3 | R41: =Q41/1000*$E$10 -> 0.00348 | S41: =IF(J41="","",SUM(L41:M41,P41,R41)) -> 0.183125 | T41: =IF(OR(J41="",K41=$E$4),"Élevé - FE PA générique",IF(W41<>"","À vérifier","Moyen")) -> Élevé - FE PA générique | U41: CHICAS/Breaking Stab | V41: EcovaMED v0.7 + hypothèses internes explicites | X41: =IF(A41="","",IF(OR(ISNUMBER(SEARCH("poche",C41)),ISNUMBER(SEARCH("ampoule",C41)),ISNUMBER(SEARCH("plastique",C41))),"Prêt à être dilué / administré (hypothèse)","Reconstitution nécessaire (hypothèse)")) -> Reconstitution nécessaire (hypothèse) | Y41: =IF(A41="","",IF(ISNUMBER(SEARCH("Reconstitution",X41)),"Flacon/poudre : ajout par défaut 1 seringue + 1 aiguille ; à revalider selon présentation exacte.","Ampoule/poche/présentation solution : aucun DM de reconstitution ajouté ; DM de perfusion calculés ailleurs.")) -> Flacon/poudre : ajout par défaut 1 seringue + 1 aiguille ; à revalider selon présentation exacte. | Z41: =IF(A41="","",IF(ISNUMBER(SEARCH("Reconstitution",X41)),1,0)) -> 1 | AA41: =IF(Z41>0,"SERINGUE_PP_24ML","") -> SERINGUE_PP_24ML | AB41: =IF(Z41>0,Z41*VLOOKUP(AA41,FACTEURS_ITEMS!$A$3:$J$30,4,FALSE()),0) -> 0.069 | AC41: =IF(A41="","",IF(ISNUMBER(SEARCH("Reconstitution",X41)),1,0)) -> 1 | AD41: =IF(AC41>0,"AIGUILLE_RECONSTITUTION","") -> AIGUILLE_RECONSTITUTION | AE41: =IF(AC41>0,AC41*VLOOKUP(AD41,FACTEURS_ITEMS!$A$3:$J$30,4,FALSE()),0) -> 0.01 | AF41: =IF(A41="","",AB41+AE41) -> 0.079 | AG41: =IF(A41="","",S41+AF41) -> 0.262125 | AH41: =IF(A41="","",IF(AF41>0,"ACV médicament incluant PA + conditionnement + DM de reconstitution. Ne comprend pas poche/solvant/tubulure/administration.","ACV médicament sans DM de reconstitution ajouté.")) -> ACV médicament incluant PA + conditionnement + DM de reconstitution. Ne comprend pas poche/solvant/tubulure/administration.
A42: Céfotaxime | B42: Flacon 1 g | C42: flacon verre | D42: Céfotaxime | E42: 1000 | J42: =IFERROR(SUM(E42,G42,I42)/1000,"") -> 1 | K42: =$E$4 -> 100 | L42: =IF(J42="","",J42/1000*K42*(1+$E$5/100)) -> 0.105 | M42: =IF(J42="","",J42/1000*$E$6) -> 9.5e-05 | N42: =IF(C42="ampoule verre",$E$12,IF(C42="poche PEA",$E$13,$E$11)) -> 10 | O42: =IF(C42="ampoule verre",$E$8,IF(C42="poche PEA",$E$9,$E$7)) -> 7.1 | P42: =N42/1000*O42*(1+$E$5/100) -> 0.07455 | Q42: =$E$14 -> 3 | R42: =Q42/1000*$E$10 -> 0.00348 | S42: =IF(J42="","",SUM(L42:M42,P42,R42)) -> 0.183125 | T42: =IF(OR(J42="",K42=$E$4),"Élevé - FE PA générique",IF(W42<>"","À vérifier","Moyen")) -> Élevé - FE PA générique | U42: Breaking Stab | V42: EcovaMED v0.7 + hypothèses internes explicites | X42: =IF(A42="","",IF(OR(ISNUMBER(SEARCH("poche",C42)),ISNUMBER(SEARCH("ampoule",C42)),ISNUMBER(SEARCH("plastique",C42))),"Prêt à être dilué / administré (hypothèse)","Reconstitution nécessaire (hypothèse)")) -> Reconstitution nécessaire (hypothèse) | Y42: =IF(A42="","",IF(ISNUMBER(SEARCH("Reconstitution",X42)),"Flacon/poudre : ajout par défaut 1 seringue + 1 aiguille ; à revalider selon présentation exacte.","Ampoule/poche/présentation solution : aucun DM de reconstitution ajouté ; DM de perfusion calculés ailleurs.")) -> Flacon/poudre : ajout par défaut 1 seringue + 1 aiguille ; à revalider selon présentation exacte. | Z42: =IF(A42="","",IF(ISNUMBER(SEARCH("Reconstitution",X42)),1,0)) -> 1 | AA42: =IF(Z42>0,"SERINGUE_PP_24ML","") -> SERINGUE_PP_24ML | AB42: =IF(Z42>0,Z42*VLOOKUP(AA42,FACTEURS_ITEMS!$A$3:$J$30,4,FALSE()),0) -> 0.069 | AC42: =IF(A42="","",IF(ISNUMBER(SEARCH("Reconstitution",X42)),1,0)) -> 1 | AD42: =IF(AC42>0,"AIGUILLE_RECONSTITUTION","") -> AIGUILLE_RECONSTITUTION | AE42: =IF(AC42>0,AC42*VLOOKUP(AD42,FACTEURS_ITEMS!$A$3:$J$30,4,FALSE()),0) -> 0.01 | AF42: =IF(A42="","",AB42+AE42) -> 0.079 | AG42: =IF(A42="","",S42+AF42) -> 0.262125 | AH42: =IF(A42="","",IF(AF42>0,"ACV médicament incluant PA + conditionnement + DM de reconstitution. Ne comprend pas poche/solvant/tubulure/administration.","ACV médicament sans DM de reconstitution ajouté.")) -> ACV médicament incluant PA + conditionnement + DM de reconstitution. Ne comprend pas poche/solvant/tubulure/administration.
A43: Céfotaxime | B43: Flacon 2 g | C43: flacon verre | D43: Céfotaxime | E43: 2000 | J43: =IFERROR(SUM(E43,G43,I43)/1000,"") -> 2 | K43: =$E$4 -> 100 | L43: =IF(J43="","",J43/1000*K43*(1+$E$5/100)) -> 0.21 | M43: =IF(J43="","",J43/1000*$E$6) -> 0.00019 | N43: =IF(C43="ampoule verre",$E$12,IF(C43="poche PEA",$E$13,$E$11)) -> 10 | O43: =IF(C43="ampoule verre",$E$8,IF(C43="poche PEA",$E$9,$E$7)) -> 7.1 | P43: =N43/1000*O43*(1+$E$5/100) -> 0.07455 | Q43: =$E$14 -> 3 | R43: =Q43/1000*$E$10 -> 0.00348 | S43: =IF(J43="","",SUM(L43:M43,P43,R43)) -> 0.28822 | T43: =IF(OR(J43="",K43=$E$4),"Élevé - FE PA générique",IF(W43<>"","À vérifier","Moyen")) -> Élevé - FE PA générique | U43: Breaking Stab | V43: EcovaMED v0.7 + hypothèses internes explicites | X43: =IF(A43="","",IF(OR(ISNUMBER(SEARCH("poche",C43)),ISNUMBER(SEARCH("ampoule",C43)),ISNUMBER(SEARCH("plastique",C43))),"Prêt à être dilué / administré (hypothèse)","Reconstitution nécessaire (hypothèse)")) -> Reconstitution nécessaire (hypothèse) | Y43: =IF(A43="","",IF(ISNUMBER(SEARCH("Reconstitution",X43)),"Flacon/poudre : ajout par défaut 1 seringue + 1 aiguille ; à revalider selon présentation exacte.","Ampoule/poche/présentation solution : aucun DM de reconstitution ajouté ; DM de perfusion calculés ailleurs.")) -> Flacon/poudre : ajout par défaut 1 seringue + 1 aiguille ; à revalider selon présentation exacte. | Z43: =IF(A43="","",IF(ISNUMBER(SEARCH("Reconstitution",X43)),1,0)) -> 1 | AA43: =IF(Z43>0,"SERINGUE_PP_24ML","") -> SERINGUE_PP_24ML | AB43: =IF(Z43>0,Z43*VLOOKUP(AA43,FACTEURS_ITEMS!$A$3:$J$30,4,FALSE()),0) -> 0.069 | AC43: =IF(A43="","",IF(ISNUMBER(SEARCH("Reconstitution",X43)),1,0)) -> 1 | AD43: =IF(AC43>0,"AIGUILLE_RECONSTITUTION","") -> AIGUILLE_RECONSTITUTION | AE43: =IF(AC43>0,AC43*VLOOKUP(AD43,FACTEURS_ITEMS!$A$3:$J$30,4,FALSE()),0) -> 0.01 | AF43: =IF(A43="","",AB43+AE43) -> 0.079 | AG43: =IF(A43="","",S43+AF43) -> 0.36722 | AH43: =IF(A43="","",IF(AF43>0,"ACV médicament incluant PA + conditionnement + DM de reconstitution. Ne comprend pas poche/solvant/tubulure/administration.","ACV médicament sans DM de reconstitution ajouté.")) -> ACV médicament incluant PA + conditionnement + DM de reconstitution. Ne comprend pas poche/solvant/tubulure/administration.
A44: Ceftazidime | B44: Flacon 1 g | C44: flacon verre | D44: Ceftazidime | E44: 1000 | J44: =IFERROR(SUM(E44,G44,I44)/1000,"") -> 1 | K44: =$E$4 -> 100 | L44: =IF(J44="","",J44/1000*K44*(1+$E$5/100)) -> 0.105 | M44: =IF(J44="","",J44/1000*$E$6) -> 9.5e-05 | N44: =IF(C44="ampoule verre",$E$12,IF(C44="poche PEA",$E$13,$E$11)) -> 10 | O44: =IF(C44="ampoule verre",$E$8,IF(C44="poche PEA",$E$9,$E$7)) -> 7.1 | P44: =N44/1000*O44*(1+$E$5/100) -> 0.07455 | Q44: =$E$14 -> 3 | R44: =Q44/1000*$E$10 -> 0.00348 | S44: =IF(J44="","",SUM(L44:M44,P44,R44)) -> 0.183125 | T44: =IF(OR(J44="",K44=$E$4),"Élevé - FE PA générique",IF(W44<>"","À vérifier","Moyen")) -> Élevé - FE PA générique | U44: Breaking Stab | V44: EcovaMED v0.7 + hypothèses internes explicites | X44: =IF(A44="","",IF(OR(ISNUMBER(SEARCH("poche",C44)),ISNUMBER(SEARCH("ampoule",C44)),ISNUMBER(SEARCH("plastique",C44))),"Prêt à être dilué / administré (hypothèse)","Reconstitution nécessaire (hypothèse)")) -> Reconstitution nécessaire (hypothèse) | Y44: =IF(A44="","",IF(ISNUMBER(SEARCH("Reconstitution",X44)),"Flacon/poudre : ajout par défaut 1 seringue + 1 aiguille ; à revalider selon présentation exacte.","Ampoule/poche/présentation solution : aucun DM de reconstitution ajouté ; DM de perfusion calculés ailleurs.")) -> Flacon/poudre : ajout par défaut 1 seringue + 1 aiguille ; à revalider selon présentation exacte. | Z44: =IF(A44="","",IF(ISNUMBER(SEARCH("Reconstitution",X44)),1,0)) -> 1 | AA44: =IF(Z44>0,"SERINGUE_PP_24ML","") -> SERINGUE_PP_24ML | AB44: =IF(Z44>0,Z44*VLOOKUP(AA44,FACTEURS_ITEMS!$A$3:$J$30,4,FALSE()),0) -> 0.069 | AC44: =IF(A44="","",IF(ISNUMBER(SEARCH("Reconstitution",X44)),1,0)) -> 1 | AD44: =IF(AC44>0,"AIGUILLE_RECONSTITUTION","") -> AIGUILLE_RECONSTITUTION | AE44: =IF(AC44>0,AC44*VLOOKUP(AD44,FACTEURS_ITEMS!$A$3:$J$30,4,FALSE()),0) -> 0.01 | AF44: =IF(A44="","",AB44+AE44) -> 0.079 | AG44: =IF(A44="","",S44+AF44) -> 0.262125 | AH44: =IF(A44="","",IF(AF44>0,"ACV médicament incluant PA + conditionnement + DM de reconstitution. Ne comprend pas poche/solvant/tubulure/administration.","ACV médicament sans DM de reconstitution ajouté.")) -> ACV médicament incluant PA + conditionnement + DM de reconstitution. Ne comprend pas poche/solvant/tubulure/administration.
A45: Ceftazidime | B45: Flacon 2 g | C45: flacon verre | D45: Ceftazidime | E45: 2000 | J45: =IFERROR(SUM(E45,G45,I45)/1000,"") -> 2 | K45: =$E$4 -> 100 | L45: =IF(J45="","",J45/1000*K45*(1+$E$5/100)) -> 0.21 | M45: =IF(J45="","",J45/1000*$E$6) -> 0.00019 | N45: =IF(C45="ampoule verre",$E$12,IF(C45="poche PEA",$E$13,$E$11)) -> 10 | O45: =IF(C45="ampoule verre",$E$8,IF(C45="poche PEA",$E$9,$E$7)) -> 7.1 | P45: =N45/1000*O45*(1+$E$5/100) -> 0.07455 | Q45: =$E$14 -> 3 | R45: =Q45/1000*$E$10 -> 0.00348 | S45: =IF(J45="","",SUM(L45:M45,P45,R45)) -> 0.28822 | T45: =IF(OR(J45="",K45=$E$4),"Élevé - FE PA générique",IF(W45<>"","À vérifier","Moyen")) -> Élevé - FE PA générique | U45: Breaking Stab | V45: EcovaMED v0.7 + hypothèses internes explicites | X45: =IF(A45="","",IF(OR(ISNUMBER(SEARCH("poche",C45)),ISNUMBER(SEARCH("ampoule",C45)),ISNUMBER(SEARCH("plastique",C45))),"Prêt à être dilué / administré (hypothèse)","Reconstitution nécessaire (hypothèse)")) -> Reconstitution nécessaire (hypothèse) | Y45: =IF(A45="","",IF(ISNUMBER(SEARCH("Reconstitution",X45)),"Flacon/poudre : ajout par défaut 1 seringue + 1 aiguille ; à revalider selon présentation exacte.","Ampoule/poche/présentation solution : aucun DM de reconstitution ajouté ; DM de perfusion calculés ailleurs.")) -> Flacon/poudre : ajout par défaut 1 seringue + 1 aiguille ; à revalider selon présentation exacte. | Z45: =IF(A45="","",IF(ISNUMBER(SEARCH("Reconstitution",X45)),1,0)) -> 1 | AA45: =IF(Z45>0,"SERINGUE_PP_24ML","") -> SERINGUE_PP_24ML | AB45: =IF(Z45>0,Z45*VLOOKUP(AA45,FACTEURS_ITEMS!$A$3:$J$30,4,FALSE()),0) -> 0.069 | AC45: =IF(A45="","",IF(ISNUMBER(SEARCH("Reconstitution",X45)),1,0)) -> 1 | AD45: =IF(AC45>0,"AIGUILLE_RECONSTITUTION","") -> AIGUILLE_RECONSTITUTION | AE45: =IF(AC45>0,AC45*VLOOKUP(AD45,FACTEURS_ITEMS!$A$3:$J$30,4,FALSE()),0) -> 0.01 | AF45: =IF(A45="","",AB45+AE45) -> 0.079 | AG45: =IF(A45="","",S45+AF45) -> 0.36722 | AH45: =IF(A45="","",IF(AF45>0,"ACV médicament incluant PA + conditionnement + DM de reconstitution. Ne comprend pas poche/solvant/tubulure/administration.","ACV médicament sans DM de reconstitution ajouté.")) -> ACV médicament incluant PA + conditionnement + DM de reconstitution. Ne comprend pas poche/solvant/tubulure/administration.
A46: Ceftriaxone | B46: Flacon 1 g | C46: flacon verre | D46: Ceftriaxone | E46: 1000 | J46: =IFERROR(SUM(E46,G46,I46)/1000,"") -> 1 | K46: =$E$4 -> 100 | L46: =IF(J46="","",J46/1000*K46*(1+$E$5/100)) -> 0.105 | M46: =IF(J46="","",J46/1000*$E$6) -> 9.5e-05 | N46: =IF(C46="ampoule verre",$E$12,IF(C46="poche PEA",$E$13,$E$11)) -> 10 | O46: =IF(C46="ampoule verre",$E$8,IF(C46="poche PEA",$E$9,$E$7)) -> 7.1 | P46: =N46/1000*O46*(1+$E$5/100) -> 0.07455 | Q46: =$E$14 -> 3 | R46: =Q46/1000*$E$10 -> 0.00348 | S46: =IF(J46="","",SUM(L46:M46,P46,R46)) -> 0.183125 | T46: =IF(OR(J46="",K46=$E$4),"Élevé - FE PA générique",IF(W46<>"","À vérifier","Moyen")) -> Élevé - FE PA générique | U46: Breaking Stab | V46: EcovaMED v0.7 + hypothèses internes explicites | X46: =IF(A46="","",IF(OR(ISNUMBER(SEARCH("poche",C46)),ISNUMBER(SEARCH("ampoule",C46)),ISNUMBER(SEARCH("plastique",C46))),"Prêt à être dilué / administré (hypothèse)","Reconstitution nécessaire (hypothèse)")) -> Reconstitution nécessaire (hypothèse) | Y46: =IF(A46="","",IF(ISNUMBER(SEARCH("Reconstitution",X46)),"Flacon/poudre : ajout par défaut 1 seringue + 1 aiguille ; à revalider selon présentation exacte.","Ampoule/poche/présentation solution : aucun DM de reconstitution ajouté ; DM de perfusion calculés ailleurs.")) -> Flacon/poudre : ajout par défaut 1 seringue + 1 aiguille ; à revalider selon présentation exacte. | Z46: =IF(A46="","",IF(ISNUMBER(SEARCH("Reconstitution",X46)),1,0)) -> 1 | AA46: =IF(Z46>0,"SERINGUE_PP_24ML","") -> SERINGUE_PP_24ML | AB46: =IF(Z46>0,Z46*VLOOKUP(AA46,FACTEURS_ITEMS!$A$3:$J$30,4,FALSE()),0) -> 0.069 | AC46: =IF(A46="","",IF(ISNUMBER(SEARCH("Reconstitution",X46)),1,0)) -> 1 | AD46: =IF(AC46>0,"AIGUILLE_RECONSTITUTION","") -> AIGUILLE_RECONSTITUTION | AE46: =IF(AC46>0,AC46*VLOOKUP(AD46,FACTEURS_ITEMS!$A$3:$J$30,4,FALSE()),0) -> 0.01 | AF46: =IF(A46="","",AB46+AE46) -> 0.079 | AG46: =IF(A46="","",S46+AF46) -> 0.262125 | AH46: =IF(A46="","",IF(AF46>0,"ACV médicament incluant PA + conditionnement + DM de reconstitution. Ne comprend pas poche/solvant/tubulure/administration.","ACV médicament sans DM de reconstitution ajouté.")) -> ACV médicament incluant PA + conditionnement + DM de reconstitution. Ne comprend pas poche/solvant/tubulure/administration.
... A49: Cefuroxime | B49: Flacon 1,5 g | C49: flacon verre | D49: Cefuroxime | E49: 1500 | J49: =IFERROR(SUM(E49,G49,I49)/1000,"") -> 1.5 | K49: =$E$4 -> 100 | L49: =IF(J49="","",J49/1000*K49*(1+$E$5/100)) -> 0.1575 | M49: =IF(J49="","",J49/1000*$E$6) -> 0.0001425 | N49: =IF(C49="ampoule verre",$E$12,IF(C49="poche PEA",$E$13,$E$11)) -> 10 | O49: =IF(C49="ampoule verre",$E$8,IF(C49="poche PEA",$E$9,$E$7)) -> 7.1 | P49: =N49/1000*O49*(1+$E$5/100) -> 0.07455 | Q49: =$E$14 -> 3 | R49: =Q49/1000*$E$10 -> 0.00348 | S49: =IF(J49="","",SUM(L49:M49,P49,R49)) -> 0.2356725 | T49: =IF(OR(J49="",K49=$E$4),"Élevé - FE PA générique",IF(W49<>"","À vérifier","Moyen")) -> Élevé - FE PA générique | U49: Micrel/Breaking Stab | V49: EcovaMED v0.7 + hypothèses internes explicites | X49: =IF(A49="","",IF(OR(ISNUMBER(SEARCH("poche",C49)),ISNUMBER(SEARCH("ampoule",C49)),ISNUMBER(SEARCH("plastique",C49))),"Prêt à être dilué / administré (hypothèse)","Reconstitution nécessaire (hypothèse)")) -> Reconstitution nécessaire (hypothèse) | Y49: =IF(A49="","",IF(ISNUMBER(SEARCH("Reconstitution",X49)),"Flacon/poudre : ajout par défaut 1 seringue + 1 aiguille ; à revalider selon présentation exacte.","Ampoule/poche/présentation solution : aucun DM de reconstitution ajouté ; DM de perfusion calculés ailleurs.")) -> Flacon/poudre : ajout par défaut 1 seringue + 1 aiguille ; à revalider selon présentation exacte. | Z49: =IF(A49="","",IF(ISNUMBER(SEARCH("Reconstitution",X49)),1,0)) -> 1 | AA49: =IF(Z49>0,"SERINGUE_PP_24ML","") -> SERINGUE_PP_24ML | AB49: =IF(Z49>0,Z49*VLOOKUP(AA49,FACTEURS_ITEMS!$A$3:$J$30,4,FALSE()),0) -> 0.069 | AC49: =IF(A49="","",IF(ISNUMBER(SEARCH("Reconstitution",X49)),1,0)) -> 1 | AD49: =IF(AC49>0,"AIGUILLE_RECONSTITUTION","") -> AIGUILLE_RECONSTITUTION | AE49: =IF(AC49>0,AC49*VLOOKUP(AD49,FACTEURS_ITEMS!$A$3:$J$30,4,FALSE()),0) -> 0.01 | AF49: =IF(A49="","",AB49+AE49) -> 0.079 | AG49: =IF(A49="","",S49+AF49) -> 0.3146725 | AH49: =IF(A49="","",IF(AF49>0,"ACV médicament incluant PA + conditionnement + DM de reconstitution. Ne comprend pas poche/solvant/tubulure/administration.","ACV médicament sans DM de reconstitution ajouté.")) -> ACV médicament incluant PA + conditionnement + DM de reconstitution. Ne comprend pas poche/solvant/tubulure/administration.
A50: Ciprofloxacine | B50: Poche prêt-à-l’emploi 200 mg | C50: poche PEA | D50: Ciprofloxacine | E50: 200 | J50: =IFERROR(SUM(E50,G50,I50)/1000,"") -> 0.2 | K50: =$E$4 -> 100 | L50: =IF(J50="","",J50/1000*K50*(1+$E$5/100)) -> 0.021 | M50: =IF(J50="","",J50/1000*$E$6) -> 1.9e-05 | N50: =IF(C50="ampoule verre",$E$12,IF(C50="poche PEA",$E$13,$E$11)) -> 20 | O50: =IF(C50="ampoule verre",$E$8,IF(C50="poche PEA",$E$9,$E$7)) -> 4.2 | P50: =N50/1000*O50*(1+$E$5/100) -> 0.0882 | Q50: =$E$14 -> 3 | R50: =Q50/1000*$E$10 -> 0.00348 | S50: =IF(J50="","",SUM(L50:M50,P50,R50)) -> 0.112699 | T50: =IF(OR(J50="",K50=$E$4),"Élevé - FE PA générique",IF(W50<>"","À vérifier","Moyen")) -> Élevé - FE PA générique | U50: Micrel/Breaking Stab | V50: EcovaMED v0.7 + hypothèses internes explicites | W50: Présentation prêt-à-l’emploi : le conditionnement primaire réel doit être remplacé par le poids fournisseur si disponible. | X50: =IF(A50="","",IF(OR(ISNUMBER(SEARCH("poche",C50)),ISNUMBER(SEARCH("ampoule",C50)),ISNUMBER(SEARCH("plastique",C50))),"Prêt à être dilué / administré (hypothèse)","Reconstitution nécessaire (hypothèse)")) -> Prêt à être dilué / administré (hypothèse) | Y50: =IF(A50="","",IF(ISNUMBER(SEARCH("Reconstitution",X50)),"Flacon/poudre : ajout par défaut 1 seringue + 1 aiguille ; à revalider selon présentation exacte.","Ampoule/poche/présentation solution : aucun DM de reconstitution ajouté ; DM de perfusion calculés ailleurs.")) -> Ampoule/poche/présentation solution : aucun DM de reconstitution ajouté ; DM de perfusion calculés ailleurs. | Z50: =IF(A50="","",IF(ISNUMBER(SEARCH("Reconstitution",X50)),1,0)) -> 0 | AA50: =IF(Z50>0,"SERINGUE_PP_24ML","") | AB50: =IF(Z50>0,Z50*VLOOKUP(AA50,FACTEURS_ITEMS!$A$3:$J$30,4,FALSE()),0) -> 0 | AC50: =IF(A50="","",IF(ISNUMBER(SEARCH("Reconstitution",X50)),1,0)) -> 0 | AD50: =IF(AC50>0,"AIGUILLE_RECONSTITUTION","") | AE50: =IF(AC50>0,AC50*VLOOKUP(AD50,FACTEURS_ITEMS!$A$3:$J$30,4,FALSE()),0) -> 0 | AF50: =IF(A50="","",AB50+AE50) -> 0 | AG50: =IF(A50="","",S50+AF50) -> 0.112699 | AH50: =IF(A50="","",IF(AF50>0,"ACV médicament incluant PA + conditionnement + DM de reconstitution. Ne comprend pas poche/solvant/tubulure/administration.","ACV médicament sans DM de reconstitution ajouté.")) -> ACV médicament sans DM de reconstitution ajouté.
A51: Ciprofloxacine | B51: Poche prêt-à-l’emploi 400 mg | C51: poche PEA | D51: Ciprofloxacine | E51: 400 | J51: =IFERROR(SUM(E51,G51,I51)/1000,"") -> 0.4 | K51: =$E$4 -> 100 | L51: =IF(J51="","",J51/1000*K51*(1+$E$5/100)) -> 0.042 | M51: =IF(J51="","",J51/1000*$E$6) -> 3.8e-05 | N51: =IF(C51="ampoule verre",$E$12,IF(C51="poche PEA",$E$13,$E$11)) -> 20 | O51: =IF(C51="ampoule verre",$E$8,IF(C51="poche PEA",$E$9,$E$7)) -> 4.2 | P51: =N51/1000*O51*(1+$E$5/100) -> 0.0882 | Q51: =$E$14 -> 3 | R51: =Q51/1000*$E$10 -> 0.00348 | S51: =IF(J51="","",SUM(L51:M51,P51,R51)) -> 0.133718 | T51: =IF(OR(J51="",K51=$E$4),"Élevé - FE PA générique",IF(W51<>"","À vérifier","Moyen")) -> Élevé - FE PA générique | U51: Micrel/Breaking Stab | V51: EcovaMED v0.7 + hypothèses internes explicites | W51: Présentation prêt-à-l’emploi : le conditionnement primaire réel doit être remplacé par le poids fournisseur si disponible. | X51: =IF(A51="","",IF(OR(ISNUMBER(SEARCH("poche",C51)),ISNUMBER(SEARCH("ampoule",C51)),ISNUMBER(SEARCH("plastique",C51))),"Prêt à être dilué / administré (hypothèse)","Reconstitution nécessaire (hypothèse)")) -> Prêt à être dilué / administré (hypothèse) | Y51: =IF(A51="","",IF(ISNUMBER(SEARCH("Reconstitution",X51)),"Flacon/poudre : ajout par défaut 1 seringue + 1 aiguille ; à revalider selon présentation exacte.","Ampoule/poche/présentation solution : aucun DM de reconstitution ajouté ; DM de perfusion calculés ailleurs.")) -> Ampoule/poche/présentation solution : aucun DM de reconstitution ajouté ; DM de perfusion calculés ailleurs. | Z51: =IF(A51="","",IF(ISNUMBER(SEARCH("Reconstitution",X51)),1,0)) -> 0 | AA51: =IF(Z51>0,"SERINGUE_PP_24ML","") | AB51: =IF(Z51>0,Z51*VLOOKUP(AA51,FACTEURS_ITEMS!$A$3:$J$30,4,FALSE()),0) -> 0 | AC51: =IF(A51="","",IF(ISNUMBER(SEARCH("Reconstitution",X51)),1,0)) -> 0 | AD51: =IF(AC51>0,"AIGUILLE_RECONSTITUTION","") | AE51: =IF(AC51>0,AC51*VLOOKUP(AD51,FACTEURS_ITEMS!$A$3:$J$30,4,FALSE()),0) -> 0 | AF51: =IF(A51="","",AB51+AE51) -> 0 | AG51: =IF(A51="","",S51+AF51) -> 0.133718 | AH51: =IF(A51="","",IF(AF51>0,"ACV médicament incluant PA + conditionnement + DM de reconstitution. Ne comprend pas poche/solvant/tubulure/administration.","ACV médicament sans DM de reconstitution ajouté.")) -> ACV médicament sans DM de reconstitution ajouté.
A52: Clindamycine | B52: Ampoule 600 mg | C52: ampoule verre | D52: Clindamycine | E52: 600 | J52: =IFERROR(SUM(E52,G52,I52)/1000,"") -> 0.6 | K52: =$E$4 -> 100 | L52: =IF(J52="","",J52/1000*K52*(1+$E$5/100)) -> 0.063 | M52: =IF(J52="","",J52/1000*$E$6) -> 5.7e-05 | N52: =IF(C52="ampoule verre",$E$12,IF(C52="poche PEA",$E$13,$E$11)) -> 5 | O52: =IF(C52="ampoule verre",$E$8,IF(C52="poche PEA",$E$9,$E$7)) -> 5 | P52: =N52/1000*O52*(1+$E$5/100) -> 0.02625 | Q52: =$E$14 -> 3 | R52: =Q52/1000*$E$10 -> 0.00348 | S52: =IF(J52="","",SUM(L52:M52,P52,R52)) -> 0.092787 | T52: =IF(OR(J52="",K52=$E$4),"Élevé - FE PA générique",IF(W52<>"","À vérifier","Moyen")) -> Élevé - FE PA générique | U52: Breaking Stab | V52: EcovaMED v0.7 + hypothèses internes explicites | X52: =IF(A52="","",IF(OR(ISNUMBER(SEARCH("poche",C52)),ISNUMBER(SEARCH("ampoule",C52)),ISNUMBER(SEARCH("plastique",C52))),"Prêt à être dilué / administré (hypothèse)","Reconstitution nécessaire (hypothèse)")) -> Prêt à être dilué / administré (hypothèse) | Y52: =IF(A52="","",IF(ISNUMBER(SEARCH("Reconstitution",X52)),"Flacon/poudre : ajout par défaut 1 seringue + 1 aiguille ; à revalider selon présentation exacte.","Ampoule/poche/présentation solution : aucun DM de reconstitution ajouté ; DM de perfusion calculés ailleurs.")) -> Ampoule/poche/présentation solution : aucun DM de reconstitution ajouté ; DM de perfusion calculés ailleurs. | Z52: =IF(A52="","",IF(ISNUMBER(SEARCH("Reconstitution",X52)),1,0)) -> 0 | AA52: =IF(Z52>0,"SERINGUE_PP_24ML","") | AB52: =IF(Z52>0,Z52*VLOOKUP(AA52,FACTEURS_ITEMS!$A$3:$J$30,4,FALSE()),0) -> 0 | AC52: =IF(A52="","",IF(ISNUMBER(SEARCH("Reconstitution",X52)),1,0)) -> 0 | AD52: =IF(AC52>0,"AIGUILLE_RECONSTITUTION","") | AE52: =IF(AC52>0,AC52*VLOOKUP(AD52,FACTEURS_ITEMS!$A$3:$J$30,4,FALSE()),0) -> 0 | AF52: =IF(A52="","",AB52+AE52) -> 0 | AG52: =IF(A52="","",S52+AF52) -> 0.092787 | AH52: =IF(A52="","",IF(AF52>0,"ACV médicament incluant PA + conditionnement + DM de reconstitution. Ne comprend pas poche/solvant/tubulure/administration.","ACV médicament sans DM de reconstitution ajouté.")) -> ACV médicament sans DM de reconstitution ajouté.
A53: Clindamycine | B53: Ampoule 900 mg | C53: ampoule verre | D53: Clindamycine | E53: 900 | J53: =IFERROR(SUM(E53,G53,I53)/1000,"") -> 0.9 | K53: =$E$4 -> 100 | L53: =IF(J53="","",J53/1000*K53*(1+$E$5/100)) -> 0.0945 | M53: =IF(J53="","",J53/1000*$E$6) -> 8.55e-05 | N53: =IF(C53="ampoule verre",$E$12,IF(C53="poche PEA",$E$13,$E$11)) -> 5 | O53: =IF(C53="ampoule verre",$E$8,IF(C53="poche PEA",$E$9,$E$7)) -> 5 | P53: =N53/1000*O53*(1+$E$5/100) -> 0.02625 | Q53: =$E$14 -> 3 | R53: =Q53/1000*$E$10 -> 0.00348 | S53: =IF(J53="","",SUM(L53:M53,P53,R53)) -> 0.1243155 | T53: =IF(OR(J53="",K53=$E$4),"Élevé - FE PA générique",IF(W53<>"","À vérifier","Moyen")) -> Élevé - FE PA générique | U53: Breaking Stab | V53: EcovaMED v0.7 + hypothèses internes explicites | X53: =IF(A53="","",IF(OR(ISNUMBER(SEARCH("poche",C53)),ISNUMBER(SEARCH("ampoule",C53)),ISNUMBER(SEARCH("plastique",C53))),"Prêt à être dilué / administré (hypothèse)","Reconstitution nécessaire (hypothèse)")) -> Prêt à être dilué / administré (hypothèse) | Y53: =IF(A53="","",IF(ISNUMBER(SEARCH("Reconstitution",X53)),"Flacon/poudre : ajout par défaut 1 seringue + 1 aiguille ; à revalider selon présentation exacte.","Ampoule/poche/présentation solution : aucun DM de reconstitution ajouté ; DM de perfusion calculés ailleurs.")) -> Ampoule/poche/présentation solution : aucun DM de reconstitution ajouté ; DM de perfusion calculés ailleurs. | Z53: =IF(A53="","",IF(ISNUMBER(SEARCH("Reconstitution",X53)),1,0)) -> 0 | AA53: =IF(Z53>0,"SERINGUE_PP_24ML","") | AB53: =IF(Z53>0,Z53*VLOOKUP(AA53,FACTEURS_ITEMS!$A$3:$J$30,4,FALSE()),0) -> 0 | AC53: =IF(A53="","",IF(ISNUMBER(SEARCH("Reconstitution",X53)),1,0)) -> 0 | AD53: =IF(AC53>0,"AIGUILLE_RECONSTITUTION","") | AE53: =IF(AC53>0,AC53*VLOOKUP(AD53,FACTEURS_ITEMS!$A$3:$J$30,4,FALSE()),0) -> 0 | AF53: =IF(A53="","",AB53+AE53) -> 0 | AG53: =IF(A53="","",S53+AF53) -> 0.1243155 | AH53: =IF(A53="","",IF(AF53>0,"ACV médicament incluant PA + conditionnement + DM de reconstitution. Ne comprend pas poche/solvant/tubulure/administration.","ACV médicament sans DM de reconstitution ajouté.")) -> ACV médicament sans DM de reconstitution ajouté.
A54: Colistine | B54: Flacon 1 MUI ≈ 80 mg CMS | C54: flacon verre | D54: Colistiméthate sodique | E54: 80 | J54: =IFERROR(SUM(E54,G54,I54)/1000,"") -> 0.08 | K54: =$E$4 -> 100 | L54: =IF(J54="","",J54/1000*K54*(1+$E$5/100)) -> 0.0084 | M54: =IF(J54="","",J54/1000*$E$6) -> 7.6e-06 | N54: =IF(C54="ampoule verre",$E$12,IF(C54="poche PEA",$E$13,$E$11)) -> 10 | O54: =IF(C54="ampoule verre",$E$8,IF(C54="poche PEA",$E$9,$E$7)) -> 7.1 | P54: =N54/1000*O54*(1+$E$5/100) -> 0.07455 | Q54: =$E$14 -> 3 | R54: =Q54/1000*$E$10 -> 0.00348 | S54: =IF(J54="","",SUM(L54:M54,P54,R54)) -> 0.0864376 | T54: =IF(OR(J54="",K54=$E$4),"Élevé - FE PA générique",IF(W54<>"","À vérifier","Moyen")) -> Élevé - FE PA générique | U54: Breaking Stab ; conversion MUI approximative | V54: EcovaMED v0.7 + hypothèses internes explicites | W54: Conversion MUI→mg utilisée pour ordre de grandeur ; à confirmer avec la présentation locale. | X54: =IF(A54="","",IF(OR(ISNUMBER(SEARCH("poche",C54)),ISNUMBER(SEARCH("ampoule",C54)),ISNUMBER(SEARCH("plastique",C54))),"Prêt à être dilué / administré (hypothèse)","Reconstitution nécessaire (hypothèse)")) -> Reconstitution nécessaire (hypothèse) | Y54: =IF(A54="","",IF(ISNUMBER(SEARCH("Reconstitution",X54)),"Flacon/poudre : ajout par défaut 1 seringue + 1 aiguille ; à revalider selon présentation exacte.","Ampoule/poche/présentation solution : aucun DM de reconstitution ajouté ; DM de perfusion calculés ailleurs.")) -> Flacon/poudre : ajout par défaut 1 seringue + 1 aiguille ; à revalider selon présentation exacte. | Z54: =IF(A54="","",IF(ISNUMBER(SEARCH("Reconstitution",X54)),1,0)) -> 1 | AA54: =IF(Z54>0,"SERINGUE_PP_24ML","") -> SERINGUE_PP_24ML | AB54: =IF(Z54>0,Z54*VLOOKUP(AA54,FACTEURS_ITEMS!$A$3:$J$30,4,FALSE()),0) -> 0.069 | AC54: =IF(A54="","",IF(ISNUMBER(SEARCH("Reconstitution",X54)),1,0)) -> 1 | AD54: =IF(AC54>0,"AIGUILLE_RECONSTITUTION","") -> AIGUILLE_RECONSTITUTION | AE54: =IF(AC54>0,AC54*VLOOKUP(AD54,FACTEURS_ITEMS!$A$3:$J$30,4,FALSE()),0) -> 0.01 | AF54: =IF(A54="","",AB54+AE54) -> 0.079 | AG54: =IF(A54="","",S54+AF54) -> 0.1654376 | AH54: =IF(A54="","",IF(AF54>0,"ACV médicament incluant PA + conditionnement + DM de reconstitution. Ne comprend pas poche/solvant/tubulure/administration.","ACV médicament sans DM de reconstitution ajouté.")) -> ACV médicament incluant PA + conditionnement + DM de reconstitution. Ne comprend pas poche/solvant/tubulure/administration.
A55: Colistine | B55: Flacon 2 MUI ≈ 160 mg CMS | C55: flacon verre | D55: Colistiméthate sodique | E55: 160 | J55: =IFERROR(SUM(E55,G55,I55)/1000,"") -> 0.16 | K55: =$E$4 -> 100 | L55: =IF(J55="","",J55/1000*K55*(1+$E$5/100)) -> 0.0168 | M55: =IF(J55="","",J55/1000*$E$6) -> 1.52e-05 | N55: =IF(C55="ampoule verre",$E$12,IF(C55="poche PEA",$E$13,$E$11)) -> 10 | O55: =IF(C55="ampoule verre",$E$8,IF(C55="poche PEA",$E$9,$E$7)) -> 7.1 | P55: =N55/1000*O55*(1+$E$5/100) -> 0.07455 | Q55: =$E$14 -> 3 | R55: =Q55/1000*$E$10 -> 0.00348 | S55: =IF(J55="","",SUM(L55:M55,P55,R55)) -> 0.0948452 | T55: =IF(OR(J55="",K55=$E$4),"Élevé - FE PA générique",IF(W55<>"","À vérifier","Moyen")) -> Élevé - FE PA générique | U55: Breaking Stab ; conversion MUI approximative | V55: EcovaMED v0.7 + hypothèses internes explicites | W55: Conversion MUI→mg utilisée pour ordre de grandeur ; à confirmer avec la présentation locale. | X55: =IF(A55="","",IF(OR(ISNUMBER(SEARCH("poche",C55)),ISNUMBER(SEARCH("ampoule",C55)),ISNUMBER(SEARCH("plastique",C55))),"Prêt à être dilué / administré (hypothèse)","Reconstitution nécessaire (hypothèse)")) -> Reconstitution nécessaire (hypothèse) | Y55: =IF(A55="","",IF(ISNUMBER(SEARCH("Reconstitution",X55)),"Flacon/poudre : ajout par défaut 1 seringue + 1 aiguille ; à revalider selon présentation exacte.","Ampoule/poche/présentation solution : aucun DM de reconstitution ajouté ; DM de perfusion calculés ailleurs.")) -> Flacon/poudre : ajout par défaut 1 seringue + 1 aiguille ; à revalider selon présentation exacte. | Z55: =IF(A55="","",IF(ISNUMBER(SEARCH("Reconstitution",X55)),1,0)) -> 1 | AA55: =IF(Z55>0,"SERINGUE_PP_24ML","") -> SERINGUE_PP_24ML | AB55: =IF(Z55>0,Z55*VLOOKUP(AA55,FACTEURS_ITEMS!$A$3:$J$30,4,FALSE()),0) -> 0.069 | AC55: =IF(A55="","",IF(ISNUMBER(SEARCH("Reconstitution",X55)),1,0)) -> 1 | AD55: =IF(AC55>0,"AIGUILLE_RECONSTITUTION","") -> AIGUILLE_RECONSTITUTION | AE55: =IF(AC55>0,AC55*VLOOKUP(AD55,FACTEURS_ITEMS!$A$3:$J$30,4,FALSE()),0) -> 0.01 | AF55: =IF(A55="","",AB55+AE55) -> 0.079 | AG55: =IF(A55="","",S55+AF55) -> 0.1738452 | AH55: =IF(A55="","",IF(AF55>0,"ACV médicament incluant PA + conditionnement + DM de reconstitution. Ne comprend pas poche/solvant/tubulure/administration.","ACV médicament sans DM de reconstitution ajouté.")) -> ACV médicament incluant PA + conditionnement + DM de reconstitution. Ne comprend pas poche/solvant/tubulure/administration.
A56: Colistine | B56: Flacon 4,5 MUI ≈ 360 mg CMS | C56: flacon verre | D56: Colistiméthate sodique | E56: 360 | J56: =IFERROR(SUM(E56,G56,I56)/1000,"") -> 0.36 | K56: =$E$4 -> 100 | L56: =IF(J56="","",J56/1000*K56*(1+$E$5/100)) -> 0.0378 | M56: =IF(J56="","",J56/1000*$E$6) -> 3.42e-05 | N56: =IF(C56="ampoule verre",$E$12,IF(C56="poche PEA",$E$13,$E$11)) -> 10 | O56: =IF(C56="ampoule verre",$E$8,IF(C56="poche PEA",$E$9,$E$7)) -> 7.1 | P56: =N56/1000*O56*(1+$E$5/100) -> 0.07455 | Q56: =$E$14 -> 3 | R56: =Q56/1000*$E$10 -> 0.00348 | S56: =IF(J56="","",SUM(L56:M56,P56,R56)) -> 0.1158642 | T56: =IF(OR(J56="",K56=$E$4),"Élevé - FE PA générique",IF(W56<>"","À vérifier","Moyen")) -> Élevé - FE PA générique | U56: Breaking Stab ; conversion MUI approximative | V56: EcovaMED v0.7 + hypothèses internes explicites | W56: Conversion MUI→mg utilisée pour ordre de grandeur ; à confirmer avec la présentation locale. | X56: =IF(A56="","",IF(OR(ISNUMBER(SEARCH("poche",C56)),ISNUMBER(SEARCH("ampoule",C56)),ISNUMBER(SEARCH("plastique",C56))),"Prêt à être dilué / administré (hypothèse)","Reconstitution nécessaire (hypothèse)")) -> Reconstitution nécessaire (hypothèse) | Y56: =IF(A56="","",IF(ISNUMBER(SEARCH("Reconstitution",X56)),"Flacon/poudre : ajout par défaut 1 seringue + 1 aiguille ; à revalider selon présentation exacte.","Ampoule/poche/présentation solution : aucun DM de reconstitution ajouté ; DM de perfusion calculés ailleurs.")) -> Flacon/poudre : ajout par défaut 1 seringue + 1 aiguille ; à revalider selon présentation exacte. | Z56: =IF(A56="","",IF(ISNUMBER(SEARCH("Reconstitution",X56)),1,0)) -> 1 | AA56: =IF(Z56>0,"SERINGUE_PP_24ML","") -> SERINGUE_PP_24ML | AB56: =IF(Z56>0,Z56*VLOOKUP(AA56,FACTEURS_ITEMS!$A$3:$J$30,4,FALSE()),0) -> 0.069 | AC56: =IF(A56="","",IF(ISNUMBER(SEARCH("Reconstitution",X56)),1,0)) -> 1 | AD56: =IF(AC56>0,"AIGUILLE_RECONSTITUTION","") -> AIGUILLE_RECONSTITUTION | AE56: =IF(AC56>0,AC56*VLOOKUP(AD56,FACTEURS_ITEMS!$A$3:$J$30,4,FALSE()),0) -> 0.01 | AF56: =IF(A56="","",AB56+AE56) -> 0.079 | AG56: =IF(A56="","",S56+AF56) -> 0.1948642 | AH56: =IF(A56="","",IF(AF56>0,"ACV médicament incluant PA + conditionnement + DM de reconstitution. Ne comprend pas poche/solvant/tubulure/administration.","ACV médicament sans DM de reconstitution ajouté.")) -> ACV médicament incluant PA + conditionnement + DM de reconstitution. Ne comprend pas poche/solvant/tubulure/administration.
A57: Cotrimoxazole IV / Bactrim® | B57: Ampoule 400/80 mg | C57: ampoule verre | D57: Sulfaméthoxazole | E57: 400 | F57: Triméthoprime | G57: 80 | J57: =IFERROR(SUM(E57,G57,I57)/1000,"") -> 0.48 | K57: =$E$4 -> 100 | L57: =IF(J57="","",J57/1000*K57*(1+$E$5/100)) -> 0.0504 | M57: =IF(J57="","",J57/1000*$E$6) -> 4.56e-05 | N57: =IF(C57="ampoule verre",$E$12,IF(C57="poche PEA",$E$13,$E$11)) -> 5 | O57: =IF(C57="ampoule verre",$E$8,IF(C57="poche PEA",$E$9,$E$7)) -> 5 | P57: =N57/1000*O57*(1+$E$5/100) -> 0.02625 | Q57: =$E$14 -> 3 | R57: =Q57/1000*$E$10 -> 0.00348 | S57: =IF(J57="","",SUM(L57:M57,P57,R57)) -> 0.0801756 | T57: =IF(OR(J57="",K57=$E$4),"Élevé - FE PA générique",IF(W57<>"","À vérifier","Moyen")) -> Élevé - FE PA générique | U57: Breaking Stab | V57: EcovaMED v0.7 + hypothèses internes explicites | X57: =IF(A57="","",IF(OR(ISNUMBER(SEARCH("poche",C57)),ISNUMBER(SEARCH("ampoule",C57)),ISNUMBER(SEARCH("plastique",C57))),"Prêt à être dilué / administré (hypothèse)","Reconstitution nécessaire (hypothèse)")) -> Prêt à être dilué / administré (hypothèse) | Y57: =IF(A57="","",IF(ISNUMBER(SEARCH("Reconstitution",X57)),"Flacon/poudre : ajout par défaut 1 seringue + 1 aiguille ; à revalider selon présentation exacte.","Ampoule/poche/présentation solution : aucun DM de reconstitution ajouté ; DM de perfusion calculés ailleurs.")) -> Ampoule/poche/présentation solution : aucun DM de reconstitution ajouté ; DM de perfusion calculés ailleurs. | Z57: =IF(A57="","",IF(ISNUMBER(SEARCH("Reconstitution",X57)),1,0)) -> 0 | AA57: =IF(Z57>0,"SERINGUE_PP_24ML","") | AB57: =IF(Z57>0,Z57*VLOOKUP(AA57,FACTEURS_ITEMS!$A$3:$J$30,4,FALSE()),0) -> 0 | AC57: =IF(A57="","",IF(ISNUMBER(SEARCH("Reconstitution",X57)),1,0)) -> 0 | AD57: =IF(AC57>0,"AIGUILLE_RECONSTITUTION","") | AE57: =IF(AC57>0,AC57*VLOOKUP(AD57,FACTEURS_ITEMS!$A$3:$J$30,4,FALSE()),0) -> 0 | AF57: =IF(A57="","",AB57+AE57) -> 0 | AG57: =IF(A57="","",S57+AF57) -> 0.0801756 | AH57: =IF(A57="","",IF(AF57>0,"ACV médicament incluant PA + conditionnement + DM de reconstitution. Ne comprend pas poche/solvant/tubulure/administration.","ACV médicament sans DM de reconstitution ajouté.")) -> ACV médicament sans DM de reconstitution ajouté.
A58: Dalbavancine | B58: Flacon 500 mg | C58: flacon verre | D58: Dalbavancine | E58: 500 | J58: =IFERROR(SUM(E58,G58,I58)/1000,"") -> 0.5 | K58: =$E$4 -> 100 | L58: =IF(J58="","",J58/1000*K58*(1+$E$5/100)) -> 0.0525 | M58: =IF(J58="","",J58/1000*$E$6) -> 4.75e-05 | N58: =IF(C58="ampoule verre",$E$12,IF(C58="poche PEA",$E$13,$E$11)) -> 10 | O58: =IF(C58="ampoule verre",$E$8,IF(C58="poche PEA",$E$9,$E$7)) -> 7.1 | P58: =N58/1000*O58*(1+$E$5/100) -> 0.07455 | Q58: =$E$14 -> 3 | R58: =Q58/1000*$E$10 -> 0.00348 | S58: =IF(J58="","",SUM(L58:M58,P58,R58)) -> 0.1305775 | T58: =IF(OR(J58="",K58=$E$4),"Élevé - FE PA générique",IF(W58<>"","À vérifier","Moyen")) -> Élevé - FE PA générique | U58: Breaking Stab | V58: EcovaMED v0.7 + hypothèses internes explicites | X58: =IF(A58="","",IF(OR(ISNUMBER(SEARCH("poche",C58)),ISNUMBER(SEARCH("ampoule",C58)),ISNUMBER(SEARCH("plastique",C58))),"Prêt à être dilué / administré (hypothèse)","Reconstitution nécessaire (hypothèse)")) -> Reconstitution nécessaire (hypothèse) | Y58: =IF(A58="","",IF(ISNUMBER(SEARCH("Reconstitution",X58)),"Flacon/poudre : ajout par défaut 1 seringue + 1 aiguille ; à revalider selon présentation exacte.","Ampoule/poche/présentation solution : aucun DM de reconstitution ajouté ; DM de perfusion calculés ailleurs.")) -> Flacon/poudre : ajout par défaut 1 seringue + 1 aiguille ; à revalider selon présentation exacte. | Z58: =IF(A58="","",IF(ISNUMBER(SEARCH("Reconstitution",X58)),1,0)) -> 1 | AA58: =IF(Z58>0,"SERINGUE_PP_24ML","") -> SERINGUE_PP_24ML | AB58: =IF(Z58>0,Z58*VLOOKUP(AA58,FACTEURS_ITEMS!$A$3:$J$30,4,FALSE()),0) -> 0.069 | AC58: =IF(A58="","",IF(ISNUMBER(SEARCH("Reconstitution",X58)),1,0)) -> 1 | AD58: =IF(AC58>0,"AIGUILLE_RECONSTITUTION","") -> AIGUILLE_RECONSTITUTION | AE58: =IF(AC58>0,AC58*VLOOKUP(AD58,FACTEURS_ITEMS!$A$3:$J$30,4,FALSE()),0) -> 0.01 | AF58: =IF(A58="","",AB58+AE58) -> 0.079 | AG58: =IF(A58="","",S58+AF58) -> 0.2095775 | AH58: =IF(A58="","",IF(AF58>0,"ACV médicament incluant PA + conditionnement + DM de reconstitution. Ne comprend pas poche/solvant/tubulure/administration.","ACV médicament sans DM de reconstitution ajouté.")) -> ACV médicament incluant PA + conditionnement + DM de reconstitution. Ne comprend pas poche/solvant/tubulure/administration.
A59: Daptomycine | B59: Flacon 350 mg | C59: flacon verre | D59: Daptomycine | E59: 350 | J59: =IFERROR(SUM(E59,G59,I59)/1000,"") -> 0.35 | K59: =$E$4 -> 100 | L59: =IF(J59="","",J59/1000*K59*(1+$E$5/100)) -> 0.03675 | M59: =IF(J59="","",J59/1000*$E$6) -> 3.325e-05 | N59: =IF(C59="ampoule verre",$E$12,IF(C59="poche PEA",$E$13,$E$11)) -> 10 | O59: =IF(C59="ampoule verre",$E$8,IF(C59="poche PEA",$E$9,$E$7)) -> 7.1 | P59: =N59/1000*O59*(1+$E$5/100) -> 0.07455 | Q59: =$E$14 -> 3 | R59: =Q59/1000*$E$10 -> 0.00348 | S59: =IF(J59="","",SUM(L59:M59,P59,R59)) -> 0.11481325 | T59: =IF(OR(J59="",K59=$E$4),"Élevé - FE PA générique",IF(W59<>"","À vérifier","Moyen")) -> Élevé - FE PA générique | U59: Breaking Stab | V59: EcovaMED v0.7 + hypothèses internes explicites | X59: =IF(A59="","",IF(OR(ISNUMBER(SEARCH("poche",C59)),ISNUMBER(SEARCH("ampoule",C59)),ISNUMBER(SEARCH("plastique",C59))),"Prêt à être dilué / administré (hypothèse)","Reconstitution nécessaire (hypothèse)")) -> Reconstitution nécessaire (hypothèse) | Y59: =IF(A59="","",IF(ISNUMBER(SEARCH("Reconstitution",X59)),"Flacon/poudre : ajout par défaut 1 seringue + 1 aiguille ; à revalider selon présentation exacte.","Ampoule/poche/présentation solution : aucun DM de reconstitution ajouté ; DM de perfusion calculés ailleurs.")) -> Flacon/poudre : ajout par défaut 1 seringue + 1 aiguille ; à revalider selon présentation exacte. | Z59: =IF(A59="","",IF(ISNUMBER(SEARCH("Reconstitution",X59)),1,0)) -> 1 | AA59: =IF(Z59>0,"SERINGUE_PP_24ML","") -> SERINGUE_PP_24ML | AB59: =IF(Z59>0,Z59*VLOOKUP(AA59,FACTEURS_ITEMS!$A$3:$J$30,4,FALSE()),0) -> 0.069 | AC59: =IF(A59="","",IF(ISNUMBER(SEARCH("Reconstitution",X59)),1,0)) -> 1 | AD59: =IF(AC59>0,"AIGUILLE_RECONSTITUTION","") -> AIGUILLE_RECONSTITUTION | AE59: =IF(AC59>0,AC59*VLOOKUP(AD59,FACTEURS_ITEMS!$A$3:$J$30,4,FALSE()),0) -> 0.01 | AF59: =IF(A59="","",AB59+AE59) -> 0.079 | AG59: =IF(A59="","",S59+AF59) -> 0.19381325 | AH59: =IF(A59="","",IF(AF59>0,"ACV médicament incluant PA + conditionnement + DM de reconstitution. Ne comprend pas poche/solvant/tubulure/administration.","ACV médicament sans DM de reconstitution ajouté.")) -> ACV médicament incluant PA + conditionnement + DM de reconstitution. Ne comprend pas poche/solvant/tubulure/administration.
A60: Daptomycine | B60: Flacon 500 mg | C60: flacon verre | D60: Daptomycine | E60: 500 | J60: =IFERROR(SUM(E60,G60,I60)/1000,"") -> 0.5 | K60: =$E$4 -> 100 | L60: =IF(J60="","",J60/1000*K60*(1+$E$5/100)) -> 0.0525 | M60: =IF(J60="","",J60/1000*$E$6) -> 4.75e-05 | N60: =IF(C60="ampoule verre",$E$12,IF(C60="poche PEA",$E$13,$E$11)) -> 10 | O60: =IF(C60="ampoule verre",$E$8,IF(C60="poche PEA",$E$9,$E$7)) -> 7.1 | P60: =N60/1000*O60*(1+$E$5/100) -> 0.07455 | Q60: =$E$14 -> 3 | R60: =Q60/1000*$E$10 -> 0.00348 | S60: =IF(J60="","",SUM(L60:M60,P60,R60)) -> 0.1305775 | T60: =IF(OR(J60="",K60=$E$4),"Élevé - FE PA générique",IF(W60<>"","À vérifier","Moyen")) -> Élevé - FE PA générique | U60: Breaking Stab | V60: EcovaMED v0.7 + hypothèses internes explicites | X60: =IF(A60="","",IF(OR(ISNUMBER(SEARCH("poche",C60)),ISNUMBER(SEARCH("ampoule",C60)),ISNUMBER(SEARCH("plastique",C60))),"Prêt à être dilué / administré (hypothèse)","Reconstitution nécessaire (hypothèse)")) -> Reconstitution nécessaire (hypothèse) | Y60: =IF(A60="","",IF(ISNUMBER(SEARCH("Reconstitution",X60)),"Flacon/poudre : ajout par défaut 1 seringue + 1 aiguille ; à revalider selon présentation exacte.","Ampoule/poche/présentation solution : aucun DM de reconstitution ajouté ; DM de perfusion calculés ailleurs.")) -> Flacon/poudre : ajout par défaut 1 seringue + 1 aiguille ; à revalider selon présentation exacte. | Z60: =IF(A60="","",IF(ISNUMBER(SEARCH("Reconstitution",X60)),1,0)) -> 1 | AA60: =IF(Z60>0,"SERINGUE_PP_24ML","") -> SERINGUE_PP_24ML | AB60: =IF(Z60>0,Z60*VLOOKUP(AA60,FACTEURS_ITEMS!$A$3:$J$30,4,FALSE()),0) -> 0.069 | AC60: =IF(A60="","",IF(ISNUMBER(SEARCH("Reconstitution",X60)),1,0)) -> 1 | AD60: =IF(AC60>0,"AIGUILLE_RECONSTITUTION","") -> AIGUILLE_RECONSTITUTION | AE60: =IF(AC60>0,AC60*VLOOKUP(AD60,FACTEURS_ITEMS!$A$3:$J$30,4,FALSE()),0) -> 0.01 | AF60: =IF(A60="","",AB60+AE60) -> 0.079 | AG60: =IF(A60="","",S60+AF60) -> 0.2095775 | AH60: =IF(A60="","",IF(AF60>0,"ACV médicament incluant PA + conditionnement + DM de reconstitution. Ne comprend pas poche/solvant/tubulure/administration.","ACV médicament sans DM de reconstitution ajouté.")) -> ACV médicament incluant PA + conditionnement + DM de reconstitution. Ne comprend pas poche/solvant/tubulure/administration.
A61: Ertapénem | B61: Flacon 1 g | C61: flacon verre | D61: Ertapénem | E61: 1000 | J61: =IFERROR(SUM(E61,G61,I61)/1000,"") -> 1 | K61: =$E$4 -> 100 | L61: =IF(J61="","",J61/1000*K61*(1+$E$5/100)) -> 0.105 | M61: =IF(J61="","",J61/1000*$E$6) -> 9.5e-05 | N61: =IF(C61="ampoule verre",$E$12,IF(C61="poche PEA",$E$13,$E$11)) -> 10 | O61: =IF(C61="ampoule verre",$E$8,IF(C61="poche PEA",$E$9,$E$7)) -> 7.1 | P61: =N61/1000*O61*(1+$E$5/100) -> 0.07455 | Q61: =$E$14 -> 3 | R61: =Q61/1000*$E$10 -> 0.00348 | S61: =IF(J61="","",SUM(L61:M61,P61,R61)) -> 0.183125 | T61: =IF(OR(J61="",K61=$E$4),"Élevé - FE PA générique",IF(W61<>"","À vérifier","Moyen")) -> Élevé - FE PA générique | U61: Breaking Stab | V61: EcovaMED v0.7 + hypothèses internes explicites | X61: =IF(A61="","",IF(OR(ISNUMBER(SEARCH("poche",C61)),ISNUMBER(SEARCH("ampoule",C61)),ISNUMBER(SEARCH("plastique",C61))),"Prêt à être dilué / administré (hypothèse)","Reconstitution nécessaire (hypothèse)")) -> Reconstitution nécessaire (hypothèse) | Y61: =IF(A61="","",IF(ISNUMBER(SEARCH("Reconstitution",X61)),"Flacon/poudre : ajout par défaut 1 seringue + 1 aiguille ; à revalider selon présentation exacte.","Ampoule/poche/présentation solution : aucun DM de reconstitution ajouté ; DM de perfusion calculés ailleurs.")) -> Flacon/poudre : ajout par défaut 1 seringue + 1 aiguille ; à revalider selon présentation exacte. | Z61: =IF(A61="","",IF(ISNUMBER(SEARCH("Reconstitution",X61)),1,0)) -> 1 | AA61: =IF(Z61>0,"SERINGUE_PP_24ML","") -> SERINGUE_PP_24ML | AB61: =IF(Z61>0,Z61*VLOOKUP(AA61,FACTEURS_ITEMS!$A$3:$J$30,4,FALSE()),0) -> 0.069 | AC61: =IF(A61="","",IF(ISNUMBER(SEARCH("Reconstitution",X61)),1,0)) -> 1 | AD61: =IF(AC61>0,"AIGUILLE_RECONSTITUTION","") -> AIGUILLE_RECONSTITUTION | AE61: =IF(AC61>0,AC61*VLOOKUP(AD61,FACTEURS_ITEMS!$A$3:$J$30,4,FALSE()),0) -> 0.01 | AF61: =IF(A61="","",AB61+AE61) -> 0.079 | AG61: =IF(A61="","",S61+AF61) -> 0.262125 | AH61: =IF(A61="","",IF(AF61>0,"ACV médicament incluant PA + conditionnement + DM de reconstitution. Ne comprend pas poche/solvant/tubulure/administration.","ACV médicament sans DM de reconstitution ajouté.")) -> ACV médicament incluant PA + conditionnement + DM de reconstitution. Ne comprend pas poche/solvant/tubulure/administration.
A62: Fluconazole | B62: Poche prêt-à-l’emploi 200 mg | C62: poche PEA | D62: Fluconazole | E62: 200 | J62: =IFERROR(SUM(E62,G62,I62)/1000,"") -> 0.2 | K62: =$E$4 -> 100 | L62: =IF(J62="","",J62/1000*K62*(1+$E$5/100)) -> 0.021 | M62: =IF(J62="","",J62/1000*$E$6) -> 1.9e-05 | N62: =IF(C62="ampoule verre",$E$12,IF(C62="poche PEA",$E$13,$E$11)) -> 20 | O62: =IF(C62="ampoule verre",$E$8,IF(C62="poche PEA",$E$9,$E$7)) -> 4.2 | P62: =N62/1000*O62*(1+$E$5/100) -> 0.0882 | Q62: =$E$14 -> 3 | R62: =Q62/1000*$E$10 -> 0.00348 | S62: =IF(J62="","",SUM(L62:M62,P62,R62)) -> 0.112699 | T62: =IF(OR(J62="",K62=$E$4),"Élevé - FE PA générique",IF(W62<>"","À vérifier","Moyen")) -> Élevé - FE PA générique | U62: Breaking Stab | V62: EcovaMED v0.7 + hypothèses internes explicites | W62: Présentation prêt-à-l’emploi : le conditionnement primaire réel doit être remplacé par le poids fournisseur si disponible. | X62: =IF(A62="","",IF(OR(ISNUMBER(SEARCH("poche",C62)),ISNUMBER(SEARCH("ampoule",C62)),ISNUMBER(SEARCH("plastique",C62))),"Prêt à être dilué / administré (hypothèse)","Reconstitution nécessaire (hypothèse)")) -> Prêt à être dilué / administré (hypothèse) | Y62: =IF(A62="","",IF(ISNUMBER(SEARCH("Reconstitution",X62)),"Flacon/poudre : ajout par défaut 1 seringue + 1 aiguille ; à revalider selon présentation exacte.","Ampoule/poche/présentation solution : aucun DM de reconstitution ajouté ; DM de perfusion calculés ailleurs.")) -> Ampoule/poche/présentation solution : aucun DM de reconstitution ajouté ; DM de perfusion calculés ailleurs. | Z62: =IF(A62="","",IF(ISNUMBER(SEARCH("Reconstitution",X62)),1,0)) -> 0 | AA62: =IF(Z62>0,"SERINGUE_PP_24ML","") | AB62: =IF(Z62>0,Z62*VLOOKUP(AA62,FACTEURS_ITEMS!$A$3:$J$30,4,FALSE()),0) -> 0 | AC62: =IF(A62="","",IF(ISNUMBER(SEARCH("Reconstitution",X62)),1,0)) -> 0 | AD62: =IF(AC62>0,"AIGUILLE_RECONSTITUTION","") | AE62: =IF(AC62>0,AC62*VLOOKUP(AD62,FACTEURS_ITEMS!$A$3:$J$30,4,FALSE()),0) -> 0 | AF62: =IF(A62="","",AB62+AE62) -> 0 | AG62: =IF(A62="","",S62+AF62) -> 0.112699 | AH62: =IF(A62="","",IF(AF62>0,"ACV médicament incluant PA + conditionnement + DM de reconstitution. Ne comprend pas poche/solvant/tubulure/administration.","ACV médicament sans DM de reconstitution ajouté.")) -> ACV médicament sans DM de reconstitution ajouté.
A63: Fluconazole | B63: Poche prêt-à-l’emploi 400 mg | C63: poche PEA | D63: Fluconazole | E63: 400 | J63: =IFERROR(SUM(E63,G63,I63)/1000,"") -> 0.4 | K63: =$E$4 -> 100 | L63: =IF(J63="","",J63/1000*K63*(1+$E$5/100)) -> 0.042 | M63: =IF(J63="","",J63/1000*$E$6) -> 3.8e-05 | N63: =IF(C63="ampoule verre",$E$12,IF(C63="poche PEA",$E$13,$E$11)) -> 20 | O63: =IF(C63="ampoule verre",$E$8,IF(C63="poche PEA",$E$9,$E$7)) -> 4.2 | P63: =N63/1000*O63*(1+$E$5/100) -> 0.0882 | Q63: =$E$14 -> 3 | R63: =Q63/1000*$E$10 -> 0.00348 | S63: =IF(J63="","",SUM(L63:M63,P63,R63)) -> 0.133718 | T63: =IF(OR(J63="",K63=$E$4),"Élevé - FE PA générique",IF(W63<>"","À vérifier","Moyen")) -> Élevé - FE PA générique | U63: Breaking Stab | V63: EcovaMED v0.7 + hypothèses internes explicites | W63: Présentation prêt-à-l’emploi : le conditionnement primaire réel doit être remplacé par le poids fournisseur si disponible. | X63: =IF(A63="","",IF(OR(ISNUMBER(SEARCH("poche",C63)),ISNUMBER(SEARCH("ampoule",C63)),ISNUMBER(SEARCH("plastique",C63))),"Prêt à être dilué / administré (hypothèse)","Reconstitution nécessaire (hypothèse)")) -> Prêt à être dilué / administré (hypothèse) | Y63: =IF(A63="","",IF(ISNUMBER(SEARCH("Reconstitution",X63)),"Flacon/poudre : ajout par défaut 1 seringue + 1 aiguille ; à revalider selon présentation exacte.","Ampoule/poche/présentation solution : aucun DM de reconstitution ajouté ; DM de perfusion calculés ailleurs.")) -> Ampoule/poche/présentation solution : aucun DM de reconstitution ajouté ; DM de perfusion calculés ailleurs. | Z63: =IF(A63="","",IF(ISNUMBER(SEARCH("Reconstitution",X63)),1,0)) -> 0 | AA63: =IF(Z63>0,"SERINGUE_PP_24ML","") | AB63: =IF(Z63>0,Z63*VLOOKUP(AA63,FACTEURS_ITEMS!$A$3:$J$30,4,FALSE()),0) -> 0 | AC63: =IF(A63="","",IF(ISNUMBER(SEARCH("Reconstitution",X63)),1,0)) -> 0 | AD63: =IF(AC63>0,"AIGUILLE_RECONSTITUTION","") | AE63: =IF(AC63>0,AC63*VLOOKUP(AD63,FACTEURS_ITEMS!$A$3:$J$30,4,FALSE()),0) -> 0 | AF63: =IF(A63="","",AB63+AE63) -> 0 | AG63: =IF(A63="","",S63+AF63) -> 0.133718 | AH63: =IF(A63="","",IF(AF63>0,"ACV médicament incluant PA + conditionnement + DM de reconstitution. Ne comprend pas poche/solvant/tubulure/administration.","ACV médicament sans DM de reconstitution ajouté.")) -> ACV médicament sans DM de reconstitution ajouté.
A64: Fosfomycine IV | B64: Flacon 4 g | C64: flacon verre | D64: Fosfomycine | E64: 4000 | J64: =IFERROR(SUM(E64,G64,I64)/1000,"") -> 4 | K64: =$E$4 -> 100 | L64: =IF(J64="","",J64/1000*K64*(1+$E$5/100)) -> 0.42 | M64: =IF(J64="","",J64/1000*$E$6) -> 0.00038 | N64: =IF(C64="ampoule verre",$E$12,IF(C64="poche PEA",$E$13,$E$11)) -> 10 | O64: =IF(C64="ampoule verre",$E$8,IF(C64="poche PEA",$E$9,$E$7)) -> 7.1 | P64: =N64/1000*O64*(1+$E$5/100) -> 0.07455 | Q64: =$E$14 -> 3 | R64: =Q64/1000*$E$10 -> 0.00348 | S64: =IF(J64="","",SUM(L64:M64,P64,R64)) -> 0.49841 | T64: =IF(OR(J64="",K64=$E$4),"Élevé - FE PA générique",IF(W64<>"","À vérifier","Moyen")) -> Élevé - FE PA générique | U64: Breaking Stab | V64: EcovaMED v0.7 + hypothèses internes explicites | X64: =IF(A64="","",IF(OR(ISNUMBER(SEARCH("poche",C64)),ISNUMBER(SEARCH("ampoule",C64)),ISNUMBER(SEARCH("plastique",C64))),"Prêt à être dilué / administré (hypothèse)","Reconstitution nécessaire (hypothèse)")) -> Reconstitution nécessaire (hypothèse) | Y64: =IF(A64="","",IF(ISNUMBER(SEARCH("Reconstitution",X64)),"Flacon/poudre : ajout par défaut 1 seringue + 1 aiguille ; à revalider selon présentation exacte.","Ampoule/poche/présentation solution : aucun DM de reconstitution ajouté ; DM de perfusion calculés ailleurs.")) -> Flacon/poudre : ajout par défaut 1 seringue + 1 aiguille ; à revalider selon présentation exacte. | Z64: =IF(A64="","",IF(ISNUMBER(SEARCH("Reconstitution",X64)),1,0)) -> 1 | AA64: =IF(Z64>0,"SERINGUE_PP_24ML","") -> SERINGUE_PP_24ML | AB64: =IF(Z64>0,Z64*VLOOKUP(AA64,FACTEURS_ITEMS!$A$3:$J$30,4,FALSE()),0) -> 0.069 | AC64: =IF(A64="","",IF(ISNUMBER(SEARCH("Reconstitution",X64)),1,0)) -> 1 | AD64: =IF(AC64>0,"AIGUILLE_RECONSTITUTION","") -> AIGUILLE_RECONSTITUTION | AE64: =IF(AC64>0,AC64*VLOOKUP(AD64,FACTEURS_ITEMS!$A$3:$J$30,4,FALSE()),0) -> 0.01 | AF64: =IF(A64="","",AB64+AE64) -> 0.079 | AG64: =IF(A64="","",S64+AF64) -> 0.57741 | AH64: =IF(A64="","",IF(AF64>0,"ACV médicament incluant PA + conditionnement + DM de reconstitution. Ne comprend pas poche/solvant/tubulure/administration.","ACV médicament sans DM de reconstitution ajouté.")) -> ACV médicament incluant PA + conditionnement + DM de reconstitution. Ne comprend pas poche/solvant/tubulure/administration.
A65: Fosfomycine IV | B65: Flacon 8 g | C65: flacon verre | D65: Fosfomycine | E65: 8000 | J65: =IFERROR(SUM(E65,G65,I65)/1000,"") -> 8 | K65: =$E$4 -> 100 | L65: =IF(J65="","",J65/1000*K65*(1+$E$5/100)) -> 0.84 | M65: =IF(J65="","",J65/1000*$E$6) -> 0.00076 | N65: =IF(C65="ampoule verre",$E$12,IF(C65="poche PEA",$E$13,$E$11)) -> 10 | O65: =IF(C65="ampoule verre",$E$8,IF(C65="poche PEA",$E$9,$E$7)) -> 7.1 | P65: =N65/1000*O65*(1+$E$5/100) -> 0.07455 | Q65: =$E$14 -> 3 | R65: =Q65/1000*$E$10 -> 0.00348 | S65: =IF(J65="","",SUM(L65:M65,P65,R65)) -> 0.91879 | T65: =IF(OR(J65="",K65=$E$4),"Élevé - FE PA générique",IF(W65<>"","À vérifier","Moyen")) -> Élevé - FE PA générique | U65: Breaking Stab | V65: EcovaMED v0.7 + hypothèses internes explicites | X65: =IF(A65="","",IF(OR(ISNUMBER(SEARCH("poche",C65)),ISNUMBER(SEARCH("ampoule",C65)),ISNUMBER(SEARCH("plastique",C65))),"Prêt à être dilué / administré (hypothèse)","Reconstitution nécessaire (hypothèse)")) -> Reconstitution nécessaire (hypothèse) | Y65: =IF(A65="","",IF(ISNUMBER(SEARCH("Reconstitution",X65)),"Flacon/poudre : ajout par défaut 1 seringue + 1 aiguille ; à revalider selon présentation exacte.","Ampoule/poche/présentation solution : aucun DM de reconstitution ajouté ; DM de perfusion calculés ailleurs.")) -> Flacon/poudre : ajout par défaut 1 seringue + 1 aiguille ; à revalider selon présentation exacte. | Z65: =IF(A65="","",IF(ISNUMBER(SEARCH("Reconstitution",X65)),1,0)) -> 1 | AA65: =IF(Z65>0,"SERINGUE_PP_24ML","") -> SERINGUE_PP_24ML | AB65: =IF(Z65>0,Z65*VLOOKUP(AA65,FACTEURS_ITEMS!$A$3:$J$30,4,FALSE()),0) -> 0.069 | AC65: =IF(A65="","",IF(ISNUMBER(SEARCH("Reconstitution",X65)),1,0)) -> 1 | AD65: =IF(AC65>0,"AIGUILLE_RECONSTITUTION","") -> AIGUILLE_RECONSTITUTION | AE65: =IF(AC65>0,AC65*VLOOKUP(AD65,FACTEURS_ITEMS!$A$3:$J$30,4,FALSE()),0) -> 0.01 | AF65: =IF(A65="","",AB65+AE65) -> 0.079 | AG65: =IF(A65="","",S65+AF65) -> 0.99779 | AH65: =IF(A65="","",IF(AF65>0,"ACV médicament incluant PA + conditionnement + DM de reconstitution. Ne comprend pas poche/solvant/tubulure/administration.","ACV médicament sans DM de reconstitution ajouté.")) -> ACV médicament incluant PA + conditionnement + DM de reconstitution. Ne comprend pas poche/solvant/tubulure/administration.
A66: Gentamicine | B66: Ampoule 80 mg | C66: ampoule verre | D66: Gentamicine | E66: 80 | J66: =IFERROR(SUM(E66,G66,I66)/1000,"") -> 0.08 | K66: =$E$4 -> 100 | L66: =IF(J66="","",J66/1000*K66*(1+$E$5/100)) -> 0.0084 | M66: =IF(J66="","",J66/1000*$E$6) -> 7.6e-06 | N66: =IF(C66="ampoule verre",$E$12,IF(C66="poche PEA",$E$13,$E$11)) -> 5 | O66: =IF(C66="ampoule verre",$E$8,IF(C66="poche PEA",$E$9,$E$7)) -> 5 | P66: =N66/1000*O66*(1+$E$5/100) -> 0.02625 | Q66: =$E$14 -> 3 | R66: =Q66/1000*$E$10 -> 0.00348 | S66: =IF(J66="","",SUM(L66:M66,P66,R66)) -> 0.0381376 | T66: =IF(OR(J66="",K66=$E$4),"Élevé - FE PA générique",IF(W66<>"","À vérifier","Moyen")) -> Élevé - FE PA générique | U66: Breaking Stab | V66: EcovaMED v0.7 + hypothèses internes explicites | X66: =IF(A66="","",IF(OR(ISNUMBER(SEARCH("poche",C66)),ISNUMBER(SEARCH("ampoule",C66)),ISNUMBER(SEARCH("plastique",C66))),"Prêt à être dilué / administré (hypothèse)","Reconstitution nécessaire (hypothèse)")) -> Prêt à être dilué / administré (hypothèse) | Y66: =IF(A66="","",IF(ISNUMBER(SEARCH("Reconstitution",X66)),"Flacon/poudre : ajout par défaut 1 seringue + 1 aiguille ; à revalider selon présentation exacte.","Ampoule/poche/présentation solution : aucun DM de reconstitution ajouté ; DM de perfusion calculés ailleurs.")) -> Ampoule/poche/présentation solution : aucun DM de reconstitution ajouté ; DM de perfusion calculés ailleurs. | Z66: =IF(A66="","",IF(ISNUMBER(SEARCH("Reconstitution",X66)),1,0)) -> 0 | AA66: =IF(Z66>0,"SERINGUE_PP_24ML","") | AB66: =IF(Z66>0,Z66*VLOOKUP(AA66,FACTEURS_ITEMS!$A$3:$J$30,4,FALSE()),0) -> 0 | AC66: =IF(A66="","",IF(ISNUMBER(SEARCH("Reconstitution",X66)),1,0)) -> 0 | AD66: =IF(AC66>0,"AIGUILLE_RECONSTITUTION","") | AE66: =IF(AC66>0,AC66*VLOOKUP(AD66,FACTEURS_ITEMS!$A$3:$J$30,4,FALSE()),0) -> 0 | AF66: =IF(A66="","",AB66+AE66) -> 0 | AG66: =IF(A66="","",S66+AF66) -> 0.0381376 | AH66: =IF(A66="","",IF(AF66>0,"ACV médicament incluant PA + conditionnement + DM de reconstitution. Ne comprend pas poche/solvant/tubulure/administration.","ACV médicament sans DM de reconstitution ajouté.")) -> ACV médicament sans DM de reconstitution ajouté.
A67: Gentamicine | B67: Ampoule 160 mg | C67: ampoule verre | D67: Gentamicine | E67: 160 | J67: =IFERROR(SUM(E67,G67,I67)/1000,"") -> 0.16 | K67: =$E$4 -> 100 | L67: =IF(J67="","",J67/1000*K67*(1+$E$5/100)) -> 0.0168 | M67: =IF(J67="","",J67/1000*$E$6) -> 1.52e-05 | N67: =IF(C67="ampoule verre",$E$12,IF(C67="poche PEA",$E$13,$E$11)) -> 5 | O67: =IF(C67="ampoule verre",$E$8,IF(C67="poche PEA",$E$9,$E$7)) -> 5 | P67: =N67/1000*O67*(1+$E$5/100) -> 0.02625 | Q67: =$E$14 -> 3 | R67: =Q67/1000*$E$10 -> 0.00348 | S67: =IF(J67="","",SUM(L67:M67,P67,R67)) -> 0.0465452 | T67: =IF(OR(J67="",K67=$E$4),"Élevé - FE PA générique",IF(W67<>"","À vérifier","Moyen")) -> Élevé - FE PA générique | U67: Breaking Stab | V67: EcovaMED v0.7 + hypothèses internes explicites | X67: =IF(A67="","",IF(OR(ISNUMBER(SEARCH("poche",C67)),ISNUMBER(SEARCH("ampoule",C67)),ISNUMBER(SEARCH("plastique",C67))),"Prêt à être dilué / administré (hypothèse)","Reconstitution nécessaire (hypothèse)")) -> Prêt à être dilué / administré (hypothèse) | Y67: =IF(A67="","",IF(ISNUMBER(SEARCH("Reconstitution",X67)),"Flacon/poudre : ajout par défaut 1 seringue + 1 aiguille ; à revalider selon présentation exacte.","Ampoule/poche/présentation solution : aucun DM de reconstitution ajouté ; DM de perfusion calculés ailleurs.")) -> Ampoule/poche/présentation solution : aucun DM de reconstitution ajouté ; DM de perfusion calculés ailleurs. | Z67: =IF(A67="","",IF(ISNUMBER(SEARCH("Reconstitution",X67)),1,0)) -> 0 | AA67: =IF(Z67>0,"SERINGUE_PP_24ML","") | AB67: =IF(Z67>0,Z67*VLOOKUP(AA67,FACTEURS_ITEMS!$A$3:$J$30,4,FALSE()),0) -> 0 | AC67: =IF(A67="","",IF(ISNUMBER(SEARCH("Reconstitution",X67)),1,0)) -> 0 | AD67: =IF(AC67>0,"AIGUILLE_RECONSTITUTION","") | AE67: =IF(AC67>0,AC67*VLOOKUP(AD67,FACTEURS_ITEMS!$A$3:$J$30,4,FALSE()),0) -> 0 | AF67: =IF(A67="","",AB67+AE67) -> 0 | AG67: =IF(A67="","",S67+AF67) -> 0.0465452 | AH67: =IF(A67="","",IF(AF67>0,"ACV médicament incluant PA + conditionnement + DM de reconstitution. Ne comprend pas poche/solvant/tubulure/administration.","ACV médicament sans DM de reconstitution ajouté.")) -> ACV médicament sans DM de reconstitution ajouté.
A68: Imipénème/cilastatine | B68: Flacon 500/500 mg | C68: flacon verre | D68: Imipénème | E68: 500 | F68: Cilastatine | G68: 500 | J68: =IFERROR(SUM(E68,G68,I68)/1000,"") -> 1 | K68: =$E$4 -> 100 | L68: =IF(J68="","",J68/1000*K68*(1+$E$5/100)) -> 0.105 | M68: =IF(J68="","",J68/1000*$E$6) -> 9.5e-05 | N68: =IF(C68="ampoule verre",$E$12,IF(C68="poche PEA",$E$13,$E$11)) -> 10 | O68: =IF(C68="ampoule verre",$E$8,IF(C68="poche PEA",$E$9,$E$7)) -> 7.1 | P68: =N68/1000*O68*(1+$E$5/100) -> 0.07455 | Q68: =$E$14 -> 3 | R68: =Q68/1000*$E$10 -> 0.00348 | S68: =IF(J68="","",SUM(L68:M68,P68,R68)) -> 0.183125 | T68: =IF(OR(J68="",K68=$E$4),"Élevé - FE PA générique",IF(W68<>"","À vérifier","Moyen")) -> Élevé - FE PA générique | U68: Breaking Stab | V68: EcovaMED v0.7 + hypothèses internes explicites | X68: =IF(A68="","",IF(OR(ISNUMBER(SEARCH("poche",C68)),ISNUMBER(SEARCH("ampoule",C68)),ISNUMBER(SEARCH("plastique",C68))),"Prêt à être dilué / administré (hypothèse)","Reconstitution nécessaire (hypothèse)")) -> Reconstitution nécessaire (hypothèse) | Y68: =IF(A68="","",IF(ISNUMBER(SEARCH("Reconstitution",X68)),"Flacon/poudre : ajout par défaut 1 seringue + 1 aiguille ; à revalider selon présentation exacte.","Ampoule/poche/présentation solution : aucun DM de reconstitution ajouté ; DM de perfusion calculés ailleurs.")) -> Flacon/poudre : ajout par défaut 1 seringue + 1 aiguille ; à revalider selon présentation exacte. | Z68: =IF(A68="","",IF(ISNUMBER(SEARCH("Reconstitution",X68)),1,0)) -> 1 | AA68: =IF(Z68>0,"SERINGUE_PP_24ML","") -> SERINGUE_PP_24ML | AB68: =IF(Z68>0,Z68*VLOOKUP(AA68,FACTEURS_ITEMS!$A$3:$J$30,4,FALSE()),0) -> 0.069 | AC68: =IF(A68="","",IF(ISNUMBER(SEARCH("Reconstitution",X68)),1,0)) -> 1 | AD68: =IF(AC68>0,"AIGUILLE_RECONSTITUTION","") -> AIGUILLE_RECONSTITUTION | AE68: =IF(AC68>0,AC68*VLOOKUP(AD68,FACTEURS_ITEMS!$A$3:$J$30,4,FALSE()),0) -> 0.01 | AF68: =IF(A68="","",AB68+AE68) -> 0.079 | AG68: =IF(A68="","",S68+AF68) -> 0.262125 | AH68: =IF(A68="","",IF(AF68>0,"ACV médicament incluant PA + conditionnement + DM de reconstitution. Ne comprend pas poche/solvant/tubulure/administration.","ACV médicament sans DM de reconstitution ajouté.")) -> ACV médicament incluant PA + conditionnement + DM de reconstitution. Ne comprend pas poche/solvant/tubulure/administration.
A69: Imipénem/relebactam | B69: Flacon 500/500/250 mg | C69: flacon verre | D69: Imipénème | E69: 500 | F69: Cilastatine | G69: 500 | H69: Relebactam | I69: 250 | J69: =IFERROR(SUM(E69,G69,I69)/1000,"") -> 1.25 | K69: =$E$4 -> 100 | L69: =IF(J69="","",J69/1000*K69*(1+$E$5/100)) -> 0.13125 | M69: =IF(J69="","",J69/1000*$E$6) -> 0.00011875 | N69: =IF(C69="ampoule verre",$E$12,IF(C69="poche PEA",$E$13,$E$11)) -> 10 | O69: =IF(C69="ampoule verre",$E$8,IF(C69="poche PEA",$E$9,$E$7)) -> 7.1 | P69: =N69/1000*O69*(1+$E$5/100) -> 0.07455 | Q69: =$E$14 -> 3 | R69: =Q69/1000*$E$10 -> 0.00348 | S69: =IF(J69="","",SUM(L69:M69,P69,R69)) -> 0.20939875 | T69: =IF(OR(J69="",K69=$E$4),"Élevé - FE PA générique",IF(W69<>"","À vérifier","Moyen")) -> Élevé - FE PA générique | U69: CHICAS/Breaking Stab | V69: EcovaMED v0.7 + hypothèses internes explicites | X69: =IF(A69="","",IF(OR(ISNUMBER(SEARCH("poche",C69)),ISNUMBER(SEARCH("ampoule",C69)),ISNUMBER(SEARCH("plastique",C69))),"Prêt à être dilué / administré (hypothèse)","Reconstitution nécessaire (hypothèse)")) -> Reconstitution nécessaire (hypothèse) | Y69: =IF(A69="","",IF(ISNUMBER(SEARCH("Reconstitution",X69)),"Flacon/poudre : ajout par défaut 1 seringue + 1 aiguille ; à revalider selon présentation exacte.","Ampoule/poche/présentation solution : aucun DM de reconstitution ajouté ; DM de perfusion calculés ailleurs.")) -> Flacon/poudre : ajout par défaut 1 seringue + 1 aiguille ; à revalider selon présentation exacte. | Z69: =IF(A69="","",IF(ISNUMBER(SEARCH("Reconstitution",X69)),1,0)) -> 1 | AA69: =IF(Z69>0,"SERINGUE_PP_24ML","") -> SERINGUE_PP_24ML | AB69: =IF(Z69>0,Z69*VLOOKUP(AA69,FACTEURS_ITEMS!$A$3:$J$30,4,FALSE()),0) -> 0.069 | AC69: =IF(A69="","",IF(ISNUMBER(SEARCH("Reconstitution",X69)),1,0)) -> 1 | AD69: =IF(AC69>0,"AIGUILLE_RECONSTITUTION","") -> AIGUILLE_RECONSTITUTION | AE69: =IF(AC69>0,AC69*VLOOKUP(AD69,FACTEURS_ITEMS!$A$3:$J$30,4,FALSE()),0) -> 0.01 | AF69: =IF(A69="","",AB69+AE69) -> 0.079 | AG69: =IF(A69="","",S69+AF69) -> 0.28839875 | AH69: =IF(A69="","",IF(AF69>0,"ACV médicament incluant PA + conditionnement + DM de reconstitution. Ne comprend pas poche/solvant/tubulure/administration.","ACV médicament sans DM de reconstitution ajouté.")) -> ACV médicament incluant PA + conditionnement + DM de reconstitution. Ne comprend pas poche/solvant/tubulure/administration.
A70: Isavuconazole | B70: Flacon 200 mg | C70: flacon verre | D70: Isavuconazole | E70: 200 | J70: =IFERROR(SUM(E70,G70,I70)/1000,"") -> 0.2 | K70: =$E$4 -> 100 | L70: =IF(J70="","",J70/1000*K70*(1+$E$5/100)) -> 0.021 | M70: =IF(J70="","",J70/1000*$E$6) -> 1.9e-05 | N70: =IF(C70="ampoule verre",$E$12,IF(C70="poche PEA",$E$13,$E$11)) -> 10 | O70: =IF(C70="ampoule verre",$E$8,IF(C70="poche PEA",$E$9,$E$7)) -> 7.1 | P70: =N70/1000*O70*(1+$E$5/100) -> 0.07455 | Q70: =$E$14 -> 3 | R70: =Q70/1000*$E$10 -> 0.00348 | S70: =IF(J70="","",SUM(L70:M70,P70,R70)) -> 0.099049 | T70: =IF(OR(J70="",K70=$E$4),"Élevé - FE PA générique",IF(W70<>"","À vérifier","Moyen")) -> Élevé - FE PA générique | U70: Breaking Stab | V70: EcovaMED v0.7 + hypothèses internes explicites | X70: =IF(A70="","",IF(OR(ISNUMBER(SEARCH("poche",C70)),ISNUMBER(SEARCH("ampoule",C70)),ISNUMBER(SEARCH("plastique",C70))),"Prêt à être dilué / administré (hypothèse)","Reconstitution nécessaire (hypothèse)")) -> Reconstitution nécessaire (hypothèse) | Y70: =IF(A70="","",IF(ISNUMBER(SEARCH("Reconstitution",X70)),"Flacon/poudre : ajout par défaut 1 seringue + 1 aiguille ; à revalider selon présentation exacte.","Ampoule/poche/présentation solution : aucun DM de reconstitution ajouté ; DM de perfusion calculés ailleurs.")) -> Flacon/poudre : ajout par défaut 1 seringue + 1 aiguille ; à revalider selon présentation exacte. | Z70: =IF(A70="","",IF(ISNUMBER(SEARCH("Reconstitution",X70)),1,0)) -> 1 | AA70: =IF(Z70>0,"SERINGUE_PP_24ML","") -> SERINGUE_PP_24ML | AB70: =IF(Z70>0,Z70*VLOOKUP(AA70,FACTEURS_ITEMS!$A$3:$J$30,4,FALSE()),0) -> 0.069 | AC70: =IF(A70="","",IF(ISNUMBER(SEARCH("Reconstitution",X70)),1,0)) -> 1 | AD70: =IF(AC70>0,"AIGUILLE_RECONSTITUTION","") -> AIGUILLE_RECONSTITUTION | AE70: =IF(AC70>0,AC70*VLOOKUP(AD70,FACTEURS_ITEMS!$A$3:$J$30,4,FALSE()),0) -> 0.01 | AF70: =IF(A70="","",AB70+AE70) -> 0.079 | AG70: =IF(A70="","",S70+AF70) -> 0.178049 | AH70: =IF(A70="","",IF(AF70>0,"ACV médicament incluant PA + conditionnement + DM de reconstitution. Ne comprend pas poche/solvant/tubulure/administration.","ACV médicament sans DM de reconstitution ajouté.")) -> ACV médicament incluant PA + conditionnement + DM de reconstitution. Ne comprend pas poche/solvant/tubulure/administration.
A71: Levofloxacine | B71: Poche prêt-à-l’emploi 500 mg | C71: poche PEA | D71: Levofloxacine | E71: 500 | J71: =IFERROR(SUM(E71,G71,I71)/1000,"") -> 0.5 | K71: =$E$4 -> 100 | L71: =IF(J71="","",J71/1000*K71*(1+$E$5/100)) -> 0.0525 | M71: =IF(J71="","",J71/1000*$E$6) -> 4.75e-05 | N71: =IF(C71="ampoule verre",$E$12,IF(C71="poche PEA",$E$13,$E$11)) -> 20 | O71: =IF(C71="ampoule verre",$E$8,IF(C71="poche PEA",$E$9,$E$7)) -> 4.2 | P71: =N71/1000*O71*(1+$E$5/100) -> 0.0882 | Q71: =$E$14 -> 3 | R71: =Q71/1000*$E$10 -> 0.00348 | S71: =IF(J71="","",SUM(L71:M71,P71,R71)) -> 0.1442275 | T71: =IF(OR(J71="",K71=$E$4),"Élevé - FE PA générique",IF(W71<>"","À vérifier","Moyen")) -> Élevé - FE PA générique | U71: Breaking Stab | V71: EcovaMED v0.7 + hypothèses internes explicites | W71: Présentation prêt-à-l’emploi : le conditionnement primaire réel doit être remplacé par le poids fournisseur si disponible. | X71: =IF(A71="","",IF(OR(ISNUMBER(SEARCH("poche",C71)),ISNUMBER(SEARCH("ampoule",C71)),ISNUMBER(SEARCH("plastique",C71))),"Prêt à être dilué / administré (hypothèse)","Reconstitution nécessaire (hypothèse)")) -> Prêt à être dilué / administré (hypothèse) | Y71: =IF(A71="","",IF(ISNUMBER(SEARCH("Reconstitution",X71)),"Flacon/poudre : ajout par défaut 1 seringue + 1 aiguille ; à revalider selon présentation exacte.","Ampoule/poche/présentation solution : aucun DM de reconstitution ajouté ; DM de perfusion calculés ailleurs.")) -> Ampoule/poche/présentation solution : aucun DM de reconstitution ajouté ; DM de perfusion calculés ailleurs. | Z71: =IF(A71="","",IF(ISNUMBER(SEARCH("Reconstitution",X71)),1,0)) -> 0 | AA71: =IF(Z71>0,"SERINGUE_PP_24ML","") | AB71: =IF(Z71>0,Z71*VLOOKUP(AA71,FACTEURS_ITEMS!$A$3:$J$30,4,FALSE()),0) -> 0 | AC71: =IF(A71="","",IF(ISNUMBER(SEARCH("Reconstitution",X71)),1,0)) -> 0 | AD71: =IF(AC71>0,"AIGUILLE_RECONSTITUTION","") | AE71: =IF(AC71>0,AC71*VLOOKUP(AD71,FACTEURS_ITEMS!$A$3:$J$30,4,FALSE()),0) -> 0 | AF71: =IF(A71="","",AB71+AE71) -> 0 | AG71: =IF(A71="","",S71+AF71) -> 0.1442275 | AH71: =IF(A71="","",IF(AF71>0,"ACV médicament incluant PA + conditionnement + DM de reconstitution. Ne comprend pas poche/solvant/tubulure/administration.","ACV médicament sans DM de reconstitution ajouté.")) -> ACV médicament sans DM de reconstitution ajouté.
A72: Linezolide | B72: Poche prêt-à-l’emploi 600 mg | C72: poche PEA | D72: Linezolide | E72: 600 | J72: =IFERROR(SUM(E72,G72,I72)/1000,"") -> 0.6 | K72: =$E$4 -> 100 | L72: =IF(J72="","",J72/1000*K72*(1+$E$5/100)) -> 0.063 | M72: =IF(J72="","",J72/1000*$E$6) -> 5.7e-05 | N72: =IF(C72="ampoule verre",$E$12,IF(C72="poche PEA",$E$13,$E$11)) -> 20 | O72: =IF(C72="ampoule verre",$E$8,IF(C72="poche PEA",$E$9,$E$7)) -> 4.2 | P72: =N72/1000*O72*(1+$E$5/100) -> 0.0882 | Q72: =$E$14 -> 3 | R72: =Q72/1000*$E$10 -> 0.00348 | S72: =IF(J72="","",SUM(L72:M72,P72,R72)) -> 0.154737 | T72: =IF(OR(J72="",K72=$E$4),"Élevé - FE PA générique",IF(W72<>"","À vérifier","Moyen")) -> Élevé - FE PA générique | U72: Breaking Stab | V72: EcovaMED v0.7 + hypothèses internes explicites | W72: Présentation prêt-à-l’emploi : le conditionnement primaire réel doit être remplacé par le poids fournisseur si disponible. | X72: =IF(A72="","",IF(OR(ISNUMBER(SEARCH("poche",C72)),ISNUMBER(SEARCH("ampoule",C72)),ISNUMBER(SEARCH("plastique",C72))),"Prêt à être dilué / administré (hypothèse)","Reconstitution nécessaire (hypothèse)")) -> Prêt à être dilué / administré (hypothèse) | Y72: =IF(A72="","",IF(ISNUMBER(SEARCH("Reconstitution",X72)),"Flacon/poudre : ajout par défaut 1 seringue + 1 aiguille ; à revalider selon présentation exacte.","Ampoule/poche/présentation solution : aucun DM de reconstitution ajouté ; DM de perfusion calculés ailleurs.")) -> Ampoule/poche/présentation solution : aucun DM de reconstitution ajouté ; DM de perfusion calculés ailleurs. | Z72: =IF(A72="","",IF(ISNUMBER(SEARCH("Reconstitution",X72)),1,0)) -> 0 | AA72: =IF(Z72>0,"SERINGUE_PP_24ML","") | AB72: =IF(Z72>0,Z72*VLOOKUP(AA72,FACTEURS_ITEMS!$A$3:$J$30,4,FALSE()),0) -> 0 | AC72: =IF(A72="","",IF(ISNUMBER(SEARCH("Reconstitution",X72)),1,0)) -> 0 | AD72: =IF(AC72>0,"AIGUILLE_RECONSTITUTION","") | AE72: =IF(AC72>0,AC72*VLOOKUP(AD72,FACTEURS_ITEMS!$A$3:$J$30,4,FALSE()),0) -> 0 | AF72: =IF(A72="","",AB72+AE72) -> 0 | AG72: =IF(A72="","",S72+AF72) -> 0.154737 | AH72: =IF(A72="","",IF(AF72>0,"ACV médicament incluant PA + conditionnement + DM de reconstitution. Ne comprend pas poche/solvant/tubulure/administration.","ACV médicament sans DM de reconstitution ajouté.")) -> ACV médicament sans DM de reconstitution ajouté.
A73: Méropénem | B73: Flacon 500 mg | C73: flacon verre | D73: Méropénem | E73: 500 | J73: =IFERROR(SUM(E73,G73,I73)/1000,"") -> 0.5 | K73: =$E$4 -> 100 | L73: =IF(J73="","",J73/1000*K73*(1+$E$5/100)) -> 0.0525 | M73: =IF(J73="","",J73/1000*$E$6) -> 4.75e-05 | N73: =IF(C73="ampoule verre",$E$12,IF(C73="poche PEA",$E$13,$E$11)) -> 10 | O73: =IF(C73="ampoule verre",$E$8,IF(C73="poche PEA",$E$9,$E$7)) -> 7.1 | P73: =N73/1000*O73*(1+$E$5/100) -> 0.07455 | Q73: =$E$14 -> 3 | R73: =Q73/1000*$E$10 -> 0.00348 | S73: =IF(J73="","",SUM(L73:M73,P73,R73)) -> 0.1305775 | T73: =IF(OR(J73="",K73=$E$4),"Élevé - FE PA générique",IF(W73<>"","À vérifier","Moyen")) -> Élevé - FE PA générique | U73: Breaking Stab | V73: EcovaMED v0.7 + hypothèses internes explicites | X73: =IF(A73="","",IF(OR(ISNUMBER(SEARCH("poche",C73)),ISNUMBER(SEARCH("ampoule",C73)),ISNUMBER(SEARCH("plastique",C73))),"Prêt à être dilué / administré (hypothèse)","Reconstitution nécessaire (hypothèse)")) -> Reconstitution nécessaire (hypothèse) | Y73: =IF(A73="","",IF(ISNUMBER(SEARCH("Reconstitution",X73)),"Flacon/poudre : ajout par défaut 1 seringue + 1 aiguille ; à revalider selon présentation exacte.","Ampoule/poche/présentation solution : aucun DM de reconstitution ajouté ; DM de perfusion calculés ailleurs.")) -> Flacon/poudre : ajout par défaut 1 seringue + 1 aiguille ; à revalider selon présentation exacte. | Z73: =IF(A73="","",IF(ISNUMBER(SEARCH("Reconstitution",X73)),1,0)) -> 1 | AA73: =IF(Z73>0,"SERINGUE_PP_24ML","") -> SERINGUE_PP_24ML | AB73: =IF(Z73>0,Z73*VLOOKUP(AA73,FACTEURS_ITEMS!$A$3:$J$30,4,FALSE()),0) -> 0.069 | AC73: =IF(A73="","",IF(ISNUMBER(SEARCH("Reconstitution",X73)),1,0)) -> 1 | AD73: =IF(AC73>0,"AIGUILLE_RECONSTITUTION","") -> AIGUILLE_RECONSTITUTION | AE73: =IF(AC73>0,AC73*VLOOKUP(AD73,FACTEURS_ITEMS!$A$3:$J$30,4,FALSE()),0) -> 0.01 | AF73: =IF(A73="","",AB73+AE73) -> 0.079 | AG73: =IF(A73="","",S73+AF73) -> 0.2095775 | AH73: =IF(A73="","",IF(AF73>0,"ACV médicament incluant PA + conditionnement + DM de reconstitution. Ne comprend pas poche/solvant/tubulure/administration.","ACV médicament sans DM de reconstitution ajouté.")) -> ACV médicament incluant PA + conditionnement + DM de reconstitution. Ne comprend pas poche/solvant/tubulure/administration.
A74: Méropénem | B74: Flacon 1 g | C74: flacon verre | D74: Méropénem | E74: 1000 | J74: =IFERROR(SUM(E74,G74,I74)/1000,"") -> 1 | K74: =$E$4 -> 100 | L74: =IF(J74="","",J74/1000*K74*(1+$E$5/100)) -> 0.105 | M74: =IF(J74="","",J74/1000*$E$6) -> 9.5e-05 | N74: =IF(C74="ampoule verre",$E$12,IF(C74="poche PEA",$E$13,$E$11)) -> 10 | O74: =IF(C74="ampoule verre",$E$8,IF(C74="poche PEA",$E$9,$E$7)) -> 7.1 | P74: =N74/1000*O74*(1+$E$5/100) -> 0.07455 | Q74: =$E$14 -> 3 | R74: =Q74/1000*$E$10 -> 0.00348 | S74: =IF(J74="","",SUM(L74:M74,P74,R74)) -> 0.183125 | T74: =IF(OR(J74="",K74=$E$4),"Élevé - FE PA générique",IF(W74<>"","À vérifier","Moyen")) -> Élevé - FE PA générique | U74: Breaking Stab | V74: EcovaMED v0.7 + hypothèses internes explicites | X74: =IF(A74="","",IF(OR(ISNUMBER(SEARCH("poche",C74)),ISNUMBER(SEARCH("ampoule",C74)),ISNUMBER(SEARCH("plastique",C74))),"Prêt à être dilué / administré (hypothèse)","Reconstitution nécessaire (hypothèse)")) -> Reconstitution nécessaire (hypothèse) | Y74: =IF(A74="","",IF(ISNUMBER(SEARCH("Reconstitution",X74)),"Flacon/poudre : ajout par défaut 1 seringue + 1 aiguille ; à revalider selon présentation exacte.","Ampoule/poche/présentation solution : aucun DM de reconstitution ajouté ; DM de perfusion calculés ailleurs.")) -> Flacon/poudre : ajout par défaut 1 seringue + 1 aiguille ; à revalider selon présentation exacte. | Z74: =IF(A74="","",IF(ISNUMBER(SEARCH("Reconstitution",X74)),1,0)) -> 1 | AA74: =IF(Z74>0,"SERINGUE_PP_24ML","") -> SERINGUE_PP_24ML | AB74: =IF(Z74>0,Z74*VLOOKUP(AA74,FACTEURS_ITEMS!$A$3:$J$30,4,FALSE()),0) -> 0.069 | AC74: =IF(A74="","",IF(ISNUMBER(SEARCH("Reconstitution",X74)),1,0)) -> 1 | AD74: =IF(AC74>0,"AIGUILLE_RECONSTITUTION","") -> AIGUILLE_RECONSTITUTION | AE74: =IF(AC74>0,AC74*VLOOKUP(AD74,FACTEURS_ITEMS!$A$3:$J$30,4,FALSE()),0) -> 0.01 | AF74: =IF(A74="","",AB74+AE74) -> 0.079 | AG74: =IF(A74="","",S74+AF74) -> 0.262125 | AH74: =IF(A74="","",IF(AF74>0,"ACV médicament incluant PA + conditionnement + DM de reconstitution. Ne comprend pas poche/solvant/tubulure/administration.","ACV médicament sans DM de reconstitution ajouté.")) -> ACV médicament incluant PA + conditionnement + DM de reconstitution. Ne comprend pas poche/solvant/tubulure/administration.
A75: Méropénem | B75: Flacon 2 g | C75: flacon verre | D75: Méropénem | E75: 2000 | J75: =IFERROR(SUM(E75,G75,I75)/1000,"") -> 2 | K75: =$E$4 -> 100 | L75: =IF(J75="","",J75/1000*K75*(1+$E$5/100)) -> 0.21 | M75: =IF(J75="","",J75/1000*$E$6) -> 0.00019 | N75: =IF(C75="ampoule verre",$E$12,IF(C75="poche PEA",$E$13,$E$11)) -> 10 | O75: =IF(C75="ampoule verre",$E$8,IF(C75="poche PEA",$E$9,$E$7)) -> 7.1 | P75: =N75/1000*O75*(1+$E$5/100) -> 0.07455 | Q75: =$E$14 -> 3 | R75: =Q75/1000*$E$10 -> 0.00348 | S75: =IF(J75="","",SUM(L75:M75,P75,R75)) -> 0.28822 | T75: =IF(OR(J75="",K75=$E$4),"Élevé - FE PA générique",IF(W75<>"","À vérifier","Moyen")) -> Élevé - FE PA générique | U75: Breaking Stab | V75: EcovaMED v0.7 + hypothèses internes explicites | X75: =IF(A75="","",IF(OR(ISNUMBER(SEARCH("poche",C75)),ISNUMBER(SEARCH("ampoule",C75)),ISNUMBER(SEARCH("plastique",C75))),"Prêt à être dilué / administré (hypothèse)","Reconstitution nécessaire (hypothèse)")) -> Reconstitution nécessaire (hypothèse) | Y75: =IF(A75="","",IF(ISNUMBER(SEARCH("Reconstitution",X75)),"Flacon/poudre : ajout par défaut 1 seringue + 1 aiguille ; à revalider selon présentation exacte.","Ampoule/poche/présentation solution : aucun DM de reconstitution ajouté ; DM de perfusion calculés ailleurs.")) -> Flacon/poudre : ajout par défaut 1 seringue + 1 aiguille ; à revalider selon présentation exacte. | Z75: =IF(A75="","",IF(ISNUMBER(SEARCH("Reconstitution",X75)),1,0)) -> 1 | AA75: =IF(Z75>0,"SERINGUE_PP_24ML","") -> SERINGUE_PP_24ML | AB75: =IF(Z75>0,Z75*VLOOKUP(AA75,FACTEURS_ITEMS!$A$3:$J$30,4,FALSE()),0) -> 0.069 | AC75: =IF(A75="","",IF(ISNUMBER(SEARCH("Reconstitution",X75)),1,0)) -> 1 | AD75: =IF(AC75>0,"AIGUILLE_RECONSTITUTION","") -> AIGUILLE_RECONSTITUTION | AE75: =IF(AC75>0,AC75*VLOOKUP(AD75,FACTEURS_ITEMS!$A$3:$J$30,4,FALSE()),0) -> 0.01 | AF75: =IF(A75="","",AB75+AE75) -> 0.079 | AG75: =IF(A75="","",S75+AF75) -> 0.36722 | AH75: =IF(A75="","",IF(AF75>0,"ACV médicament incluant PA + conditionnement + DM de reconstitution. Ne comprend pas poche/solvant/tubulure/administration.","ACV médicament sans DM de reconstitution ajouté.")) -> ACV médicament incluant PA + conditionnement + DM de reconstitution. Ne comprend pas poche/solvant/tubulure/administration.
A76: Méropénem/vaborbactam | B76: Flacon 1 g/1 g | C76: flacon verre | D76: Méropénem | E76: 1000 | F76: Vaborbactam | G76: 1000 | J76: =IFERROR(SUM(E76,G76,I76)/1000,"") -> 2 | K76: =$E$4 -> 100 | L76: =IF(J76="","",J76/1000*K76*(1+$E$5/100)) -> 0.21 | M76: =IF(J76="","",J76/1000*$E$6) -> 0.00019 | N76: =IF(C76="ampoule verre",$E$12,IF(C76="poche PEA",$E$13,$E$11)) -> 10 | O76: =IF(C76="ampoule verre",$E$8,IF(C76="poche PEA",$E$9,$E$7)) -> 7.1 | P76: =N76/1000*O76*(1+$E$5/100) -> 0.07455 | Q76: =$E$14 -> 3 | R76: =Q76/1000*$E$10 -> 0.00348 | S76: =IF(J76="","",SUM(L76:M76,P76,R76)) -> 0.28822 | T76: =IF(OR(J76="",K76=$E$4),"Élevé - FE PA générique",IF(W76<>"","À vérifier","Moyen")) -> Élevé - FE PA générique | U76: CHICAS/Breaking Stab | V76: EcovaMED v0.7 + hypothèses internes explicites | X76: =IF(A76="","",IF(OR(ISNUMBER(SEARCH("poche",C76)),ISNUMBER(SEARCH("ampoule",C76)),ISNUMBER(SEARCH("plastique",C76))),"Prêt à être dilué / administré (hypothèse)","Reconstitution nécessaire (hypothèse)")) -> Reconstitution nécessaire (hypothèse) | Y76: =IF(A76="","",IF(ISNUMBER(SEARCH("Reconstitution",X76)),"Flacon/poudre : ajout par défaut 1 seringue + 1 aiguille ; à revalider selon présentation exacte.","Ampoule/poche/présentation solution : aucun DM de reconstitution ajouté ; DM de perfusion calculés ailleurs.")) -> Flacon/poudre : ajout par défaut 1 seringue + 1 aiguille ; à revalider selon présentation exacte. | Z76: =IF(A76="","",IF(ISNUMBER(SEARCH("Reconstitution",X76)),1,0)) -> 1 | AA76: =IF(Z76>0,"SERINGUE_PP_24ML","") -> SERINGUE_PP_24ML | AB76: =IF(Z76>0,Z76*VLOOKUP(AA76,FACTEURS_ITEMS!$A$3:$J$30,4,FALSE()),0) -> 0.069 | AC76: =IF(A76="","",IF(ISNUMBER(SEARCH("Reconstitution",X76)),1,0)) -> 1 | AD76: =IF(AC76>0,"AIGUILLE_RECONSTITUTION","") -> AIGUILLE_RECONSTITUTION | AE76: =IF(AC76>0,AC76*VLOOKUP(AD76,FACTEURS_ITEMS!$A$3:$J$30,4,FALSE()),0) -> 0.01 | AF76: =IF(A76="","",AB76+AE76) -> 0.079 | AG76: =IF(A76="","",S76+AF76) -> 0.36722 | AH76: =IF(A76="","",IF(AF76>0,"ACV médicament incluant PA + conditionnement + DM de reconstitution. Ne comprend pas poche/solvant/tubulure/administration.","ACV médicament sans DM de reconstitution ajouté.")) -> ACV médicament incluant PA + conditionnement + DM de reconstitution. Ne comprend pas poche/solvant/tubulure/administration.
A77: Métronidazole | B77: Poche prêt-à-l’emploi 500 mg | C77: poche PEA | D77: Métronidazole | E77: 500 | J77: =IFERROR(SUM(E77,G77,I77)/1000,"") -> 0.5 | K77: =$E$4 -> 100 | L77: =IF(J77="","",J77/1000*K77*(1+$E$5/100)) -> 0.0525 | M77: =IF(J77="","",J77/1000*$E$6) -> 4.75e-05 | N77: =IF(C77="ampoule verre",$E$12,IF(C77="poche PEA",$E$13,$E$11)) -> 20 | O77: =IF(C77="ampoule verre",$E$8,IF(C77="poche PEA",$E$9,$E$7)) -> 4.2 | P77: =N77/1000*O77*(1+$E$5/100) -> 0.0882 | Q77: =$E$14 -> 3 | R77: =Q77/1000*$E$10 -> 0.00348 | S77: =IF(J77="","",SUM(L77:M77,P77,R77)) -> 0.1442275 | T77: =IF(OR(J77="",K77=$E$4),"Élevé - FE PA générique",IF(W77<>"","À vérifier","Moyen")) -> Élevé - FE PA générique | U77: Breaking Stab | V77: EcovaMED v0.7 + hypothèses internes explicites | W77: Présentation prêt-à-l’emploi : le conditionnement primaire réel doit être remplacé par le poids fournisseur si disponible. | X77: =IF(A77="","",IF(OR(ISNUMBER(SEARCH("poche",C77)),ISNUMBER(SEARCH("ampoule",C77)),ISNUMBER(SEARCH("plastique",C77))),"Prêt à être dilué / administré (hypothèse)","Reconstitution nécessaire (hypothèse)")) -> Prêt à être dilué / administré (hypothèse) | Y77: =IF(A77="","",IF(ISNUMBER(SEARCH("Reconstitution",X77)),"Flacon/poudre : ajout par défaut 1 seringue + 1 aiguille ; à revalider selon présentation exacte.","Ampoule/poche/présentation solution : aucun DM de reconstitution ajouté ; DM de perfusion calculés ailleurs.")) -> Ampoule/poche/présentation solution : aucun DM de reconstitution ajouté ; DM de perfusion calculés ailleurs. | Z77: =IF(A77="","",IF(ISNUMBER(SEARCH("Reconstitution",X77)),1,0)) -> 0 | AA77: =IF(Z77>0,"SERINGUE_PP_24ML","") | AB77: =IF(Z77>0,Z77*VLOOKUP(AA77,FACTEURS_ITEMS!$A$3:$J$30,4,FALSE()),0) -> 0 | AC77: =IF(A77="","",IF(ISNUMBER(SEARCH("Reconstitution",X77)),1,0)) -> 0 | AD77: =IF(AC77>0,"AIGUILLE_RECONSTITUTION","") | AE77: =IF(AC77>0,AC77*VLOOKUP(AD77,FACTEURS_ITEMS!$A$3:$J$30,4,FALSE()),0) -> 0 | AF77: =IF(A77="","",AB77+AE77) -> 0 | AG77: =IF(A77="","",S77+AF77) -> 0.1442275 | AH77: =IF(A77="","",IF(AF77>0,"ACV médicament incluant PA + conditionnement + DM de reconstitution. Ne comprend pas poche/solvant/tubulure/administration.","ACV médicament sans DM de reconstitution ajouté.")) -> ACV médicament sans DM de reconstitution ajouté.
A78: Micafungine | B78: Flacon 50 mg | C78: flacon verre | D78: Micafungine | E78: 50 | J78: =IFERROR(SUM(E78,G78,I78)/1000,"") -> 0.05 | K78: =$E$4 -> 100 | L78: =IF(J78="","",J78/1000*K78*(1+$E$5/100)) -> 0.00525 | M78: =IF(J78="","",J78/1000*$E$6) -> 4.75e-06 | N78: =IF(C78="ampoule verre",$E$12,IF(C78="poche PEA",$E$13,$E$11)) -> 10 | O78: =IF(C78="ampoule verre",$E$8,IF(C78="poche PEA",$E$9,$E$7)) -> 7.1 | P78: =N78/1000*O78*(1+$E$5/100) -> 0.07455 | Q78: =$E$14 -> 3 | R78: =Q78/1000*$E$10 -> 0.00348 | S78: =IF(J78="","",SUM(L78:M78,P78,R78)) -> 0.08328475 | T78: =IF(OR(J78="",K78=$E$4),"Élevé - FE PA générique",IF(W78<>"","À vérifier","Moyen")) -> Élevé - FE PA générique | U78: Breaking Stab | V78: EcovaMED v0.7 + hypothèses internes explicites | X78: =IF(A78="","",IF(OR(ISNUMBER(SEARCH("poche",C78)),ISNUMBER(SEARCH("ampoule",C78)),ISNUMBER(SEARCH("plastique",C78))),"Prêt à être dilué / administré (hypothèse)","Reconstitution nécessaire (hypothèse)")) -> Reconstitution nécessaire (hypothèse) | Y78: =IF(A78="","",IF(ISNUMBER(SEARCH("Reconstitution",X78)),"Flacon/poudre : ajout par défaut 1 seringue + 1 aiguille ; à revalider selon présentation exacte.","Ampoule/poche/présentation solution : aucun DM de reconstitution ajouté ; DM de perfusion calculés ailleurs.")) -> Flacon/poudre : ajout par défaut 1 seringue + 1 aiguille ; à revalider selon présentation exacte. | Z78: =IF(A78="","",IF(ISNUMBER(SEARCH("Reconstitution",X78)),1,0)) -> 1 | AA78: =IF(Z78>0,"SERINGUE_PP_24ML","") -> SERINGUE_PP_24ML | AB78: =IF(Z78>0,Z78*VLOOKUP(AA78,FACTEURS_ITEMS!$A$3:$J$30,4,FALSE()),0) -> 0.069 | AC78: =IF(A78="","",IF(ISNUMBER(SEARCH("Reconstitution",X78)),1,0)) -> 1 | AD78: =IF(AC78>0,"AIGUILLE_RECONSTITUTION","") -> AIGUILLE_RECONSTITUTION | AE78: =IF(AC78>0,AC78*VLOOKUP(AD78,FACTEURS_ITEMS!$A$3:$J$30,4,FALSE()),0) -> 0.01 | AF78: =IF(A78="","",AB78+AE78) -> 0.079 | AG78: =IF(A78="","",S78+AF78) -> 0.16228475 | AH78: =IF(A78="","",IF(AF78>0,"ACV médicament incluant PA + conditionnement + DM de reconstitution. Ne comprend pas poche/solvant/tubulure/administration.","ACV médicament sans DM de reconstitution ajouté.")) -> ACV médicament incluant PA + conditionnement + DM de reconstitution. Ne comprend pas poche/solvant/tubulure/administration.
A79: Micafungine | B79: Flacon 100 mg | C79: flacon verre | D79: Micafungine | E79: 100 | J79: =IFERROR(SUM(E79,G79,I79)/1000,"") -> 0.1 | K79: =$E$4 -> 100 | L79: =IF(J79="","",J79/1000*K79*(1+$E$5/100)) -> 0.0105 | M79: =IF(J79="","",J79/1000*$E$6) -> 9.5e-06 | N79: =IF(C79="ampoule verre",$E$12,IF(C79="poche PEA",$E$13,$E$11)) -> 10 | O79: =IF(C79="ampoule verre",$E$8,IF(C79="poche PEA",$E$9,$E$7)) -> 7.1 | P79: =N79/1000*O79*(1+$E$5/100) -> 0.07455 | Q79: =$E$14 -> 3 | R79: =Q79/1000*$E$10 -> 0.00348 | S79: =IF(J79="","",SUM(L79:M79,P79,R79)) -> 0.0885395 | T79: =IF(OR(J79="",K79=$E$4),"Élevé - FE PA générique",IF(W79<>"","À vérifier","Moyen")) -> Élevé - FE PA générique | U79: Breaking Stab | V79: EcovaMED v0.7 + hypothèses internes explicites | X79: =IF(A79="","",IF(OR(ISNUMBER(SEARCH("poche",C79)),ISNUMBER(SEARCH("ampoule",C79)),ISNUMBER(SEARCH("plastique",C79))),"Prêt à être dilué / administré (hypothèse)","Reconstitution nécessaire (hypothèse)")) -> Reconstitution nécessaire (hypothèse) | Y79: =IF(A79="","",IF(ISNUMBER(SEARCH("Reconstitution",X79)),"Flacon/poudre : ajout par défaut 1 seringue + 1 aiguille ; à revalider selon présentation exacte.","Ampoule/poche/présentation solution : aucun DM de reconstitution ajouté ; DM de perfusion calculés ailleurs.")) -> Flacon/poudre : ajout par défaut 1 seringue + 1 aiguille ; à revalider selon présentation exacte. | Z79: =IF(A79="","",IF(ISNUMBER(SEARCH("Reconstitution",X79)),1,0)) -> 1 | AA79: =IF(Z79>0,"SERINGUE_PP_24ML","") -> SERINGUE_PP_24ML | AB79: =IF(Z79>0,Z79*VLOOKUP(AA79,FACTEURS_ITEMS!$A$3:$J$30,4,FALSE()),0) -> 0.069 | AC79: =IF(A79="","",IF(ISNUMBER(SEARCH("Reconstitution",X79)),1,0)) -> 1 | AD79: =IF(AC79>0,"AIGUILLE_RECONSTITUTION","") -> AIGUILLE_RECONSTITUTION | AE79: =IF(AC79>0,AC79*VLOOKUP(AD79,FACTEURS_ITEMS!$A$3:$J$30,4,FALSE()),0) -> 0.01 | AF79: =IF(A79="","",AB79+AE79) -> 0.079 | AG79: =IF(A79="","",S79+AF79) -> 0.1675395 | AH79: =IF(A79="","",IF(AF79>0,"ACV médicament incluant PA + conditionnement + DM de reconstitution. Ne comprend pas poche/solvant/tubulure/administration.","ACV médicament sans DM de reconstitution ajouté.")) -> ACV médicament incluant PA + conditionnement + DM de reconstitution. Ne comprend pas poche/solvant/tubulure/administration.
A80: Ofloxacine | B80: Poche prêt-à-l’emploi 200 mg | C80: poche PEA | D80: Ofloxacine | E80: 200 | J80: =IFERROR(SUM(E80,G80,I80)/1000,"") -> 0.2 | K80: =$E$4 -> 100 | L80: =IF(J80="","",J80/1000*K80*(1+$E$5/100)) -> 0.021 | M80: =IF(J80="","",J80/1000*$E$6) -> 1.9e-05 | N80: =IF(C80="ampoule verre",$E$12,IF(C80="poche PEA",$E$13,$E$11)) -> 20 | O80: =IF(C80="ampoule verre",$E$8,IF(C80="poche PEA",$E$9,$E$7)) -> 4.2 | P80: =N80/1000*O80*(1+$E$5/100) -> 0.0882 | Q80: =$E$14 -> 3 | R80: =Q80/1000*$E$10 -> 0.00348 | S80: =IF(J80="","",SUM(L80:M80,P80,R80)) -> 0.112699 | T80: =IF(OR(J80="",K80=$E$4),"Élevé - FE PA générique",IF(W80<>"","À vérifier","Moyen")) -> Élevé - FE PA générique | U80: Breaking Stab | V80: EcovaMED v0.7 + hypothèses internes explicites | W80: Présentation prêt-à-l’emploi : le conditionnement primaire réel doit être remplacé par le poids fournisseur si disponible. | X80: =IF(A80="","",IF(OR(ISNUMBER(SEARCH("poche",C80)),ISNUMBER(SEARCH("ampoule",C80)),ISNUMBER(SEARCH("plastique",C80))),"Prêt à être dilué / administré (hypothèse)","Reconstitution nécessaire (hypothèse)")) -> Prêt à être dilué / administré (hypothèse) | Y80: =IF(A80="","",IF(ISNUMBER(SEARCH("Reconstitution",X80)),"Flacon/poudre : ajout par défaut 1 seringue + 1 aiguille ; à revalider selon présentation exacte.","Ampoule/poche/présentation solution : aucun DM de reconstitution ajouté ; DM de perfusion calculés ailleurs.")) -> Ampoule/poche/présentation solution : aucun DM de reconstitution ajouté ; DM de perfusion calculés ailleurs. | Z80: =IF(A80="","",IF(ISNUMBER(SEARCH("Reconstitution",X80)),1,0)) -> 0 | AA80: =IF(Z80>0,"SERINGUE_PP_24ML","") | AB80: =IF(Z80>0,Z80*VLOOKUP(AA80,FACTEURS_ITEMS!$A$3:$J$30,4,FALSE()),0) -> 0 | AC80: =IF(A80="","",IF(ISNUMBER(SEARCH("Reconstitution",X80)),1,0)) -> 0 | AD80: =IF(AC80>0,"AIGUILLE_RECONSTITUTION","") | AE80: =IF(AC80>0,AC80*VLOOKUP(AD80,FACTEURS_ITEMS!$A$3:$J$30,4,FALSE()),0) -> 0 | AF80: =IF(A80="","",AB80+AE80) -> 0 | AG80: =IF(A80="","",S80+AF80) -> 0.112699 | AH80: =IF(A80="","",IF(AF80>0,"ACV médicament incluant PA + conditionnement + DM de reconstitution. Ne comprend pas poche/solvant/tubulure/administration.","ACV médicament sans DM de reconstitution ajouté.")) -> ACV médicament sans DM de reconstitution ajouté.
A81: Oxacilline | B81: Flacon 1 g | C81: flacon verre | D81: Oxacilline | E81: 1000 | J81: =IFERROR(SUM(E81,G81,I81)/1000,"") -> 1 | K81: =$E$4 -> 100 | L81: =IF(J81="","",J81/1000*K81*(1+$E$5/100)) -> 0.105 | M81: =IF(J81="","",J81/1000*$E$6) -> 9.5e-05 | N81: =IF(C81="ampoule verre",$E$12,IF(C81="poche PEA",$E$13,$E$11)) -> 10 | O81: =IF(C81="ampoule verre",$E$8,IF(C81="poche PEA",$E$9,$E$7)) -> 7.1 | P81: =N81/1000*O81*(1+$E$5/100) -> 0.07455 | Q81: =$E$14 -> 3 | R81: =Q81/1000*$E$10 -> 0.00348 | S81: =IF(J81="","",SUM(L81:M81,P81,R81)) -> 0.183125 | T81: =IF(OR(J81="",K81=$E$4),"Élevé - FE PA générique",IF(W81<>"","À vérifier","Moyen")) -> Élevé - FE PA générique | U81: Micrel/Breaking Stab | V81: EcovaMED v0.7 + hypothèses internes explicites | X81: =IF(A81="","",IF(OR(ISNUMBER(SEARCH("poche",C81)),ISNUMBER(SEARCH("ampoule",C81)),ISNUMBER(SEARCH("plastique",C81))),"Prêt à être dilué / administré (hypothèse)","Reconstitution nécessaire (hypothèse)")) -> Reconstitution nécessaire (hypothèse) | Y81: =IF(A81="","",IF(ISNUMBER(SEARCH("Reconstitution",X81)),"Flacon/poudre : ajout par défaut 1 seringue + 1 aiguille ; à revalider selon présentation exacte.","Ampoule/poche/présentation solution : aucun DM de reconstitution ajouté ; DM de perfusion calculés ailleurs.")) -> Flacon/poudre : ajout par défaut 1 seringue + 1 aiguille ; à revalider selon présentation exacte. | Z81: =IF(A81="","",IF(ISNUMBER(SEARCH("Reconstitution",X81)),1,0)) -> 1 | AA81: =IF(Z81>0,"SERINGUE_PP_24ML","") -> SERINGUE_PP_24ML | AB81: =IF(Z81>0,Z81*VLOOKUP(AA81,FACTEURS_ITEMS!$A$3:$J$30,4,FALSE()),0) -> 0.069 | AC81: =IF(A81="","",IF(ISNUMBER(SEARCH("Reconstitution",X81)),1,0)) -> 1 | AD81: =IF(AC81>0,"AIGUILLE_RECONSTITUTION","") -> AIGUILLE_RECONSTITUTION | AE81: =IF(AC81>0,AC81*VLOOKUP(AD81,FACTEURS_ITEMS!$A$3:$J$30,4,FALSE()),0) -> 0.01 | AF81: =IF(A81="","",AB81+AE81) -> 0.079 | AG81: =IF(A81="","",S81+AF81) -> 0.262125 | AH81: =IF(A81="","",IF(AF81>0,"ACV médicament incluant PA + conditionnement + DM de reconstitution. Ne comprend pas poche/solvant/tubulure/administration.","ACV médicament sans DM de reconstitution ajouté.")) -> ACV médicament incluant PA + conditionnement + DM de reconstitution. Ne comprend pas poche/solvant/tubulure/administration.
A82: Oxacilline | B82: Flacon 2 g | C82: flacon verre | D82: Oxacilline | E82: 2000 | J82: =IFERROR(SUM(E82,G82,I82)/1000,"") -> 2 | K82: =$E$4 -> 100 | L82: =IF(J82="","",J82/1000*K82*(1+$E$5/100)) -> 0.21 | M82: =IF(J82="","",J82/1000*$E$6) -> 0.00019 | N82: =IF(C82="ampoule verre",$E$12,IF(C82="poche PEA",$E$13,$E$11)) -> 10 | O82: =IF(C82="ampoule verre",$E$8,IF(C82="poche PEA",$E$9,$E$7)) -> 7.1 | P82: =N82/1000*O82*(1+$E$5/100) -> 0.07455 | Q82: =$E$14 -> 3 | R82: =Q82/1000*$E$10 -> 0.00348 | S82: =IF(J82="","",SUM(L82:M82,P82,R82)) -> 0.28822 | T82: =IF(OR(J82="",K82=$E$4),"Élevé - FE PA générique",IF(W82<>"","À vérifier","Moyen")) -> Élevé - FE PA générique | U82: Micrel/Breaking Stab | V82: EcovaMED v0.7 + hypothèses internes explicites | X82: =IF(A82="","",IF(OR(ISNUMBER(SEARCH("poche",C82)),ISNUMBER(SEARCH("ampoule",C82)),ISNUMBER(SEARCH("plastique",C82))),"Prêt à être dilué / administré (hypothèse)","Reconstitution nécessaire (hypothèse)")) -> Reconstitution nécessaire (hypothèse) | Y82: =IF(A82="","",IF(ISNUMBER(SEARCH("Reconstitution",X82)),"Flacon/poudre : ajout par défaut 1 seringue + 1 aiguille ; à revalider selon présentation exacte.","Ampoule/poche/présentation solution : aucun DM de reconstitution ajouté ; DM de perfusion calculés ailleurs.")) -> Flacon/poudre : ajout par défaut 1 seringue + 1 aiguille ; à revalider selon présentation exacte. | Z82: =IF(A82="","",IF(ISNUMBER(SEARCH("Reconstitution",X82)),1,0)) -> 1 | AA82: =IF(Z82>0,"SERINGUE_PP_24ML","") -> SERINGUE_PP_24ML | AB82: =IF(Z82>0,Z82*VLOOKUP(AA82,FACTEURS_ITEMS!$A$3:$J$30,4,FALSE()),0) -> 0.069 | AC82: =IF(A82="","",IF(ISNUMBER(SEARCH("Reconstitution",X82)),1,0)) -> 1 | AD82: =IF(AC82>0,"AIGUILLE_RECONSTITUTION","") -> AIGUILLE_RECONSTITUTION | AE82: =IF(AC82>0,AC82*VLOOKUP(AD82,FACTEURS_ITEMS!$A$3:$J$30,4,FALSE()),0) -> 0.01 | AF82: =IF(A82="","",AB82+AE82) -> 0.079 | AG82: =IF(A82="","",S82+AF82) -> 0.36722 | AH82: =IF(A82="","",IF(AF82>0,"ACV médicament incluant PA + conditionnement + DM de reconstitution. Ne comprend pas poche/solvant/tubulure/administration.","ACV médicament sans DM de reconstitution ajouté.")) -> ACV médicament incluant PA + conditionnement + DM de reconstitution. Ne comprend pas poche/solvant/tubulure/administration.
A83: Pipéracilline | B83: Flacon 2 g | C83: flacon verre | D83: Pipéracilline | E83: 2000 | J83: =IFERROR(SUM(E83,G83,I83)/1000,"") -> 2 | K83: =$E$4 -> 100 | L83: =IF(J83="","",J83/1000*K83*(1+$E$5/100)) -> 0.21 | M83: =IF(J83="","",J83/1000*$E$6) -> 0.00019 | N83: =IF(C83="ampoule verre",$E$12,IF(C83="poche PEA",$E$13,$E$11)) -> 10 | O83: =IF(C83="ampoule verre",$E$8,IF(C83="poche PEA",$E$9,$E$7)) -> 7.1 | P83: =N83/1000*O83*(1+$E$5/100) -> 0.07455 | Q83: =$E$14 -> 3 | R83: =Q83/1000*$E$10 -> 0.00348 | S83: =IF(J83="","",SUM(L83:M83,P83,R83)) -> 0.28822 | T83: =IF(OR(J83="",K83=$E$4),"Élevé - FE PA générique",IF(W83<>"","À vérifier","Moyen")) -> Élevé - FE PA générique | U83: Micrel/Breaking Stab | V83: EcovaMED v0.7 + hypothèses internes explicites | X83: =IF(A83="","",IF(OR(ISNUMBER(SEARCH("poche",C83)),ISNUMBER(SEARCH("ampoule",C83)),ISNUMBER(SEARCH("plastique",C83))),"Prêt à être dilué / administré (hypothèse)","Reconstitution nécessaire (hypothèse)")) -> Reconstitution nécessaire (hypothèse) | Y83: =IF(A83="","",IF(ISNUMBER(SEARCH("Reconstitution",X83)),"Flacon/poudre : ajout par défaut 1 seringue + 1 aiguille ; à revalider selon présentation exacte.","Ampoule/poche/présentation solution : aucun DM de reconstitution ajouté ; DM de perfusion calculés ailleurs.")) -> Flacon/poudre : ajout par défaut 1 seringue + 1 aiguille ; à revalider selon présentation exacte. | Z83: =IF(A83="","",IF(ISNUMBER(SEARCH("Reconstitution",X83)),1,0)) -> 1 | AA83: =IF(Z83>0,"SERINGUE_PP_24ML","") -> SERINGUE_PP_24ML | AB83: =IF(Z83>0,Z83*VLOOKUP(AA83,FACTEURS_ITEMS!$A$3:$J$30,4,FALSE()),0) -> 0.069 | AC83: =IF(A83="","",IF(ISNUMBER(SEARCH("Reconstitution",X83)),1,0)) -> 1 | AD83: =IF(AC83>0,"AIGUILLE_RECONSTITUTION","") -> AIGUILLE_RECONSTITUTION | AE83: =IF(AC83>0,AC83*VLOOKUP(AD83,FACTEURS_ITEMS!$A$3:$J$30,4,FALSE()),0) -> 0.01 | AF83: =IF(A83="","",AB83+AE83) -> 0.079 | AG83: =IF(A83="","",S83+AF83) -> 0.36722 | AH83: =IF(A83="","",IF(AF83>0,"ACV médicament incluant PA + conditionnement + DM de reconstitution. Ne comprend pas poche/solvant/tubulure/administration.","ACV médicament sans DM de reconstitution ajouté.")) -> ACV médicament incluant PA + conditionnement + DM de reconstitution. Ne comprend pas poche/solvant/tubulure/administration.
A84: Pipéracilline | B84: Flacon 4 g | C84: flacon verre | D84: Pipéracilline | E84: 4000 | J84: =IFERROR(SUM(E84,G84,I84)/1000,"") -> 4 | K84: =$E$4 -> 100 | L84: =IF(J84="","",J84/1000*K84*(1+$E$5/100)) -> 0.42 | M84: =IF(J84="","",J84/1000*$E$6) -> 0.00038 | N84: =IF(C84="ampoule verre",$E$12,IF(C84="poche PEA",$E$13,$E$11)) -> 10 | O84: =IF(C84="ampoule verre",$E$8,IF(C84="poche PEA",$E$9,$E$7)) -> 7.1 | P84: =N84/1000*O84*(1+$E$5/100) -> 0.07455 | Q84: =$E$14 -> 3 | R84: =Q84/1000*$E$10 -> 0.00348 | S84: =IF(J84="","",SUM(L84:M84,P84,R84)) -> 0.49841 | T84: =IF(OR(J84="",K84=$E$4),"Élevé - FE PA générique",IF(W84<>"","À vérifier","Moyen")) -> Élevé - FE PA générique | U84: Micrel/Breaking Stab | V84: EcovaMED v0.7 + hypothèses internes explicites | X84: =IF(A84="","",IF(OR(ISNUMBER(SEARCH("poche",C84)),ISNUMBER(SEARCH("ampoule",C84)),ISNUMBER(SEARCH("plastique",C84))),"Prêt à être dilué / administré (hypothèse)","Reconstitution nécessaire (hypothèse)")) -> Reconstitution nécessaire (hypothèse) | Y84: =IF(A84="","",IF(ISNUMBER(SEARCH("Reconstitution",X84)),"Flacon/poudre : ajout par défaut 1 seringue + 1 aiguille ; à revalider selon présentation exacte.","Ampoule/poche/présentation solution : aucun DM de reconstitution ajouté ; DM de perfusion calculés ailleurs.")) -> Flacon/poudre : ajout par défaut 1 seringue + 1 aiguille ; à revalider selon présentation exacte. | Z84: =IF(A84="","",IF(ISNUMBER(SEARCH("Reconstitution",X84)),1,0)) -> 1 | AA84: =IF(Z84>0,"SERINGUE_PP_24ML","") -> SERINGUE_PP_24ML | AB84: =IF(Z84>0,Z84*VLOOKUP(AA84,FACTEURS_ITEMS!$A$3:$J$30,4,FALSE()),0) -> 0.069 | AC84: =IF(A84="","",IF(ISNUMBER(SEARCH("Reconstitution",X84)),1,0)) -> 1 | AD84: =IF(AC84>0,"AIGUILLE_RECONSTITUTION","") -> AIGUILLE_RECONSTITUTION | AE84: =IF(AC84>0,AC84*VLOOKUP(AD84,FACTEURS_ITEMS!$A$3:$J$30,4,FALSE()),0) -> 0.01 | AF84: =IF(A84="","",AB84+AE84) -> 0.079 | AG84: =IF(A84="","",S84+AF84) -> 0.57741 | AH84: =IF(A84="","",IF(AF84>0,"ACV médicament incluant PA + conditionnement + DM de reconstitution. Ne comprend pas poche/solvant/tubulure/administration.","ACV médicament sans DM de reconstitution ajouté.")) -> ACV médicament incluant PA + conditionnement + DM de reconstitution. Ne comprend pas poche/solvant/tubulure/administration.
A85: Pipéracilline/tazobactam | B85: Flacon 2 g/250 mg | C85: flacon verre | D85: Pipéracilline | E85: 2000 | F85: Tazobactam | G85: 250 | J85: =IFERROR(SUM(E85,G85,I85)/1000,"") -> 2.25 | K85: =$E$4 -> 100 | L85: =IF(J85="","",J85/1000*K85*(1+$E$5/100)) -> 0.23625 | M85: =IF(J85="","",J85/1000*$E$6) -> 0.00021375 | N85: =IF(C85="ampoule verre",$E$12,IF(C85="poche PEA",$E$13,$E$11)) -> 10 | O85: =IF(C85="ampoule verre",$E$8,IF(C85="poche PEA",$E$9,$E$7)) -> 7.1 | P85: =N85/1000*O85*(1+$E$5/100) -> 0.07455 | Q85: =$E$14 -> 3 | R85: =Q85/1000*$E$10 -> 0.00348 | S85: =IF(J85="","",SUM(L85:M85,P85,R85)) -> 0.31449375 | T85: =IF(OR(J85="",K85=$E$4),"Élevé - FE PA générique",IF(W85<>"","À vérifier","Moyen")) -> Élevé - FE PA générique | U85: Breaking Stab | V85: EcovaMED v0.7 + hypothèses internes explicites | X85: =IF(A85="","",IF(OR(ISNUMBER(SEARCH("poche",C85)),ISNUMBER(SEARCH("ampoule",C85)),ISNUMBER(SEARCH("plastique",C85))),"Prêt à être dilué / administré (hypothèse)","Reconstitution nécessaire (hypothèse)")) -> Reconstitution nécessaire (hypothèse) | Y85: =IF(A85="","",IF(ISNUMBER(SEARCH("Reconstitution",X85)),"Flacon/poudre : ajout par défaut 1 seringue + 1 aiguille ; à revalider selon présentation exacte.","Ampoule/poche/présentation solution : aucun DM de reconstitution ajouté ; DM de perfusion calculés ailleurs.")) -> Flacon/poudre : ajout par défaut 1 seringue + 1 aiguille ; à revalider selon présentation exacte. | Z85: =IF(A85="","",IF(ISNUMBER(SEARCH("Reconstitution",X85)),1,0)) -> 1 | AA85: =IF(Z85>0,"SERINGUE_PP_24ML","") -> SERINGUE_PP_24ML | AB85: =IF(Z85>0,Z85*VLOOKUP(AA85,FACTEURS_ITEMS!$A$3:$J$30,4,FALSE()),0) -> 0.069 | AC85: =IF(A85="","",IF(ISNUMBER(SEARCH("Reconstitution",X85)),1,0)) -> 1 | AD85: =IF(AC85>0,"AIGUILLE_RECONSTITUTION","") -> AIGUILLE_RECONSTITUTION | AE85: =IF(AC85>0,AC85*VLOOKUP(AD85,FACTEURS_ITEMS!$A$3:$J$30,4,FALSE()),0) -> 0.01 | AF85: =IF(A85="","",AB85+AE85) -> 0.079 | AG85: =IF(A85="","",S85+AF85) -> 0.39349375 | AH85: =IF(A85="","",IF(AF85>0,"ACV médicament incluant PA + conditionnement + DM de reconstitution. Ne comprend pas poche/solvant/tubulure/administration.","ACV médicament sans DM de reconstitution ajouté.")) -> ACV médicament incluant PA + conditionnement + DM de reconstitution. Ne comprend pas poche/solvant/tubulure/administration.
A86: Pipéracilline/tazobactam | B86: Flacon 4 g/500 mg | C86: flacon verre | D86: Pipéracilline | E86: 4000 | F86: Tazobactam | G86: 500 | J86: =IFERROR(SUM(E86,G86,I86)/1000,"") -> 4.5 | K86: =$E$4 -> 100 | L86: =IF(J86="","",J86/1000*K86*(1+$E$5/100)) -> 0.4725 | M86: =IF(J86="","",J86/1000*$E$6) -> 0.0004275 | N86: =IF(C86="ampoule verre",$E$12,IF(C86="poche PEA",$E$13,$E$11)) -> 10 | O86: =IF(C86="ampoule verre",$E$8,IF(C86="poche PEA",$E$9,$E$7)) -> 7.1 | P86: =N86/1000*O86*(1+$E$5/100) -> 0.07455 | Q86: =$E$14 -> 3 | R86: =Q86/1000*$E$10 -> 0.00348 | S86: =IF(J86="","",SUM(L86:M86,P86,R86)) -> 0.5509575 | T86: =IF(OR(J86="",K86=$E$4),"Élevé - FE PA générique",IF(W86<>"","À vérifier","Moyen")) -> Élevé - FE PA générique | U86: Breaking Stab | V86: EcovaMED v0.7 + hypothèses internes explicites | X86: =IF(A86="","",IF(OR(ISNUMBER(SEARCH("poche",C86)),ISNUMBER(SEARCH("ampoule",C86)),ISNUMBER(SEARCH("plastique",C86))),"Prêt à être dilué / administré (hypothèse)","Reconstitution nécessaire (hypothèse)")) -> Reconstitution nécessaire (hypothèse) | Y86: =IF(A86="","",IF(ISNUMBER(SEARCH("Reconstitution",X86)),"Flacon/poudre : ajout par défaut 1 seringue + 1 aiguille ; à revalider selon présentation exacte.","Ampoule/poche/présentation solution : aucun DM de reconstitution ajouté ; DM de perfusion calculés ailleurs.")) -> Flacon/poudre : ajout par défaut 1 seringue + 1 aiguille ; à revalider selon présentation exacte. | Z86: =IF(A86="","",IF(ISNUMBER(SEARCH("Reconstitution",X86)),1,0)) -> 1 | AA86: =IF(Z86>0,"SERINGUE_PP_24ML","") -> SERINGUE_PP_24ML | AB86: =IF(Z86>0,Z86*VLOOKUP(AA86,FACTEURS_ITEMS!$A$3:$J$30,4,FALSE()),0) -> 0.069 | AC86: =IF(A86="","",IF(ISNUMBER(SEARCH("Reconstitution",X86)),1,0)) -> 1 | AD86: =IF(AC86>0,"AIGUILLE_RECONSTITUTION","") -> AIGUILLE_RECONSTITUTION | AE86: =IF(AC86>0,AC86*VLOOKUP(AD86,FACTEURS_ITEMS!$A$3:$J$30,4,FALSE()),0) -> 0.01 | AF86: =IF(A86="","",AB86+AE86) -> 0.079 | AG86: =IF(A86="","",S86+AF86) -> 0.6299575 | AH86: =IF(A86="","",IF(AF86>0,"ACV médicament incluant PA + conditionnement + DM de reconstitution. Ne comprend pas poche/solvant/tubulure/administration.","ACV médicament sans DM de reconstitution ajouté.")) -> ACV médicament incluant PA + conditionnement + DM de reconstitution. Ne comprend pas poche/solvant/tubulure/administration.
A87: Rifampicine IV | B87: Flacon 600 mg | C87: flacon verre | D87: Rifampicine | E87: 600 | J87: =IFERROR(SUM(E87,G87,I87)/1000,"") -> 0.6 | K87: =$E$4 -> 100 | L87: =IF(J87="","",J87/1000*K87*(1+$E$5/100)) -> 0.063 | M87: =IF(J87="","",J87/1000*$E$6) -> 5.7e-05 | N87: =IF(C87="ampoule verre",$E$12,IF(C87="poche PEA",$E$13,$E$11)) -> 10 | O87: =IF(C87="ampoule verre",$E$8,IF(C87="poche PEA",$E$9,$E$7)) -> 7.1 | P87: =N87/1000*O87*(1+$E$5/100) -> 0.07455 | Q87: =$E$14 -> 3 | R87: =Q87/1000*$E$10 -> 0.00348 | S87: =IF(J87="","",SUM(L87:M87,P87,R87)) -> 0.141087 | T87: =IF(OR(J87="",K87=$E$4),"Élevé - FE PA générique",IF(W87<>"","À vérifier","Moyen")) -> Élevé - FE PA générique | U87: Breaking Stab | V87: EcovaMED v0.7 + hypothèses internes explicites | X87: =IF(A87="","",IF(OR(ISNUMBER(SEARCH("poche",C87)),ISNUMBER(SEARCH("ampoule",C87)),ISNUMBER(SEARCH("plastique",C87))),"Prêt à être dilué / administré (hypothèse)","Reconstitution nécessaire (hypothèse)")) -> Reconstitution nécessaire (hypothèse) | Y87: =IF(A87="","",IF(ISNUMBER(SEARCH("Reconstitution",X87)),"Flacon/poudre : ajout par défaut 1 seringue + 1 aiguille ; à revalider selon présentation exacte.","Ampoule/poche/présentation solution : aucun DM de reconstitution ajouté ; DM de perfusion calculés ailleurs.")) -> Flacon/poudre : ajout par défaut 1 seringue + 1 aiguille ; à revalider selon présentation exacte. | Z87: =IF(A87="","",IF(ISNUMBER(SEARCH("Reconstitution",X87)),1,0)) -> 1 | AA87: =IF(Z87>0,"SERINGUE_PP_24ML","") -> SERINGUE_PP_24ML | AB87: =IF(Z87>0,Z87*VLOOKUP(AA87,FACTEURS_ITEMS!$A$3:$J$30,4,FALSE()),0) -> 0.069 | AC87: =IF(A87="","",IF(ISNUMBER(SEARCH("Reconstitution",X87)),1,0)) -> 1 | AD87: =IF(AC87>0,"AIGUILLE_RECONSTITUTION","") -> AIGUILLE_RECONSTITUTION | AE87: =IF(AC87>0,AC87*VLOOKUP(AD87,FACTEURS_ITEMS!$A$3:$J$30,4,FALSE()),0) -> 0.01 | AF87: =IF(A87="","",AB87+AE87) -> 0.079 | AG87: =IF(A87="","",S87+AF87) -> 0.220087 | AH87: =IF(A87="","",IF(AF87>0,"ACV médicament incluant PA + conditionnement + DM de reconstitution. Ne comprend pas poche/solvant/tubulure/administration.","ACV médicament sans DM de reconstitution ajouté.")) -> ACV médicament incluant PA + conditionnement + DM de reconstitution. Ne comprend pas poche/solvant/tubulure/administration.
A88: Spiramycine | B88: Flacon 1,5 MUI | C88: flacon verre | D88: Spiramycine | E88: 500 | J88: =IFERROR(SUM(E88,G88,I88)/1000,"") -> 0.5 | K88: =$E$4 -> 100 | L88: =IF(J88="","",J88/1000*K88*(1+$E$5/100)) -> 0.0525 | M88: =IF(J88="","",J88/1000*$E$6) -> 4.75e-05 | N88: =IF(C88="ampoule verre",$E$12,IF(C88="poche PEA",$E$13,$E$11)) -> 10 | O88: =IF(C88="ampoule verre",$E$8,IF(C88="poche PEA",$E$9,$E$7)) -> 7.1 | P88: =N88/1000*O88*(1+$E$5/100) -> 0.07455 | Q88: =$E$14 -> 3 | R88: =Q88/1000*$E$10 -> 0.00348 | S88: =IF(J88="","",SUM(L88:M88,P88,R88)) -> 0.1305775 | T88: =IF(OR(J88="",K88=$E$4),"Élevé - FE PA générique",IF(W88<>"","À vérifier","Moyen")) -> Élevé - FE PA générique | U88: Breaking Stab ; masse PA à compléter | V88: EcovaMED v0.7 + hypothèses internes explicites | W88: Masse PA estimée : 1 MUI ≈ 333 mg selon Pharmacopée Européenne. À revalider. | X88: =IF(A88="","",IF(OR(ISNUMBER(SEARCH("poche",C88)),ISNUMBER(SEARCH("ampoule",C88)),ISNUMBER(SEARCH("plastique",C88))),"Prêt à être dilué / administré (hypothèse)","Reconstitution nécessaire (hypothèse)")) -> Reconstitution nécessaire (hypothèse) | Y88: =IF(A88="","",IF(ISNUMBER(SEARCH("Reconstitution",X88)),"Flacon/poudre : ajout par défaut 1 seringue + 1 aiguille ; à revalider selon présentation exacte.","Ampoule/poche/présentation solution : aucun DM de reconstitution ajouté ; DM de perfusion calculés ailleurs.")) -> Flacon/poudre : ajout par défaut 1 seringue + 1 aiguille ; à revalider selon présentation exacte. | Z88: =IF(A88="","",IF(ISNUMBER(SEARCH("Reconstitution",X88)),1,0)) -> 1 | AA88: =IF(Z88>0,"SERINGUE_PP_24ML","") -> SERINGUE_PP_24ML | AB88: =IF(Z88>0,Z88*VLOOKUP(AA88,FACTEURS_ITEMS!$A$3:$J$30,4,FALSE()),0) -> 0.069 | AC88: =IF(A88="","",IF(ISNUMBER(SEARCH("Reconstitution",X88)),1,0)) -> 1 | AD88: =IF(AC88>0,"AIGUILLE_RECONSTITUTION","") -> AIGUILLE_RECONSTITUTION | AE88: =IF(AC88>0,AC88*VLOOKUP(AD88,FACTEURS_ITEMS!$A$3:$J$30,4,FALSE()),0) -> 0.01 | AF88: =IF(A88="","",AB88+AE88) -> 0.079 | AG88: =IF(A88="","",S88+AF88) -> 0.2095775 | AH88: =IF(A88="","",IF(AF88>0,"ACV médicament incluant PA + conditionnement + DM de reconstitution. Ne comprend pas poche/solvant/tubulure/administration.","ACV médicament sans DM de reconstitution ajouté.")) -> ACV médicament incluant PA + conditionnement + DM de reconstitution. Ne comprend pas poche/solvant/tubulure/administration.
A89: Spiramycine | B89: Flacon 3 MUI | C89: flacon verre | D89: Spiramycine | E89: 1000 | J89: =IFERROR(SUM(E89,G89,I89)/1000,"") -> 1 | K89: =$E$4 -> 100 | L89: =IF(J89="","",J89/1000*K89*(1+$E$5/100)) -> 0.105 | M89: =IF(J89="","",J89/1000*$E$6) -> 9.5e-05 | N89: =IF(C89="ampoule verre",$E$12,IF(C89="poche PEA",$E$13,$E$11)) -> 10 | O89: =IF(C89="ampoule verre",$E$8,IF(C89="poche PEA",$E$9,$E$7)) -> 7.1 | P89: =N89/1000*O89*(1+$E$5/100) -> 0.07455 | Q89: =$E$14 -> 3 | R89: =Q89/1000*$E$10 -> 0.00348 | S89: =IF(J89="","",SUM(L89:M89,P89,R89)) -> 0.183125 | T89: =IF(OR(J89="",K89=$E$4),"Élevé - FE PA générique",IF(W89<>"","À vérifier","Moyen")) -> Élevé - FE PA générique | U89: Breaking Stab ; masse PA à compléter | V89: EcovaMED v0.7 + hypothèses internes explicites | W89: Masse PA estimée : 1 MUI ≈ 333 mg selon Pharmacopée Européenne. À revalider. | X89: =IF(A89="","",IF(OR(ISNUMBER(SEARCH("poche",C89)),ISNUMBER(SEARCH("ampoule",C89)),ISNUMBER(SEARCH("plastique",C89))),"Prêt à être dilué / administré (hypothèse)","Reconstitution nécessaire (hypothèse)")) -> Reconstitution nécessaire (hypothèse) | Y89: =IF(A89="","",IF(ISNUMBER(SEARCH("Reconstitution",X89)),"Flacon/poudre : ajout par défaut 1 seringue + 1 aiguille ; à revalider selon présentation exacte.","Ampoule/poche/présentation solution : aucun DM de reconstitution ajouté ; DM de perfusion calculés ailleurs.")) -> Flacon/poudre : ajout par défaut 1 seringue + 1 aiguille ; à revalider selon présentation exacte. | Z89: =IF(A89="","",IF(ISNUMBER(SEARCH("Reconstitution",X89)),1,0)) -> 1 | AA89: =IF(Z89>0,"SERINGUE_PP_24ML","") -> SERINGUE_PP_24ML | AB89: =IF(Z89>0,Z89*VLOOKUP(AA89,FACTEURS_ITEMS!$A$3:$J$30,4,FALSE()),0) -> 0.069 | AC89: =IF(A89="","",IF(ISNUMBER(SEARCH("Reconstitution",X89)),1,0)) -> 1 | AD89: =IF(AC89>0,"AIGUILLE_RECONSTITUTION","") -> AIGUILLE_RECONSTITUTION | AE89: =IF(AC89>0,AC89*VLOOKUP(AD89,FACTEURS_ITEMS!$A$3:$J$30,4,FALSE()),0) -> 0.01 | AF89: =IF(A89="","",AB89+AE89) -> 0.079 | AG89: =IF(A89="","",S89+AF89) -> 0.262125 | AH89: =IF(A89="","",IF(AF89>0,"ACV médicament incluant PA + conditionnement + DM de reconstitution. Ne comprend pas poche/solvant/tubulure/administration.","ACV médicament sans DM de reconstitution ajouté.")) -> ACV médicament incluant PA + conditionnement + DM de reconstitution. Ne comprend pas poche/solvant/tubulure/administration.
A90: Tedizolide | B90: Flacon 200 mg | C90: flacon verre | D90: Tedizolide | E90: 200 | J90: =IFERROR(SUM(E90,G90,I90)/1000,"") -> 0.2 | K90: =$E$4 -> 100 | L90: =IF(J90="","",J90/1000*K90*(1+$E$5/100)) -> 0.021 | M90: =IF(J90="","",J90/1000*$E$6) -> 1.9e-05 | N90: =IF(C90="ampoule verre",$E$12,IF(C90="poche PEA",$E$13,$E$11)) -> 10 | O90: =IF(C90="ampoule verre",$E$8,IF(C90="poche PEA",$E$9,$E$7)) -> 7.1 | P90: =N90/1000*O90*(1+$E$5/100) -> 0.07455 | Q90: =$E$14 -> 3 | R90: =Q90/1000*$E$10 -> 0.00348 | S90: =IF(J90="","",SUM(L90:M90,P90,R90)) -> 0.099049 | T90: =IF(OR(J90="",K90=$E$4),"Élevé - FE PA générique",IF(W90<>"","À vérifier","Moyen")) -> Élevé - FE PA générique | U90: Breaking Stab | V90: EcovaMED v0.7 + hypothèses internes explicites | X90: =IF(A90="","",IF(OR(ISNUMBER(SEARCH("poche",C90)),ISNUMBER(SEARCH("ampoule",C90)),ISNUMBER(SEARCH("plastique",C90))),"Prêt à être dilué / administré (hypothèse)","Reconstitution nécessaire (hypothèse)")) -> Reconstitution nécessaire (hypothèse) | Y90: =IF(A90="","",IF(ISNUMBER(SEARCH("Reconstitution",X90)),"Flacon/poudre : ajout par défaut 1 seringue + 1 aiguille ; à revalider selon présentation exacte.","Ampoule/poche/présentation solution : aucun DM de reconstitution ajouté ; DM de perfusion calculés ailleurs.")) -> Flacon/poudre : ajout par défaut 1 seringue + 1 aiguille ; à revalider selon présentation exacte. | Z90: =IF(A90="","",IF(ISNUMBER(SEARCH("Reconstitution",X90)),1,0)) -> 1 | AA90: =IF(Z90>0,"SERINGUE_PP_24ML","") -> SERINGUE_PP_24ML | AB90: =IF(Z90>0,Z90*VLOOKUP(AA90,FACTEURS_ITEMS!$A$3:$J$30,4,FALSE()),0) -> 0.069 | AC90: =IF(A90="","",IF(ISNUMBER(SEARCH("Reconstitution",X90)),1,0)) -> 1 | AD90: =IF(AC90>0,"AIGUILLE_RECONSTITUTION","") -> AIGUILLE_RECONSTITUTION | AE90: =IF(AC90>0,AC90*VLOOKUP(AD90,FACTEURS_ITEMS!$A$3:$J$30,4,FALSE()),0) -> 0.01 | AF90: =IF(A90="","",AB90+AE90) -> 0.079 | AG90: =IF(A90="","",S90+AF90) -> 0.178049 | AH90: =IF(A90="","",IF(AF90>0,"ACV médicament incluant PA + conditionnement + DM de reconstitution. Ne comprend pas poche/solvant/tubulure/administration.","ACV médicament sans DM de reconstitution ajouté.")) -> ACV médicament incluant PA + conditionnement + DM de reconstitution. Ne comprend pas poche/solvant/tubulure/administration.
A91: Teicoplanine | B91: Flacon 200 mg | C91: flacon verre | D91: Teicoplanine | E91: 200 | J91: =IFERROR(SUM(E91,G91,I91)/1000,"") -> 0.2 | K91: =$E$4 -> 100 | L91: =IF(J91="","",J91/1000*K91*(1+$E$5/100)) -> 0.021 | M91: =IF(J91="","",J91/1000*$E$6) -> 1.9e-05 | N91: =IF(C91="ampoule verre",$E$12,IF(C91="poche PEA",$E$13,$E$11)) -> 10 | O91: =IF(C91="ampoule verre",$E$8,IF(C91="poche PEA",$E$9,$E$7)) -> 7.1 | P91: =N91/1000*O91*(1+$E$5/100) -> 0.07455 | Q91: =$E$14 -> 3 | R91: =Q91/1000*$E$10 -> 0.00348 | S91: =IF(J91="","",SUM(L91:M91,P91,R91)) -> 0.099049 | T91: =IF(OR(J91="",K91=$E$4),"Élevé - FE PA générique",IF(W91<>"","À vérifier","Moyen")) -> Élevé - FE PA générique | U91: Breaking Stab | V91: EcovaMED v0.7 + hypothèses internes explicites | X91: =IF(A91="","",IF(OR(ISNUMBER(SEARCH("poche",C91)),ISNUMBER(SEARCH("ampoule",C91)),ISNUMBER(SEARCH("plastique",C91))),"Prêt à être dilué / administré (hypothèse)","Reconstitution nécessaire (hypothèse)")) -> Reconstitution nécessaire (hypothèse) | Y91: =IF(A91="","",IF(ISNUMBER(SEARCH("Reconstitution",X91)),"Flacon/poudre : ajout par défaut 1 seringue + 1 aiguille ; à revalider selon présentation exacte.","Ampoule/poche/présentation solution : aucun DM de reconstitution ajouté ; DM de perfusion calculés ailleurs.")) -> Flacon/poudre : ajout par défaut 1 seringue + 1 aiguille ; à revalider selon présentation exacte. | Z91: =IF(A91="","",IF(ISNUMBER(SEARCH("Reconstitution",X91)),1,0)) -> 1 | AA91: =IF(Z91>0,"SERINGUE_PP_24ML","") -> SERINGUE_PP_24ML | AB91: =IF(Z91>0,Z91*VLOOKUP(AA91,FACTEURS_ITEMS!$A$3:$J$30,4,FALSE()),0) -> 0.069 | AC91: =IF(A91="","",IF(ISNUMBER(SEARCH("Reconstitution",X91)),1,0)) -> 1 | AD91: =IF(AC91>0,"AIGUILLE_RECONSTITUTION","") -> AIGUILLE_RECONSTITUTION | AE91: =IF(AC91>0,AC91*VLOOKUP(AD91,FACTEURS_ITEMS!$A$3:$J$30,4,FALSE()),0) -> 0.01 | AF91: =IF(A91="","",AB91+AE91) -> 0.079 | AG91: =IF(A91="","",S91+AF91) -> 0.178049 | AH91: =IF(A91="","",IF(AF91>0,"ACV médicament incluant PA + conditionnement + DM de reconstitution. Ne comprend pas poche/solvant/tubulure/administration.","ACV médicament sans DM de reconstitution ajouté.")) -> ACV médicament incluant PA + conditionnement + DM de reconstitution. Ne comprend pas poche/solvant/tubulure/administration.
A92: Teicoplanine | B92: Flacon 400 mg | C92: flacon verre | D92: Teicoplanine | E92: 400 | J92: =IFERROR(SUM(E92,G92,I92)/1000,"") -> 0.4 | K92: =$E$4 -> 100 | L92: =IF(J92="","",J92/1000*K92*(1+$E$5/100)) -> 0.042 | M92: =IF(J92="","",J92/1000*$E$6) -> 3.8e-05 | N92: =IF(C92="ampoule verre",$E$12,IF(C92="poche PEA",$E$13,$E$11)) -> 10 | O92: =IF(C92="ampoule verre",$E$8,IF(C92="poche PEA",$E$9,$E$7)) -> 7.1 | P92: =N92/1000*O92*(1+$E$5/100) -> 0.07455 | Q92: =$E$14 -> 3 | R92: =Q92/1000*$E$10 -> 0.00348 | S92: =IF(J92="","",SUM(L92:M92,P92,R92)) -> 0.120068 | T92: =IF(OR(J92="",K92=$E$4),"Élevé - FE PA générique",IF(W92<>"","À vérifier","Moyen")) -> Élevé - FE PA générique | U92: Breaking Stab | V92: EcovaMED v0.7 + hypothèses internes explicites | X92: =IF(A92="","",IF(OR(ISNUMBER(SEARCH("poche",C92)),ISNUMBER(SEARCH("ampoule",C92)),ISNUMBER(SEARCH("plastique",C92))),"Prêt à être dilué / administré (hypothèse)","Reconstitution nécessaire (hypothèse)")) -> Reconstitution nécessaire (hypothèse) | Y92: =IF(A92="","",IF(ISNUMBER(SEARCH("Reconstitution",X92)),"Flacon/poudre : ajout par défaut 1 seringue + 1 aiguille ; à revalider selon présentation exacte.","Ampoule/poche/présentation solution : aucun DM de reconstitution ajouté ; DM de perfusion calculés ailleurs.")) -> Flacon/poudre : ajout par défaut 1 seringue + 1 aiguille ; à revalider selon présentation exacte. | Z92: =IF(A92="","",IF(ISNUMBER(SEARCH("Reconstitution",X92)),1,0)) -> 1 | AA92: =IF(Z92>0,"SERINGUE_PP_24ML","") -> SERINGUE_PP_24ML | AB92: =IF(Z92>0,Z92*VLOOKUP(AA92,FACTEURS_ITEMS!$A$3:$J$30,4,FALSE()),0) -> 0.069 | AC92: =IF(A92="","",IF(ISNUMBER(SEARCH("Reconstitution",X92)),1,0)) -> 1 | AD92: =IF(AC92>0,"AIGUILLE_RECONSTITUTION","") -> AIGUILLE_RECONSTITUTION | AE92: =IF(AC92>0,AC92*VLOOKUP(AD92,FACTEURS_ITEMS!$A$3:$J$30,4,FALSE()),0) -> 0.01 | AF92: =IF(A92="","",AB92+AE92) -> 0.079 | AG92: =IF(A92="","",S92+AF92) -> 0.199068 | AH92: =IF(A92="","",IF(AF92>0,"ACV médicament incluant PA + conditionnement + DM de reconstitution. Ne comprend pas poche/solvant/tubulure/administration.","ACV médicament sans DM de reconstitution ajouté.")) -> ACV médicament incluant PA + conditionnement + DM de reconstitution. Ne comprend pas poche/solvant/tubulure/administration.
A93: Témocilline | B93: Flacon 1 g | C93: flacon verre | D93: Témocilline | E93: 1000 | J93: =IFERROR(SUM(E93,G93,I93)/1000,"") -> 1 | K93: =$E$4 -> 100 | L93: =IF(J93="","",J93/1000*K93*(1+$E$5/100)) -> 0.105 | M93: =IF(J93="","",J93/1000*$E$6) -> 9.5e-05 | N93: =IF(C93="ampoule verre",$E$12,IF(C93="poche PEA",$E$13,$E$11)) -> 10 | O93: =IF(C93="ampoule verre",$E$8,IF(C93="poche PEA",$E$9,$E$7)) -> 7.1 | P93: =N93/1000*O93*(1+$E$5/100) -> 0.07455 | Q93: =$E$14 -> 3 | R93: =Q93/1000*$E$10 -> 0.00348 | S93: =IF(J93="","",SUM(L93:M93,P93,R93)) -> 0.183125 | T93: =IF(OR(J93="",K93=$E$4),"Élevé - FE PA générique",IF(W93<>"","À vérifier","Moyen")) -> Élevé - FE PA générique | U93: Breaking Stab | V93: EcovaMED v0.7 + hypothèses internes explicites | X93: =IF(A93="","",IF(OR(ISNUMBER(SEARCH("poche",C93)),ISNUMBER(SEARCH("ampoule",C93)),ISNUMBER(SEARCH("plastique",C93))),"Prêt à être dilué / administré (hypothèse)","Reconstitution nécessaire (hypothèse)")) -> Reconstitution nécessaire (hypothèse) | Y93: =IF(A93="","",IF(ISNUMBER(SEARCH("Reconstitution",X93)),"Flacon/poudre : ajout par défaut 1 seringue + 1 aiguille ; à revalider selon présentation exacte.","Ampoule/poche/présentation solution : aucun DM de reconstitution ajouté ; DM de perfusion calculés ailleurs.")) -> Flacon/poudre : ajout par défaut 1 seringue + 1 aiguille ; à revalider selon présentation exacte. | Z93: =IF(A93="","",IF(ISNUMBER(SEARCH("Reconstitution",X93)),1,0)) -> 1 | AA93: =IF(Z93>0,"SERINGUE_PP_24ML","") -> SERINGUE_PP_24ML | AB93: =IF(Z93>0,Z93*VLOOKUP(AA93,FACTEURS_ITEMS!$A$3:$J$30,4,FALSE()),0) -> 0.069 | AC93: =IF(A93="","",IF(ISNUMBER(SEARCH("Reconstitution",X93)),1,0)) -> 1 | AD93: =IF(AC93>0,"AIGUILLE_RECONSTITUTION","") -> AIGUILLE_RECONSTITUTION | AE93: =IF(AC93>0,AC93*VLOOKUP(AD93,FACTEURS_ITEMS!$A$3:$J$30,4,FALSE()),0) -> 0.01 | AF93: =IF(A93="","",AB93+AE93) -> 0.079 | AG93: =IF(A93="","",S93+AF93) -> 0.262125 | AH93: =IF(A93="","",IF(AF93>0,"ACV médicament incluant PA + conditionnement + DM de reconstitution. Ne comprend pas poche/solvant/tubulure/administration.","ACV médicament sans DM de reconstitution ajouté.")) -> ACV médicament incluant PA + conditionnement + DM de reconstitution. Ne comprend pas poche/solvant/tubulure/administration.
A94: Témocilline | B94: Flacon 2 g | C94: flacon verre | D94: Témocilline | E94: 2000 | J94: =IFERROR(SUM(E94,G94,I94)/1000,"") -> 2 | K94: =$E$4 -> 100 | L94: =IF(J94="","",J94/1000*K94*(1+$E$5/100)) -> 0.21 | M94: =IF(J94="","",J94/1000*$E$6) -> 0.00019 | N94: =IF(C94="ampoule verre",$E$12,IF(C94="poche PEA",$E$13,$E$11)) -> 10 | O94: =IF(C94="ampoule verre",$E$8,IF(C94="poche PEA",$E$9,$E$7)) -> 7.1 | P94: =N94/1000*O94*(1+$E$5/100) -> 0.07455 | Q94: =$E$14 -> 3 | R94: =Q94/1000*$E$10 -> 0.00348 | S94: =IF(J94="","",SUM(L94:M94,P94,R94)) -> 0.28822 | T94: =IF(OR(J94="",K94=$E$4),"Élevé - FE PA générique",IF(W94<>"","À vérifier","Moyen")) -> Élevé - FE PA générique | U94: Breaking Stab | V94: EcovaMED v0.7 + hypothèses internes explicites | X94: =IF(A94="","",IF(OR(ISNUMBER(SEARCH("poche",C94)),ISNUMBER(SEARCH("ampoule",C94)),ISNUMBER(SEARCH("plastique",C94))),"Prêt à être dilué / administré (hypothèse)","Reconstitution nécessaire (hypothèse)")) -> Reconstitution nécessaire (hypothèse) | Y94: =IF(A94="","",IF(ISNUMBER(SEARCH("Reconstitution",X94)),"Flacon/poudre : ajout par défaut 1 seringue + 1 aiguille ; à revalider selon présentation exacte.","Ampoule/poche/présentation solution : aucun DM de reconstitution ajouté ; DM de perfusion calculés ailleurs.")) -> Flacon/poudre : ajout par défaut 1 seringue + 1 aiguille ; à revalider selon présentation exacte. | Z94: =IF(A94="","",IF(ISNUMBER(SEARCH("Reconstitution",X94)),1,0)) -> 1 | AA94: =IF(Z94>0,"SERINGUE_PP_24ML","") -> SERINGUE_PP_24ML | AB94: =IF(Z94>0,Z94*VLOOKUP(AA94,FACTEURS_ITEMS!$A$3:$J$30,4,FALSE()),0) -> 0.069 | AC94: =IF(A94="","",IF(ISNUMBER(SEARCH("Reconstitution",X94)),1,0)) -> 1 | AD94: =IF(AC94>0,"AIGUILLE_RECONSTITUTION","") -> AIGUILLE_RECONSTITUTION | AE94: =IF(AC94>0,AC94*VLOOKUP(AD94,FACTEURS_ITEMS!$A$3:$J$30,4,FALSE()),0) -> 0.01 | AF94: =IF(A94="","",AB94+AE94) -> 0.079 | AG94: =IF(A94="","",S94+AF94) -> 0.36722 | AH94: =IF(A94="","",IF(AF94>0,"ACV médicament incluant PA + conditionnement + DM de reconstitution. Ne comprend pas poche/solvant/tubulure/administration.","ACV médicament sans DM de reconstitution ajouté.")) -> ACV médicament incluant PA + conditionnement + DM de reconstitution. Ne comprend pas poche/solvant/tubulure/administration.
A95: Ticarcilline | B95: Flacon 1 g | C95: flacon verre | D95: Ticarcilline | E95: 1000 | J95: =IFERROR(SUM(E95,G95,I95)/1000,"") -> 1 | K95: =$E$4 -> 100 | L95: =IF(J95="","",J95/1000*K95*(1+$E$5/100)) -> 0.105 | M95: =IF(J95="","",J95/1000*$E$6) -> 9.5e-05 | N95: =IF(C95="ampoule verre",$E$12,IF(C95="poche PEA",$E$13,$E$11)) -> 10 | O95: =IF(C95="ampoule verre",$E$8,IF(C95="poche PEA",$E$9,$E$7)) -> 7.1 | P95: =N95/1000*O95*(1+$E$5/100) -> 0.07455 | Q95: =$E$14 -> 3 | R95: =Q95/1000*$E$10 -> 0.00348 | S95: =IF(J95="","",SUM(L95:M95,P95,R95)) -> 0.183125 | T95: =IF(OR(J95="",K95=$E$4),"Élevé - FE PA générique",IF(W95<>"","À vérifier","Moyen")) -> Élevé - FE PA générique | U95: Micrel/Breaking Stab | V95: EcovaMED v0.7 + hypothèses internes explicites | X95: =IF(A95="","",IF(OR(ISNUMBER(SEARCH("poche",C95)),ISNUMBER(SEARCH("ampoule",C95)),ISNUMBER(SEARCH("plastique",C95))),"Prêt à être dilué / administré (hypothèse)","Reconstitution nécessaire (hypothèse)")) -> Reconstitution nécessaire (hypothèse) | Y95: =IF(A95="","",IF(ISNUMBER(SEARCH("Reconstitution",X95)),"Flacon/poudre : ajout par défaut 1 seringue + 1 aiguille ; à revalider selon présentation exacte.","Ampoule/poche/présentation solution : aucun DM de reconstitution ajouté ; DM de perfusion calculés ailleurs.")) -> Flacon/poudre : ajout par défaut 1 seringue + 1 aiguille ; à revalider selon présentation exacte. | Z95: =IF(A95="","",IF(ISNUMBER(SEARCH("Reconstitution",X95)),1,0)) -> 1 | AA95: =IF(Z95>0,"SERINGUE_PP_24ML","") -> SERINGUE_PP_24ML | AB95: =IF(Z95>0,Z95*VLOOKUP(AA95,FACTEURS_ITEMS!$A$3:$J$30,4,FALSE()),0) -> 0.069 | AC95: =IF(A95="","",IF(ISNUMBER(SEARCH("Reconstitution",X95)),1,0)) -> 1 | AD95: =IF(AC95>0,"AIGUILLE_RECONSTITUTION","") -> AIGUILLE_RECONSTITUTION | AE95: =IF(AC95>0,AC95*VLOOKUP(AD95,FACTEURS_ITEMS!$A$3:$J$30,4,FALSE()),0) -> 0.01 | AF95: =IF(A95="","",AB95+AE95) -> 0.079 | AG95: =IF(A95="","",S95+AF95) -> 0.262125 | AH95: =IF(A95="","",IF(AF95>0,"ACV médicament incluant PA + conditionnement + DM de reconstitution. Ne comprend pas poche/solvant/tubulure/administration.","ACV médicament sans DM de reconstitution ajouté.")) -> ACV médicament incluant PA + conditionnement + DM de reconstitution. Ne comprend pas poche/solvant/tubulure/administration.
